Workbook

Sheet RESUMEN 2026
D1: SOLO SERVICIO | F1: CON VENTAS EXTRAS
A2: MES 2026 | B2: $ARG/kg SERVICIO | C2: CANTIDA CABEZAS | D2: $ARG POR SERVICIO | E2: $ ARG POR CABEZA | F2: TOTAL OPERACIÓN $ARG | G2: $ARG POR ANIMAL
A3: ENERO | B3: =+AVERAGE(DETALLE!E2:E51) -> 375.8 | C3: =+DETALLE!D52 -> 1021 | D3: =+SUM(DETALLE!G2:G51) -> 84059288 | E3: =+D3/C3 -> 82330.351 | F3: =+DETALLE!I52 -> 86783487 | G3: =+F3/C3 -> 84998.518
A4: FEBRERO | B4: =+AVERAGE(DETALLE!E53:E98) -> 420 | C4: =+DETALLE!D99 -> 815 | D4: =+SUM(DETALLE!G53:G98) -> 76018824 | E4: =+D4/C4 -> 93274.631 | F4: =+DETALLE!I99 -> 80093843 | G4: =+F4/C4 -> 98274.654
A5: MARZO
A6: ABRIL
A7: MAYO
A8: JUNIO
A9: JULIO
A10: AGOSTO
A11: SEPTIEMBRE
A12: OCTUBRE
A13: NOVIEMBRE
A14: DICIEMBRE
A15: TOTAL | C15: =SUM(C3:C14) -> 1836 | D15: =SUM(D3:D14) -> 1.6007811e+08 | E15: =SUM(E3:E14) -> 175604.98 | F15: =SUM(F3:F14) -> 1.6687733e+08 | G15: =SUM(G3:G14) -> 183273.17

Sheet DETALLE
A1: MES 2026 | B1: TROPA | C1: USUARIO | D1: CANTIDAD DE ANIMALES | E1: $/kg SERVICIO S/RECUPERO | F1: KG GANCHO | G1: SERVICIO FAENA | H1: SERVICIO DESPOSTADA | I1: TOTAL OPERACIÓN $ | J1: FACTURA COMPRA MENUDENCIA | K1: FACTURA VENTA MENUDENCIA | L1: VENTA LAVADITO | M1: $ MONTO HUESO | N1: $ MONTO DESPERDICIO | O1: $ MONTO GRASA | P1: $ CUERO | Q1: $ GRASA DREASING
A2: ENERO | B2: =+'SERVICIO FAENA'!A3 -> 1 | C2: =+'SERVICIO FAENA'!B3 -> MORAGA | D2: =+'SERVICIO FAENA'!C3 -> 15 | E2: =+'SERVICIO FAENA'!H3 -> 335 | F2: =+'SERVICIO FAENA'!F3 -> 2940.3 | G2: =+'SERVICIO FAENA'!J3 -> 985000.5 | H2: =+'SERVICIO DESPOSTE'!W3 -> 0 | I2: =+(G2-J2)+K2+M2+N2+O2+P2+Q2+L2+H2 -> 985000.5 | J2: =+MENUDENCIAS!I3 -> 0 | K2: =+MENUDENCIAS!O3 -> 0 | L2: =+'MERCADO INTERNO'!AG4 -> 0 | M2: =+RENDERING!H2 -> 0 | N2: =+RENDERING!F2 -> 0 | O2: =+RENDERING!J2 -> 0 | P2: =+CUEROS!N4 -> 0 | Q2: =+'GRASA DREASING'!G2 -> 0
B3: =+'SERVICIO FAENA'!A4 -> 2 | C3: =+'SERVICIO FAENA'!B4 -> GANADERA NORTE NEUQUINO | D3: =+'SERVICIO FAENA'!C4 -> 43 | E3: =+'SERVICIO FAENA'!H4 -> 335 | F3: =+'SERVICIO FAENA'!F4 -> 9891.8 | G3: =+'SERVICIO FAENA'!J4 -> 3313753 | H3: =+'SERVICIO DESPOSTE'!W4 -> 0 | I3: =+(G3-J3)+K3+M3+N3+O3+P3+Q3+L3+H3 -> 3313753 | J3: =+MENUDENCIAS!I4 -> 0 | K3: =+MENUDENCIAS!O4 -> 0 | L3: =+'MERCADO INTERNO'!AG5 -> 0 | M3: =+RENDERING!H3 -> 0 | N3: =+RENDERING!F3 -> 0 | O3: =+RENDERING!J3 -> 0 | P3: =+CUEROS!N5 -> 0 | Q3: =+'GRASA DREASING'!G3 -> 0
B4: =+'SERVICIO FAENA'!A5 -> 3 | C4: =+'SERVICIO FAENA'!B5 -> GANADERA NORTE NEUQUINO | D4: =+'SERVICIO FAENA'!C5 -> 40 | E4: =+'SERVICIO FAENA'!H5 -> 335 | F4: =+'SERVICIO FAENA'!F5 -> 8567.8 | G4: =+'SERVICIO FAENA'!J5 -> 2870213 | H4: =+'SERVICIO DESPOSTE'!W5 -> 0 | I4: =+(G4-J4)+K4+M4+N4+O4+P4+Q4+L4+H4 -> 2870213 | J4: =+MENUDENCIAS!I5 -> 0 | K4: =+MENUDENCIAS!O5 -> 0 | L4: =+'MERCADO INTERNO'!AG6 -> 0 | M4: =+RENDERING!H4 -> 0 | N4: =+RENDERING!F4 -> 0 | O4: =+RENDERING!J4 -> 0 | P4: =+CUEROS!N6 -> 0 | Q4: =+'GRASA DREASING'!G4 -> 0
B5: =+'SERVICIO FAENA'!A6 -> 4 | C5: =+'SERVICIO FAENA'!B6 -> DOS DE FIERRO SA | D5: =+'SERVICIO FAENA'!C6 -> 25 | E5: =+'SERVICIO FAENA'!H6 -> 335 | F5: =+'SERVICIO FAENA'!F6 -> 5030.4 | G5: =+'SERVICIO FAENA'!J6 -> 1685184 | H5: =+'SERVICIO DESPOSTE'!W6 -> 0 | I5: =+(G5-J5)+K5+M5+N5+O5+P5+Q5+L5+H5 -> 1685184 | J5: =+MENUDENCIAS!I6 -> 0 | K5: =+MENUDENCIAS!O6 -> 0 | L5: =+'MERCADO INTERNO'!AG7 -> 0 | M5: =+RENDERING!H5 -> 0 | N5: =+RENDERING!F5 -> 0 | O5: =+RENDERING!J5 -> 0 | P5: =+CUEROS!N7 -> 0 | Q5: =+'GRASA DREASING'!G5 -> 0
B6: =+'SERVICIO FAENA'!A7 -> 5 | C6: =+'SERVICIO FAENA'!B7 -> DISTRIBUIDORA DE LA PATAGONIA | D6: =+'SERVICIO FAENA'!C7 -> 30 | E6: =+'SERVICIO FAENA'!H7 -> 335 | F6: =+'SERVICIO FAENA'!F7 -> 6743.3 | G6: =+'SERVICIO FAENA'!J7 -> 2259005.5 | H6: =+'SERVICIO DESPOSTE'!W7 -> 0 | I6: =+(G6-J6)+K6+M6+N6+O6+P6+Q6+L6+H6 -> 2259005.5 | J6: =+MENUDENCIAS!I7 -> 0 | K6: =+MENUDENCIAS!O7 -> 0 | L6: =+'MERCADO INTERNO'!AG8 -> 0 | M6: =+RENDERING!H6 -> 0 | N6: =+RENDERING!F6 -> 0 | O6: =+RENDERING!J6 -> 0 | P6: =+CUEROS!N8 -> 0 | Q6: =+'GRASA DREASING'!G6 -> 0
B7: =+'SERVICIO FAENA'!A8 -> 6 | C7: =+'SERVICIO FAENA'!B8 -> DISTRIBUIDORA DE LA PATAGONIA | D7: =+'SERVICIO FAENA'!C8 -> 15 | E7: =+'SERVICIO FAENA'!H8 -> 335 | F7: =+'SERVICIO FAENA'!F8 -> 3075.2 | G7: =+'SERVICIO FAENA'!J8 -> 1030192 | H7: =+'SERVICIO DESPOSTE'!W8 -> 0 | I7: =+(G7-J7)+K7+M7+N7+O7+P7+Q7+L7+H7 -> 1030192 | J7: =+MENUDENCIAS!I8 -> 0 | K7: =+MENUDENCIAS!O8 -> 0 | L7: =+'MERCADO INTERNO'!AG9 -> 0 | M7: =+RENDERING!H7 -> 0 | N7: =+RENDERING!F7 -> 0 | O7: =+RENDERING!J7 -> 0 | P7: =+CUEROS!N9 -> 0 | Q7: =+'GRASA DREASING'!G7 -> 0
B8: =+'SERVICIO FAENA'!A9 -> 7 | C8: =+'SERVICIO FAENA'!B9 -> MUCA SAS | D8: =+'SERVICIO FAENA'!C9 -> 35 | E8: =+'SERVICIO FAENA'!H9 -> 335 | F8: =+'SERVICIO FAENA'!F9 -> 10641.5 | G8: =+'SERVICIO FAENA'!J9 -> 3564902.5 | H8: =+'SERVICIO DESPOSTE'!W9 -> 0 | I8: =+(G8-J8)+K8+M8+N8+O8+P8+Q8+L8+H8 -> 3564902.5 | J8: =+MENUDENCIAS!I9 -> 0 | K8: =+MENUDENCIAS!O9 -> 0 | L8: =+'MERCADO INTERNO'!AG10 -> 0 | M8: =+RENDERING!H8 -> 0 | N8: =+RENDERING!F8 -> 0 | O8: =+RENDERING!J8 -> 0 | P8: =+CUEROS!N10 -> 0 | Q8: =+'GRASA DREASING'!G8 -> 0
B9: =+'SERVICIO FAENA'!A10 -> 8 | C9: =+'SERVICIO FAENA'!B10 -> MUCA SAS | D9: =+'SERVICIO FAENA'!C10 -> 5 | E9: =+'SERVICIO FAENA'!H10 -> 335 | F9: =+'SERVICIO FAENA'!F10 -> 1585.2 | G9: =+'SERVICIO FAENA'!J10 -> 531042 | H9: =+'SERVICIO DESPOSTE'!W10 -> 0 | I9: =+(G9-J9)+K9+M9+N9+O9+P9+Q9+L9+H9 -> 531042 | J9: =+MENUDENCIAS!I10 -> 0 | K9: =+MENUDENCIAS!O10 -> 0 | L9: =+'MERCADO INTERNO'!AG11 -> 0 | M9: =+RENDERING!H9 -> 0 | N9: =+RENDERING!F9 -> 0 | O9: =+RENDERING!J9 -> 0 | P9: =+CUEROS!N11 -> 0 | Q9: =+'GRASA DREASING'!G9 -> 0
B10: =+'SERVICIO FAENA'!A11 -> 9 | C10: =+'SERVICIO FAENA'!B11 -> MUCA SAS | D10: =+'SERVICIO FAENA'!C11 -> 10 | E10: =+'SERVICIO FAENA'!H11 -> 335 | F10: =+'SERVICIO FAENA'!F11 -> 2712.6 | G10: =+'SERVICIO FAENA'!J11 -> 908721 | H10: =+'SERVICIO DESPOSTE'!W11 -> 0 | I10: =+(G10-J10)+K10+M10+N10+O10+P10+Q10+L10+H10 -> 908721 | J10: =+MENUDENCIAS!I11 -> 0 | K10: =+MENUDENCIAS!O11 -> 0 | L10: =+'MERCADO INTERNO'!AG12 -> 0 | M10: =+RENDERING!H10 -> 0 | N10: =+RENDERING!F10 -> 0 | O10: =+RENDERING!J10 -> 0 | P10: =+CUEROS!N12 -> 0 | Q10: =+'GRASA DREASING'!G10 -> 0
B11: =+'SERVICIO FAENA'!A12 -> 10 | C11: =+'SERVICIO FAENA'!B12 -> MORAGA | D11: =+'SERVICIO FAENA'!C12 -> 15 | E11: =+'SERVICIO FAENA'!H12 -> 335 | F11: =+'SERVICIO FAENA'!F12 -> 3623.5 | G11: =+'SERVICIO FAENA'!J12 -> 1213872.5 | H11: =+'SERVICIO DESPOSTE'!W12 -> 0 | I11: =+(G11-J11)+K11+M11+N11+O11+P11+Q11+L11+H11 -> 1213872.5 | J11: =+MENUDENCIAS!I12 -> 0 | K11: =+MENUDENCIAS!O12 -> 0 | L11: =+'MERCADO INTERNO'!AG13 -> 0 | M11: =+RENDERING!H11 -> 0 | N11: =+RENDERING!F11 -> 0 | O11: =+RENDERING!J11 -> 0 | P11: =+CUEROS!N13 -> 0 | Q11: =+'GRASA DREASING'!G11 -> 0
B12: =+'SERVICIO FAENA'!A13 -> 11 | C12: =+'SERVICIO FAENA'!B13 -> FERREYRA MARTIN | D12: =+'SERVICIO FAENA'!C13 -> 20 | E12: =+'SERVICIO FAENA'!H13 -> 335 | F12: =+'SERVICIO FAENA'!F13 -> 3381.6 | G12: =+'SERVICIO FAENA'!J13 -> 1132836 | H12: =+'SERVICIO DESPOSTE'!W13 -> 0 | I12: =+(G12-J12)+K12+M12+N12+O12+P12+Q12+L12+H12 -> 1132836 | J12: =+MENUDENCIAS!I13 -> 0 | K12: =+MENUDENCIAS!O13 -> 0 | L12: =+'MERCADO INTERNO'!AG14 -> 0 | M12: =+RENDERING!H12 -> 0 | N12: =+RENDERING!F12 -> 0 | O12: =+RENDERING!J12 -> 0 | P12: =+CUEROS!N14 -> 0 | Q12: =+'GRASA DREASING'!G12 -> 0
B13: =+'SERVICIO FAENA'!A14 -> 12 | C13: =+'SERVICIO FAENA'!B14 -> FERREYRA MARTIN | D13: =+'SERVICIO FAENA'!C14 -> 3 | E13: =+'SERVICIO FAENA'!H14 -> 335 | F13: =+'SERVICIO FAENA'!F14 -> 467.9 | G13: =+'SERVICIO FAENA'!J14 -> 156746.5 | H13: =+'SERVICIO DESPOSTE'!W14 -> 0 | I13: =+(G13-J13)+K13+M13+N13+O13+P13+Q13+L13+H13 -> 409253.22 | J13: =+MENUDENCIAS!I14 -> 0 | K13: =+MENUDENCIAS!O14 -> 0 | L13: =+'MERCADO INTERNO'!AG15 -> 252506.72 | M13: =+RENDERING!H13 -> 0 | N13: =+RENDERING!F13 -> 0 | O13: =+RENDERING!J13 -> 0 | P13: =+CUEROS!N15 -> 0 | Q13: =+'GRASA DREASING'!G13 -> 0
B14: =+'SERVICIO FAENA'!A15 -> 13 | C14: =+'SERVICIO FAENA'!B15 -> GANADERA NORTE NEUQUINO | D14: =+'SERVICIO FAENA'!C15 -> 40 | E14: =+'SERVICIO FAENA'!H15 -> 335 | F14: =+'SERVICIO FAENA'!F15 -> 8946.1 | G14: =+'SERVICIO FAENA'!J15 -> 2996943.5 | H14: =+'SERVICIO DESPOSTE'!W15 -> 0 | I14: =+(G14-J14)+K14+M14+N14+O14+P14+Q14+L14+H14 -> 3253567.9 | J14: =+MENUDENCIAS!I15 -> 0 | K14: =+MENUDENCIAS!O15 -> 0 | L14: =+'MERCADO INTERNO'!AG16 -> 256624.45 | M14: =+RENDERING!H14 -> 0 | N14: =+RENDERING!F14 -> 0 | O14: =+RENDERING!J14 -> 0 | P14: =+CUEROS!N16 -> 0 | Q14: =+'GRASA DREASING'!G14 -> 0
... B51: =+'SERVICIO FAENA'!A52 -> 50 | C51: =+'SERVICIO FAENA'!B52 -> MUCA SAS | D51: =+'SERVICIO FAENA'!C52 -> 2 | E51: =+'SERVICIO FAENA'!H52 -> 420 | F51: =+'SERVICIO FAENA'!F52 -> 423.7 | G51: =+'SERVICIO FAENA'!J52 -> 177954 | H51: =+'SERVICIO DESPOSTE'!W52 -> 0 | I51: =+(G51-J51)+K51+M51+N51+O51+P51+Q51+L51+H51 -> 177954 | J51: =+MENUDENCIAS!I52 -> 0 | K51: =+MENUDENCIAS!O52 -> 0 | L51: =+'MERCADO INTERNO'!AG53 -> 0 | M51: =+RENDERING!H51 -> 0 | N51: =+RENDERING!F51 -> 0 | O51: =+RENDERING!J51 -> 0 | P51: =+CUEROS!N53 -> 0 | Q51: =+'GRASA DREASING'!G51 -> 0
A52: TOTAL | D52: =SUM(D2:D51) -> 1021 | F52: Promedio animal | G52: =+I52/D52 -> 84998.518 | I52: =SUM(I2:I51) -> 86783487
A53: FEBRERO | B53: =+'SERVICIO FAENA'!A53 -> 51 | C53: =+'SERVICIO FAENA'!B53 -> GANADERA NORTE NEUQUINO | D53: =+'SERVICIO FAENA'!C53 -> 42 | E53: =+'SERVICIO FAENA'!H53 -> 420 | F53: =+'SERVICIO FAENA'!F53 -> 9646.8 | G53: =+'SERVICIO FAENA'!J53 -> 4051656 | H53: =+'SERVICIO DESPOSTE'!W53 -> 0 | I53: =+(G53-J53)+K53+M53+N53+O53+P53+Q53+L53+H53 -> 4188456 | J53: =+MENUDENCIAS!I53 -> 0 | K53: =+MENUDENCIAS!O53 -> 0 | L53: =+'MERCADO INTERNO'!AG54 -> 0 | M53: =+RENDERING!H52 -> 36000 | N53: =+RENDERING!F52 -> 81600 | O53: =+RENDERING!J52 -> 19200 | P53: =+CUEROS!N55 -> 0 | Q53: =+'GRASA DREASING'!G52 -> 0
B54: =+'SERVICIO FAENA'!A54 -> 52 | C54: =+'SERVICIO FAENA'!B54 -> FERREYRA MARTIN | D54: =+'SERVICIO FAENA'!C54 -> 18 | E54: =+'SERVICIO FAENA'!H54 -> 420 | F54: =+'SERVICIO FAENA'!F54 -> 3004.4 | G54: =+'SERVICIO FAENA'!J54 -> 1261848 | H54: =+'SERVICIO DESPOSTE'!W54 -> 0 | I54: =+(G54-J54)+K54+M54+N54+O54+P54+Q54+L54+H54 -> 1261848 | J54: =+MENUDENCIAS!I54 -> 0 | K54: =+MENUDENCIAS!O54 -> 0 | L54: =+'MERCADO INTERNO'!AG55 -> 0 | M54: =+RENDERING!H53 -> 0 | N54: =+RENDERING!F53 -> 0 | O54: =+RENDERING!J53 -> 0 | P54: =+CUEROS!N56 -> 0 | Q54: =+'GRASA DREASING'!G53 -> 0
B55: =+'SERVICIO FAENA'!A55 -> 53 | C55: =+'SERVICIO FAENA'!B55 -> BOSQUES AMADOS SRL | D55: =+'SERVICIO FAENA'!C55 -> 17 | E55: =+'SERVICIO FAENA'!H55 -> 420 | F55: =+'SERVICIO FAENA'!F55 -> 3545.7 | G55: =+'SERVICIO FAENA'!J55 -> 1489194 | H55: =+'SERVICIO DESPOSTE'!W55 -> 0 | I55: =+(G55-J55)+K55+M55+N55+O55+P55+Q55+L55+H55 -> 1489194 | J55: =+MENUDENCIAS!I55 -> 0 | K55: =+MENUDENCIAS!O55 -> 0 | L55: =+'MERCADO INTERNO'!AG56 -> 0 | M55: =+RENDERING!H54 -> 0 | N55: =+RENDERING!F54 -> 0 | O55: =+RENDERING!J54 -> 0 | P55: =+CUEROS!N57 -> 0 | Q55: =+'GRASA DREASING'!G54 -> 0
B56: =+'SERVICIO FAENA'!A56 -> 54 | C56: =+'SERVICIO FAENA'!B56 -> MUCA SAS | D56: =+'SERVICIO FAENA'!C56 -> 50 | E56: =+'SERVICIO FAENA'!H56 -> 420 | F56: =+'SERVICIO FAENA'!F56 -> 15684.1 | G56: =+'SERVICIO FAENA'!J56 -> 6587322 | H56: =+'SERVICIO DESPOSTE'!W56 -> 0 | I56: =+(G56-J56)+K56+M56+N56+O56+P56+Q56+L56+H56 -> 6770522 | J56: =+MENUDENCIAS!I56 -> 0 | K56: =+MENUDENCIAS!O56 -> 0 | L56: =+'MERCADO INTERNO'!AG57 -> 0 | M56: =+RENDERING!H55 -> 36000 | N56: =+RENDERING!F55 -> 111200 | O56: =+RENDERING!J55 -> 36000 | P56: =+CUEROS!N58 -> 0 | Q56: =+'GRASA DREASING'!G55 -> 0
B57: =+'SERVICIO FAENA'!A57 -> 55 | C57: =+'SERVICIO FAENA'!B57 -> MORAGA | D57: =+'SERVICIO FAENA'!C57 -> 10 | E57: =+'SERVICIO FAENA'!H57 -> 420 | F57: =+'SERVICIO FAENA'!F57 -> 1943.7 | G57: =+'SERVICIO FAENA'!J57 -> 816354 | H57: =+'SERVICIO DESPOSTE'!W57 -> 0 | I57: =+(G57-J57)+K57+M57+N57+O57+P57+Q57+L57+H57 -> 889154 | J57: =+MENUDENCIAS!I57 -> 0 | K57: =+MENUDENCIAS!O57 -> 0 | L57: =+'MERCADO INTERNO'!AG58 -> 0 | M57: =+RENDERING!H56 -> 19200 | N57: =+RENDERING!F56 -> 42400 | O57: =+RENDERING!J56 -> 11200 | P57: =+CUEROS!N59 -> 0 | Q57: =+'GRASA DREASING'!G56 -> 0
B58: =+'SERVICIO FAENA'!A58 -> 56 | C58: =+'SERVICIO FAENA'!B58 -> FERREYRA MARTIN | D58: =+'SERVICIO FAENA'!C58 -> 15 | E58: =+'SERVICIO FAENA'!H58 -> 420 | F58: =+'SERVICIO FAENA'!F58 -> 3484.6 | G58: =+'SERVICIO FAENA'!J58 -> 1463532 | H58: =+'SERVICIO DESPOSTE'!W58 -> 0 | I58: =+(G58-J58)+K58+M58+N58+O58+P58+Q58+L58+H58 -> 1463532 | J58: =+MENUDENCIAS!I58 -> 0 | K58: =+MENUDENCIAS!O58 -> 0 | L58: =+'MERCADO INTERNO'!AG59 -> 0 | M58: =+RENDERING!H57 -> 0 | N58: =+RENDERING!F57 -> 0 | O58: =+RENDERING!J57 -> 0 | P58: =+CUEROS!N60 -> 0 | Q58: =+'GRASA DREASING'!G57 -> 0
B59: =+'SERVICIO FAENA'!A59 -> 57 | C59: =+'SERVICIO FAENA'!B59 -> FERREYRA ALBERTO | D59: =+'SERVICIO FAENA'!C59 -> 5 | E59: =+'SERVICIO FAENA'!H59 -> 420 | F59: =+'SERVICIO FAENA'!F59 -> 925.9 | G59: =+'SERVICIO FAENA'!J59 -> 388878 | H59: =+'SERVICIO DESPOSTE'!W59 -> 0 | I59: =+(G59-J59)+K59+M59+N59+O59+P59+Q59+L59+H59 -> 388878 | J59: =+MENUDENCIAS!I59 -> 0 | K59: =+MENUDENCIAS!O59 -> 0 | L59: =+'MERCADO INTERNO'!AG60 -> 0 | M59: =+RENDERING!H58 -> 0 | N59: =+RENDERING!F58 -> 0 | O59: =+RENDERING!J58 -> 0 | P59: =+CUEROS!N61 -> 0 | Q59: =+'GRASA DREASING'!G58 -> 0
B60: =+'SERVICIO FAENA'!A60 -> 58 | C60: =+'SERVICIO FAENA'!B60 -> FERREYRA MARTIN | D60: =+'SERVICIO FAENA'!C60 -> 10 | E60: =+'SERVICIO FAENA'!H60 -> 420 | F60: =+'SERVICIO FAENA'!F60 -> 1768.6 | G60: =+'SERVICIO FAENA'!J60 -> 742812 | H60: =+'SERVICIO DESPOSTE'!W60 -> 0 | I60: =+(G60-J60)+K60+M60+N60+O60+P60+Q60+L60+H60 -> 742812 | J60: =+MENUDENCIAS!I60 -> 0 | K60: =+MENUDENCIAS!O60 -> 0 | L60: =+'MERCADO INTERNO'!AG61 -> 0 | M60: =+RENDERING!H59 -> 0 | N60: =+RENDERING!F59 -> 0 | O60: =+RENDERING!J59 -> 0 | P60: =+CUEROS!N62 -> 0 | Q60: =+'GRASA DREASING'!G59 -> 0
B61: =+'SERVICIO FAENA'!A61 -> 59 | C61: =+'SERVICIO FAENA'!B61 -> FRIGORIFICO DE LA PATAGONIA SRL | D61: =+'SERVICIO FAENA'!C61 -> 20 | E61: =+'SERVICIO FAENA'!H61 -> 420 | F61: =+'SERVICIO FAENA'!F61 -> 3150.7 | G61: =+'SERVICIO FAENA'!J61 -> 1323294 | H61: =+'SERVICIO DESPOSTE'!W61 -> 0 | I61: =+(G61-J61)+K61+M61+N61+O61+P61+Q61+L61+H61 -> 1463294 | J61: =+MENUDENCIAS!I61 -> 0 | K61: =+MENUDENCIAS!O61 -> 0 | L61: =+'MERCADO INTERNO'!AG62 -> 0 | M61: =+RENDERING!H60 -> 39200 | N61: =+RENDERING!F60 -> 83200 | O61: =+RENDERING!J60 -> 17600 | P61: =+CUEROS!N63 -> 0 | Q61: =+'GRASA DREASING'!G60 -> 0
B62: =+'SERVICIO FAENA'!A62 -> 60 | C62: =+'SERVICIO FAENA'!B62 -> FRIGORIFICO DE LA PATAGONIA SRL | D62: =+'SERVICIO FAENA'!C62 -> 28 | E62: =+'SERVICIO FAENA'!H62 -> 420 | F62: =+'SERVICIO FAENA'!F62 -> 5073.9 | G62: =+'SERVICIO FAENA'!J62 -> 2131038 | H62: =+'SERVICIO DESPOSTE'!W62 -> 0 | I62: =+(G62-J62)+K62+M62+N62+O62+P62+Q62+L62+H62 -> 2131038 | J62: =+MENUDENCIAS!I62 -> 0 | K62: =+MENUDENCIAS!O62 -> 0 | L62: =+'MERCADO INTERNO'!AG63 -> 0 | M62: =+RENDERING!H61 -> 0 | N62: =+RENDERING!F61 -> 0 | O62: =+RENDERING!J61 -> 0 | P62: =+CUEROS!N64 -> 0 | Q62: =+'GRASA DREASING'!G61 -> 0
B63: =+'SERVICIO FAENA'!A63 -> 61 | C63: =+'SERVICIO FAENA'!B63 -> MAIZALES DE LA PATAGONIA SRL | D63: =+'SERVICIO FAENA'!C63 -> 20 | E63: =+'SERVICIO FAENA'!H63 -> 420 | F63: =+'SERVICIO FAENA'!F63 -> 4074.2 | G63: =+'SERVICIO FAENA'!J63 -> 1711164 | H63: =+'SERVICIO DESPOSTE'!W63 -> 0 | I63: =+(G63-J63)+K63+M63+N63+O63+P63+Q63+L63+H63 -> 1711164 | J63: =+MENUDENCIAS!I63 -> 0 | K63: =+MENUDENCIAS!O63 -> 0 | L63: =+'MERCADO INTERNO'!AG64 -> 0 | M63: =+RENDERING!H62 -> 0 | N63: =+RENDERING!F62 -> 0 | O63: =+RENDERING!J62 -> 0 | P63: =+CUEROS!N65 -> 0 | Q63: =+'GRASA DREASING'!G62 -> 0
B64: =+'SERVICIO FAENA'!A64 -> 62 | C64: =+'SERVICIO FAENA'!B64 -> FRIGORIFICO DE LA PATAGONIA SRL | D64: =+'SERVICIO FAENA'!C64 -> 1 | E64: =+'SERVICIO FAENA'!H64 -> 420 | F64: =+'SERVICIO FAENA'!F64 -> 189.7 | G64: =+'SERVICIO FAENA'!J64 -> 79674 | H64: =+'SERVICIO DESPOSTE'!W64 -> 0 | I64: =+(G64-J64)+K64+M64+N64+O64+P64+Q64+L64+H64 -> 79674 | J64: =+MENUDENCIAS!I64 -> 0 | K64: =+MENUDENCIAS!O64 -> 0 | L64: =+'MERCADO INTERNO'!AG65 -> 0 | M64: =+RENDERING!H63 -> 0 | N64: =+RENDERING!F63 -> 0 | O64: =+RENDERING!J63 -> 0 | P64: =+CUEROS!N66 -> 0 | Q64: =+'GRASA DREASING'!G63 -> 0
B65: =+'SERVICIO FAENA'!A65 -> 63 | C65: =+'SERVICIO FAENA'!B65 -> FERREYRA MARTIN | D65: =+'SERVICIO FAENA'!C65 -> 8 | E65: =+'SERVICIO FAENA'!H65 -> 420 | F65: =+'SERVICIO FAENA'!F65 -> 1437.3 | G65: =+'SERVICIO FAENA'!J65 -> 603666 | H65: =+'SERVICIO DESPOSTE'!W65 -> 0 | I65: =+(G65-J65)+K65+M65+N65+O65+P65+Q65+L65+H65 -> 761266 | J65: =+MENUDENCIAS!I65 -> 0 | K65: =+MENUDENCIAS!O65 -> 0 | L65: =+'MERCADO INTERNO'!AG66 -> 0 | M65: =+RENDERING!H64 -> 45600 | N65: =+RENDERING!F64 -> 84000 | O65: =+RENDERING!J64 -> 28000 | P65: =+CUEROS!N67 -> 0 | Q65: =+'GRASA DREASING'!G64 -> 0
... B98: =+'SERVICIO FAENA'!A98 -> 96 | C98: =+'SERVICIO FAENA'!B98 -> FRIGORIFICO DE LA PATAGONIA SRL | D98: =+'SERVICIO FAENA'!C98 -> 22 | E98: =+'SERVICIO FAENA'!H98 -> 420 | F98: =+'SERVICIO FAENA'!F98 -> 4885.3 | G98: =+'SERVICIO FAENA'!J98 -> 2051826 | H98: =+'SERVICIO DESPOSTE'!W98 -> 0 | I98: =+(G98-J98)+K98+M98+N98+O98+P98+Q98+L98+H98 -> 2051826 | J98: =+MENUDENCIAS!I98 -> 0 | K98: =+MENUDENCIAS!O98 -> 0 | L98: =+'MERCADO INTERNO'!AG99 -> 0 | M98: =+RENDERING!H97 -> 0 | N98: =+RENDERING!F97 -> 0 | O98: =+RENDERING!J97 -> 0 | P98: =+CUEROS!N100 -> 0 | Q98: =+'GRASA DREASING'!G97 -> 0
A99: TOTAL | D99: =SUM(D53:D98) -> 815 | F99: Promedio animal | G99: =+I99/D99 -> 98274.654 | I99: =SUM(I53:I98) -> 80093843
A100: MARZO | B100: =+'SERVICIO FAENA'!A99 -> 97 | C100: =+'SERVICIO FAENA'!B99 -> FERREYRA MARTIN | D100: =+'SERVICIO FAENA'!C99 -> 18 | E100: =+'SERVICIO FAENA'!H99 -> 500 | F100: =+'SERVICIO FAENA'!F99 -> 2665.6 | G100: =+'SERVICIO FAENA'!J99 -> 1332800 | H100: =+'SERVICIO DESPOSTE'!W99 -> 0 | I100: =+(G100-J100)+K100+M100+N100+O100+P100+Q100+L100+H100 -> 1332800 | J100: =+MENUDENCIAS!I99 -> 0 | K100: =+MENUDENCIAS!O99 -> 0 | L100: =+MENUDENCIAS!P99 -> 0 | M100: =+RENDERING!H98 -> 0 | N100: =+RENDERING!F98 -> 0 | O100: =+RENDERING!J98 -> 0 | P100: =+CUEROS!N101 -> 0 | Q100: =+'GRASA DREASING'!G98 -> 0
B101: =+'SERVICIO FAENA'!A100 -> 98 | C101: =+'SERVICIO FAENA'!B100 -> GANADERA NORTE NEUQUINO | D101: =+'SERVICIO FAENA'!C100 -> 44 | E101: =+'SERVICIO FAENA'!H100 -> 500 | F101: =+'SERVICIO FAENA'!F100 -> 9281.5 | G101: =+'SERVICIO FAENA'!J100 -> 4640750 | H101: =+'SERVICIO DESPOSTE'!W100 -> 0 | I101: =+(G101-J101)+K101+M101+N101+O101+P101+Q101+L101+H101 -> 4640750 | J101: =+MENUDENCIAS!I100 -> 0 | K101: =+MENUDENCIAS!O100 -> 0 | L101: =+MENUDENCIAS!P100 -> 0 | M101: =+RENDERING!H99 -> 0 | N101: =+RENDERING!F99 -> 0 | O101: =+RENDERING!J99 -> 0 | P101: =+CUEROS!N102 -> 0 | Q101: =+'GRASA DREASING'!G99 -> 0
B102: =+'SERVICIO FAENA'!A101 -> 99 | C102: =+'SERVICIO FAENA'!B101 -> DOS DE FIERRO SA | D102: =+'SERVICIO FAENA'!C101 -> 21 | E102: =+'SERVICIO FAENA'!H101 -> 500 | F102: =+'SERVICIO FAENA'!F101 -> 4772.3 | G102: =+'SERVICIO FAENA'!J101 -> 2386150 | H102: =+'SERVICIO DESPOSTE'!W101 -> 0 | I102: =+(G102-J102)+K102+M102+N102+O102+P102+Q102+L102+H102 -> 2386150 | J102: =+MENUDENCIAS!I101 -> 0 | K102: =+MENUDENCIAS!O101 -> 0 | L102: =+MENUDENCIAS!P101 -> 0 | M102: =+RENDERING!H100 -> 0 | N102: =+RENDERING!F100 -> 0 | O102: =+RENDERING!J100 -> 0 | P102: =+CUEROS!N103 -> 0 | Q102: =+'GRASA DREASING'!G100 -> 0
B103: =+'SERVICIO FAENA'!A102 -> 100 | C103: =+'SERVICIO FAENA'!B102 -> BOSQUES AMADOS SRL | D103: =+'SERVICIO FAENA'!C102 -> 18 | E103: =+'SERVICIO FAENA'!H102 -> 500 | F103: =+'SERVICIO FAENA'!F102 -> 3494.7 | G103: =+'SERVICIO FAENA'!J102 -> 1747350 | H103: =+'SERVICIO DESPOSTE'!W102 -> 0 | I103: =+(G103-J103)+K103+M103+N103+O103+P103+Q103+L103+H103 -> 1747350 | J103: =+MENUDENCIAS!I102 -> 0 | K103: =+MENUDENCIAS!O102 -> 0 | L103: =+MENUDENCIAS!P102 -> 0 | M103: =+RENDERING!H101 -> 0 | N103: =+RENDERING!F101 -> 0 | O103: =+RENDERING!J101 -> 0 | P103: =+CUEROS!N104 -> 0 | Q103: =+'GRASA DREASING'!G101 -> 0
B104: =+'SERVICIO FAENA'!A103 -> 101 | C104: =+'SERVICIO FAENA'!B103 -> FERREYRA ALBERTO | D104: =+'SERVICIO FAENA'!C103 -> 8 | E104: =+'SERVICIO FAENA'!H103 -> 500 | F104: =+'SERVICIO FAENA'!F103 -> 1416.4 | G104: =+'SERVICIO FAENA'!J103 -> 708200 | H104: =+'SERVICIO DESPOSTE'!W103 -> 0 | I104: =+(G104-J104)+K104+M104+N104+O104+P104+Q104+L104+H104 -> 708200 | J104: =+MENUDENCIAS!I103 -> 0 | K104: =+MENUDENCIAS!O103 -> 0 | L104: =+MENUDENCIAS!P103 -> 0 | M104: =+RENDERING!H102 -> 0 | N104: =+RENDERING!F102 -> 0 | O104: =+RENDERING!J102 -> 0 | P104: =+CUEROS!N105 -> 0 | Q104: =+'GRASA DREASING'!G102 -> 0
B105: =+'SERVICIO FAENA'!A104 -> 102 | C105: =+'SERVICIO FAENA'!B104 -> FERREYRA MARTIN | D105: =+'SERVICIO FAENA'!C104 -> 12 | E105: =+'SERVICIO FAENA'!H104 -> 500 | F105: =+'SERVICIO FAENA'!F104 -> 2884.7 | G105: =+'SERVICIO FAENA'!J104 -> 1442350 | H105: =+'SERVICIO DESPOSTE'!W104 -> 0 | I105: =+(G105-J105)+K105+M105+N105+O105+P105+Q105+L105+H105 -> 1442350 | J105: =+MENUDENCIAS!I104 -> 0 | K105: =+MENUDENCIAS!O104 -> 0 | L105: =+MENUDENCIAS!P104 -> 0 | M105: =+RENDERING!H103 -> 0 | N105: =+RENDERING!F103 -> 0 | O105: =+RENDERING!J103 -> 0 | P105: =+CUEROS!N106 -> 0 | Q105: =+'GRASA DREASING'!G103 -> 0
B106: =+'SERVICIO FAENA'!A105 -> 103 | C106: =+'SERVICIO FAENA'!B105 -> FERREYRA MARTIN | D106: =+'SERVICIO FAENA'!C105 -> 10 | E106: =+'SERVICIO FAENA'!H105 -> 500 | F106: =+'SERVICIO FAENA'!F105 -> 1674.7 | G106: =+'SERVICIO FAENA'!J105 -> 837350 | H106: =+'SERVICIO DESPOSTE'!W105 -> 0 | I106: =+(G106-J106)+K106+M106+N106+O106+P106+Q106+L106+H106 -> 837350 | J106: =+MENUDENCIAS!I105 -> 0 | K106: =+MENUDENCIAS!O105 -> 0 | L106: =+MENUDENCIAS!P105 -> 0 | M106: =+RENDERING!H104 -> 0 | N106: =+RENDERING!F104 -> 0 | O106: =+RENDERING!J104 -> 0 | P106: =+CUEROS!N107 -> 0 | Q106: =+'GRASA DREASING'!G104 -> 0
B107: =+'SERVICIO FAENA'!A106 -> 104 | C107: =+'SERVICIO FAENA'!B106 -> MUCA SAS | D107: =+'SERVICIO FAENA'!C106 -> 20 | E107: =+'SERVICIO FAENA'!H106 -> 500 | F107: =+'SERVICIO FAENA'!F106 -> 4976.6 | G107: =+'SERVICIO FAENA'!J106 -> 2488300 | H107: =+'SERVICIO DESPOSTE'!W106 -> 0 | I107: =+(G107-J107)+K107+M107+N107+O107+P107+Q107+L107+H107 -> 2488300 | J107: =+MENUDENCIAS!I106 -> 0 | K107: =+MENUDENCIAS!O106 -> 0 | L107: =+MENUDENCIAS!P106 -> 0 | M107: =+RENDERING!H105 -> 0 | N107: =+RENDERING!F105 -> 0 | O107: =+RENDERING!J105 -> 0 | P107: =+CUEROS!N108 -> 0 | Q107: =+'GRASA DREASING'!G105 -> 0
B108: =+'SERVICIO FAENA'!A107 -> 0 | C108: =+'SERVICIO FAENA'!B107 -> 0 | D108: =+'SERVICIO FAENA'!C107 -> 0 | E108: =+'SERVICIO FAENA'!H107 -> 0 | F108: =+'SERVICIO FAENA'!F107 -> 0 | G108: =+'SERVICIO FAENA'!J107 -> 0 | H108: =+'SERVICIO DESPOSTE'!W107 -> 0 | I108: =+(G108-J108)+K108+M108+N108+O108+P108+Q108+L108+H108 -> 0 | J108: =+MENUDENCIAS!I107 -> 0 | K108: =+MENUDENCIAS!O107 -> 0 | L108: =+MENUDENCIAS!P107 -> 0 | M108: =+RENDERING!H106 -> 0 | N108: =+RENDERING!F106 -> 0 | O108: =+RENDERING!J106 -> 0 | P108: =+CUEROS!N109 -> 0 | Q108: =+'GRASA DREASING'!G106 -> 0
B109: =+'SERVICIO FAENA'!A108 -> 0 | C109: =+'SERVICIO FAENA'!B108 -> 0 | D109: =+'SERVICIO FAENA'!C108 -> 0 | E109: =+'SERVICIO FAENA'!H108 -> 0 | F109: =+'SERVICIO FAENA'!F108 -> 0 | G109: =+'SERVICIO FAENA'!J108 -> 0 | H109: =+'SERVICIO DESPOSTE'!W108 -> 0 | I109: =+(G109-J109)+K109+M109+N109+O109+P109+Q109+L109+H109 -> 0 | J109: =+MENUDENCIAS!I108 -> 0 | K109: =+MENUDENCIAS!O108 -> 0 | L109: =+MENUDENCIAS!P108 -> 0 | M109: =+RENDERING!H107 -> 0 | N109: =+RENDERING!F107 -> 0 | O109: =+RENDERING!J107 -> 0 | P109: =+CUEROS!N110 -> 0 | Q109: =+'GRASA DREASING'!G107 -> 0
B110: =+'SERVICIO FAENA'!A109 -> 0 | C110: =+'SERVICIO FAENA'!B109 -> 0 | D110: =+'SERVICIO FAENA'!C109 -> 0 | E110: =+'SERVICIO FAENA'!H109 -> 0 | F110: =+'SERVICIO FAENA'!F109 -> 0 | G110: =+'SERVICIO FAENA'!J109 -> 0 | H110: =+'SERVICIO DESPOSTE'!W109 -> 0 | I110: =+(G110-J110)+K110+M110+N110+O110+P110+Q110+L110+H110 -> 0 | J110: =+MENUDENCIAS!I109 -> 0 | K110: =+MENUDENCIAS!O109 -> 0 | L110: =+MENUDENCIAS!P109 -> 0 | M110: =+RENDERING!H108 -> 0 | N110: =+RENDERING!F108 -> 0 | O110: =+RENDERING!J108 -> 0 | P110: =+CUEROS!N111 -> 0 | Q110: =+'GRASA DREASING'!G108 -> 0
B111: =+'SERVICIO FAENA'!A110 -> 0 | C111: =+'SERVICIO FAENA'!B110 -> 0 | D111: =+'SERVICIO FAENA'!C110 -> 0 | E111: =+'SERVICIO FAENA'!H110 -> 0 | F111: =+'SERVICIO FAENA'!F110 -> 0 | G111: =+'SERVICIO FAENA'!J110 -> 0 | H111: =+'SERVICIO DESPOSTE'!W110 -> 0 | I111: =+(G111-J111)+K111+M111+N111+O111+P111+Q111+L111+H111 -> 0 | J111: =+MENUDENCIAS!I110 -> 0 | K111: =+MENUDENCIAS!O110 -> 0 | L111: =+MENUDENCIAS!P110 -> 0 | M111: =+RENDERING!H109 -> 0 | N111: =+RENDERING!F109 -> 0 | O111: =+RENDERING!J109 -> 0 | P111: =+CUEROS!N112 -> 0 | Q111: =+'GRASA DREASING'!G109 -> 0
B112: =+'SERVICIO FAENA'!A111 -> 0 | C112: =+'SERVICIO FAENA'!B111 -> 0 | D112: =+'SERVICIO FAENA'!C111 -> 0 | E112: =+'SERVICIO FAENA'!H111 -> 0 | F112: =+'SERVICIO FAENA'!F111 -> 0 | G112: =+'SERVICIO FAENA'!J111 -> 0 | H112: =+'SERVICIO DESPOSTE'!W111 -> 0 | I112: =+(G112-J112)+K112+M112+N112+O112+P112+Q112+L112+H112 -> 0 | J112: =+MENUDENCIAS!I111 -> 0 | K112: =+MENUDENCIAS!O111 -> 0 | L112: =+MENUDENCIAS!P111 -> 0 | M112: =+RENDERING!H110 -> 0 | N112: =+RENDERING!F110 -> 0 | O112: =+RENDERING!J110 -> 0 | P112: =+CUEROS!N113 -> 0 | Q112: =+'GRASA DREASING'!G110 -> 0
... B449: =+'SERVICIO FAENA'!A448 -> 0 | C449: =+'SERVICIO FAENA'!B448 -> 0 | D449: =+'SERVICIO FAENA'!C448 -> 0 | E449: =+'SERVICIO FAENA'!H448 -> 0 | F449: =+'SERVICIO FAENA'!F448 -> 0 | G449: =+'SERVICIO FAENA'!J448 -> 0 | H449: =+'SERVICIO DESPOSTE'!W448 -> 0 | I449: =+(G449-J449)+K449+M449+N449+O449+P449+Q449+L449+H449 -> 0 | J449: =+MENUDENCIAS!I448 -> 0 | K449: =+MENUDENCIAS!O448 -> 0 | L449: =+MENUDENCIAS!P448 -> 0 | M449: =+RENDERING!H447 -> 0 | N449: =+RENDERING!F447 -> 0 | O449: =+RENDERING!J447 -> 0 | P449: =+CUEROS!N450 -> 0 | Q449: =+'GRASA DREASING'!G447 -> 0

Sheet SERVICIO FAENA
A1: Nº TROPA | B1: USUARIO | C1: CANTIDAD DE ANIMALES | D1: KG PIE | E1: FECHA FAENA | F1: KG GANCHO | G1: RINDE % | H1: $/kg SERVICIO S/RECUPERO | I1: $/KG SERV. C/RECUPERO | J1: TOTAL $ X SERV. + 21% IVA | K1: TASA INSP. VET. (X CAB.) | L1: ARANCEL IPCVA (X CAB.) | M1: TOTAL $ FACTURA C/IMP. | N1: Nº FACTURA | O1: FECHA FACTURA | P1: FECHA PAGO | R1: MONTO DEPOSITADO | S1: ESTADO PAG. | T1: OBSERVACIONES
K2: 392.78 | L2: 535
A3: 1 | B3: MORAGA | C3: 15 | D3: 5052 | E3: 46024 | F3: 2940.3 | G3: =+F3/D3 -> 0.58200713 | H3: 335 | J3: =+H3*F3 -> 985000.5 | K3: =$K$2*C3 -> 5891.7 | L3: 5625 | M3: =+(J3*1.21)+K3+L3 -> 1203367.3 | N3: 00004-00000388 | O3: 46027 | P3: 46029 | Q3: =+P3-O3 -> 2 | R3: 1203367.3 | S3: =+R3-M3 -> 0.0049999999
A4: 2 | B4: GANADERA NORTE NEUQUINO | C4: 43 | D4: 16831 | E4: 46024 | F4: 9891.8 | G4: =+F4/D4 -> 0.58771315 | H4: 335 | J4: =+H4*F4 -> 3313753 | K4: =$K$2*C4 -> 16889.54 | L4: 16125 | M4: =+(J4*1.21)+K4+L4 -> 4042655.7 | N4: 00004-00000387 | O4: 46027 | P4: 46029 | Q4: =+P4-O4 -> 2 | R4: 4042655.7 | S4: =+R4-M4 -> 0
A5: 3 | B5: GANADERA NORTE NEUQUINO | C5: 40 | D5: 14972 | E5: 46027 | F5: 8567.8 | G5: =+F5/D5 -> 0.57225488 | H5: 335 | J5: =+H5*F5 -> 2870213 | K5: =$K$2*C5 -> 15711.2 | L5: 15000 | M5: =+(J5*1.21)+K5+L5 -> 3503668.9 | N5: 00004-00000393 | O5: 46029 | P5: 46034 | Q5: =+P5-O5 -> 5 | R5: 3503668.9 | S5: =+R5-M5 -> 0
A6: 4 | B6: DOS DE FIERRO SA | C6: 25 | D6: 8989 | E6: 46027 | F6: 5030.4 | G6: =+F6/D6 -> 0.55961731 | H6: 335 | J6: =+H6*F6 -> 1685184 | K6: =$K$2*C6 -> 9819.5 | L6: 9375 | M6: =+(J6*1.21)+K6+L6 -> 2058267.1 | N6: 00004-00000390 | O6: 46028 | P6: 46038 | Q6: =+P6-O6 -> 10 | R6: 2058267.1 | S6: =+R6-M6 -> 0 | T6: E-CHEQ
A7: 5 | B7: DISTRIBUIDORA DE LA PATAGONIA | C7: 30 | D7: 11530 | E7: 46027 | F7: 6743.3 | G7: =+F7/D7 -> 0.58484822 | H7: 335 | J7: =+H7*F7 -> 2259005.5 | K7: =$K$2*C7 -> 11783.4 | L7: 11250 | M7: =+(J7*1.21)+K7+L7 -> 2756430.1 | N7: 00004-00000389 | O7: 46028 | P7: 46028 | Q7: =+P7-O7 -> 0 | R7: 2756430.1 | S7: =+R7-M7 -> 0.0050000004
A8: 6 | B8: DISTRIBUIDORA DE LA PATAGONIA | C8: 15 | D8: 5216 | E8: 46028 | F8: 3075.2 | G8: =+F8/D8 -> 0.58957055 | H8: 335 | J8: =+H8*F8 -> 1030192 | K8: =$K$2*C8 -> 5891.7 | L8: 5625 | M8: =+(J8*1.21)+K8+L8 -> 1258049 | N8: 00004-00000391 | O8: 46028 | P8: 46028 | Q8: =+P8-O8 -> 0 | R8: 1258049 | S8: =+R8-M8 -> 0
A9: 7 | B9: MUCA SAS | C9: 35 | D9: 17870 | E9: 46028 | F9: 10641.5 | G9: =+F9/D9 -> 0.59549524 | H9: 335 | J9: =+H9*F9 -> 3564902.5 | K9: =$K$2*C9 -> 13747.3 | L9: =$L$2*C9 -> 18725 | M9: =+(J9*1.21)+K9+L9 -> 4346004.3 | N9: 00004-00000395 | O9: 46030 | P9: 46045 | Q9: =+P9-O9 -> 15 | R9: 4346004.3 | S9: =+R9-M9 -> 0.0050000008 | T9: E-CHEQ SALDO
A10: 8 | B10: MUCA SAS | C10: 5 | D10: 2714 | E10: 46028 | F10: 1585.2 | G10: =+F10/D10 -> 0.58408254 | H10: 335 | J10: =+H10*F10 -> 531042 | K10: =$K$2*C10 -> 1963.9 | L10: =$L$2*C10 -> 2675 | M10: =+(J10*1.21)+K10+L10 -> 647199.72 | N10: 00004-00000395 | O10: 46030 | P10: 46045 | Q10: =+P10-O10 -> 15 | R10: 647199.72 | S10: =+R10-M10 -> 0 | T10: E-CHEQ
A11: 9 | B11: MUCA SAS | C11: 10 | D11: 4777 | E11: 46028 | F11: 2712.6 | G11: =+F11/D11 -> 0.56784593 | H11: 335 | J11: =+H11*F11 -> 908721 | K11: =$K$2*C11 -> 3927.8 | L11: =$L$2*C11 -> 5350 | M11: =+(J11*1.21)+K11+L11 -> 1108830.2 | N11: 00004-00000395 | O11: 46030 | P11: 46045 | Q11: =+P11-O11 -> 15 | R11: 1108830.2 | S11: =+R11-M11 -> 0 | T11: E-CHEQ
A12: 10 | B12: MORAGA | C12: 15 | D12: 6180 | E12: 46028 | F12: 3623.5 | G12: =+F12/D12 -> 0.58632686 | H12: 335 | J12: =+H12*F12 -> 1213872.5 | K12: =$K$2*C12 -> 5891.7 | L12: 5625 | M12: =+(J12*1.21)+K12+L12 -> 1480302.4 | N12: 00004-00000394 | O12: 46029 | P12: 46029 | Q12: =+P12-O12 -> 0 | R12: 1480302.7 | S12: =+R12-M12 -> 0.265
A13: 11 | B13: FERREYRA MARTIN | C13: 20 | D13: 6150 | E13: 46029 | F13: 3381.6 | G13: =+F13/D13 -> 0.54985366 | H13: 335 | J13: =+H13*F13 -> 1132836 | K13: =$K$2*C13 -> 7855.6 | L13: =$L$2*C13 -> 10700 | M13: =+(J13*1.21)+K13+L13 -> 1389287.2 | N13: 00004-00000396 | O13: 46031 | P13: 46036 | Q13: =+P13-O13 -> 5 | R13: 1389287.2 | S13: =+R13-M13 -> 0
A14: 12 | B14: FERREYRA MARTIN | C14: 3 | D14: 825 | E14: 46029 | F14: 467.9 | G14: =+F14/D14 -> 0.56715152 | H14: 335 | J14: =+H14*F14 -> 156746.5 | K14: =$K$2*C14 -> 1178.34 | L14: =$L$2*C14 -> 1605 | M14: =+(J14*1.21)+K14+L14 -> 192446.6 | N14: =+N13 -> 00004-00000396 | O14: 46031 | P14: 46036 | Q14: =+P14-O14 -> 5 | R14: 192446.59 | S14: =+R14-M14 -> -0.015
A15: 13 | B15: GANADERA NORTE NEUQUINO | C15: 40 | D15: 16040 | E15: 46029 | F15: 8946.1 | G15: =+F15/D15 -> 0.55773691 | H15: 335 | J15: =+H15*F15 -> 2996943.5 | K15: =$K$2*C15 -> 15711.2 | L15: =$L$2*C15 -> 21400 | M15: =+(J15*1.21)+K15+L15 -> 3663412.8 | N15: 00004-00000397 | O15: 46031 | P15: 46034 | Q15: =+P15-O15 -> 3 | R15: 3663412.8 | S15: =+R15-M15 -> 0.0049999999
A16: 14 | B16: FRIGORIFICO DE LA PATAGONIA SRL | C16: 35 | D16: 10198 | E16: 46030 | F16: 5797.4 | G16: =+F16/D16 -> 0.56848402 | H16: 335 | J16: =+H16*F16 -> 1942129 | K16: =$K$2*C16 -> 13747.3 | L16: =$L$2*C16 -> 18725 | M16: =+(J16*1.21)+K16+L16 -> 2382448.4 | N16: 00004-00000398 | O16: 46031 | P16: 46041 | Q16: =+P16-O16 -> 10 | R16: 2382448.4 | S16: =+R16-M16 -> 0
A17: 15 | B17: GANADERA NORTE NEUQUINO | C17: 46 | D17: 16054 | E17: 46031 | F17: 9276.2 | G17: =+F17/D17 -> 0.57781238 | H17: 335 | J17: =+H17*F17 -> 3107527 | K17: =$K$2*C17 -> 18067.88 | L17: =$L$2*C17 -> 24610 | M17: =+(J17*1.21)+K17+L17 -> 3802785.6 | N17: 00004-00000400 | O17: 46035 | P17: 46038 | Q17: =+P17-O17 -> 3 | R17: 3802785.5 | S17: =+R17-M17 -> 0
A18: 16 | B18: MORAGA | C18: 15 | D18: 6402 | E18: 46031 | F18: 3771.7 | G18: =+F18/D18 -> 0.58914402 | H18: 335 | J18: =+H18*F18 -> 1263519.5 | K18: =$K$2*C18 -> 5891.7 | L18: =$L$2*C18 -> 8025 | M18: =+(J18*1.21)+K18+L18 -> 1542775.3 | N18: 00004-00000401 | O18: 46035 | P18: 46035 | Q18: =+P18-O18 -> 0 | R18: 1542775.3 | S18: =+R18-M18 -> 0.0050000001
A19: 17 | B19: LASAGNO JORGE ALBERTO | C19: 17 | D19: 6546 | E19: 46031 | F19: 3815 | G19: =+F19/D19 -> 0.58279866 | H19: 335 | J19: =+H19*F19 -> 1278025 | K19: =$K$2*C19 -> 6677.26 | L19: =$L$2*C19 -> 9095 | M19: =+(J19*1.21)+K19+L19 -> 1562182.5 | N19: 00004-00000399 | O19: 46032 | P19: 46032 | Q19: =+P19-O19 -> 0 | R19: 1562182.5 | S19: =+R19-M19 -> 0
A20: 18 | B20: GANADERA NORTE NEUQUINO | C20: 43 | D20: 15144 | E20: 46034 | F20: 8837.3 | G20: =+F20/D20 -> 0.58355124 | H20: 335 | J20: =+H20*F20 -> 2960495.5 | K20: =$K$2*C20 -> 16889.54 | L20: =$L$2*C20 -> 23005 | M20: =+(J20*1.21)+K20+L20 -> 3622094.1 | N20: 00004-00000402 | O20: 46034 | P20: 46041 | Q20: =+P20-O20 -> 7 | R20: 3622094.1 | S20: =+R20-M20 -> 0.0050000008
A21: 19 | B21: DOS DE FIERRO SA | C21: 25 | D21: 9054 | E21: 46034 | F21: 5048.5 | G21: =+F21/D21 -> 0.55759885 | H21: 335 | J21: =+H21*F21 -> 1691247.5 | K21: =$K$2*C21 -> 9819.5 | L21: =$L$2*C21 -> 13375 | M21: =+(J21*1.21)+K21+L21 -> 2069604 | N21: 00004-00000403 | O21: 46034 | P21: 46041 | Q21: =+P21-O21 -> 7 | R21: 2069603 | S21: =+R21-M21 -> -0.975
A22: 20 | B22: FERREYRA MARTIN | C22: 15 | D22: 4722 | E22: 46034 | F22: 2689.9 | G22: =+F22/D22 -> 0.56965269 | H22: 335 | J22: =+H22*F22 -> 901116.5 | K22: =$K$2*C22 -> 5891.7 | L22: =$L$2*C22 -> 8025 | M22: =+(J22*1.21)+K22+L22 -> 1104267.7 | N22: 00004-00000404 | O22: 46034 | P22: 46041 | Q22: =+P22-O22 -> 7 | R22: 1104267.7 | S22: =+R22-M22 -> -0.0050000001
A23: 21 | B23: MUCA SAS | C23: 8 | D23: 3551 | E23: 46035 | F23: 2076.3 | G23: =+F23/D23 -> 0.58470853 | H23: 335 | J23: =+H23*F23 -> 695560.5 | K23: =$K$2*C23 -> 3142.24 | L23: =$L$2*C23 -> 4280 | M23: =+(J23*1.21)+K23+L23 -> 849050.45 | N23: 00004-00000405 | O23: 46036 | P23: 46045 | Q23: =+P23-O23 -> 9 | R23: 849050.45 | S23: =+R23-M23 -> 0.0049999999 | T23: E-CHEQ
A24: 22 | B24: MUCA SAS | C24: 7 | D24: 3139 | E24: 46035 | F24: 1852.3 | G24: =+F24/D24 -> 0.59009239 | H24: 335 | J24: =+H24*F24 -> 620520.5 | K24: =$K$2*C24 -> 2749.46 | L24: =$L$2*C24 -> 3745 | M24: =+(J24*1.21)+K24+L24 -> 757324.26 | N24: =+N23 -> 00004-00000405 | O24: 46036 | P24: 46045 | Q24: =+P24-O24 -> 9 | R24: 757324.27 | S24: =+R24-M24 -> 0.0050000001 | T24: E-CHEQ
A25: 23 | B25: MUCA SAS | C25: 5 | D25: 3736 | E25: 46035 | F25: 2266.5 | G25: =+F25/D25 -> 0.60666488 | H25: 335 | J25: =+H25*F25 -> 759277.5 | K25: =$K$2*C25 -> 1963.9 | L25: =$L$2*C25 -> 2675 | M25: =+(J25*1.21)+K25+L25 -> 923364.68 | N25: =+N24 -> 00004-00000405 | O25: 46036 | P25: 46045 | Q25: =+P25-O25 -> 9 | R25: 923364.68 | S25: =+R25-M25 -> 0.005 | T25: E-CHEQ
A26: 24 | B26: FERREYRA MARTIN | C26: 30 | D26: 10277 | E26: 46036 | F26: 5913.5 | G26: =+F26/D26 -> 0.57541111 | H26: 335 | J26: =+H26*F26 -> 1981022.5 | K26: =$K$2*C26 -> 11783.4 | L26: =$L$2*C26 -> 16050 | M26: =+(J26*1.21)+K26+L26 -> 2424870.6 | N26: 00004-00000406 | O26: 46037 | P26: 46045 | Q26: =+P26-O26 -> 8 | R26: 2424870.6 | S26: =+R26-M26 -> 0.0049999999
A27: 25 | B27: FERREYRA ALBERTO | C27: 6 | D27: 1839 | E27: 46036 | F27: 1026 | G27: =+F27/D27 -> 0.55791191 | H27: 335 | J27: =+H27*F27 -> 343710 | K27: =$K$2*C27 -> 2356.68 | L27: =$L$2*C27 -> 3210 | M27: =+(J27*1.21)+K27+L27 -> 421455.78 | N27: 00004-00000407 | O27: 46037 | P27: 46038 | Q27: =+P27-O27 -> 1 | R27: 421455.78 | S27: =+R27-M27 -> 0
A28: 26 | B28: FRIGORIFICO DE LA PATAGONIA SRL | C28: 50 | D28: 20868 | E28: 46038 | F28: 11388.5 | G28: =+F28/D28 -> 0.54573989 | H28: 335 | J28: =+H28*F28 -> 3815147.5 | K28: =$K$2*C28 -> 19639 | L28: =$L$2*C28 -> 26750 | M28: =+(J28*1.21)+K28+L28 -> 4662717.5 | N28: 00004-00000408 | O28: 46041 | P28: 46041 | Q28: =+P28-O28 -> 0 | R28: 4662717.5 | S28: =+R28-M28 -> 0.0050000008
A29: 27 | B29: GANADERA NORTE NEUQUINO | C29: 40 | D29: 16159 | E29: 46041 | F29: 9184 | G29: =+F29/D29 -> 0.568352 | H29: 420 | J29: =+H29*F29 -> 3857280 | K29: =$K$2*C29 -> 15711.2 | L29: =$L$2*C29 -> 21400 | M29: =+(J29*1.21)+K29+L29 -> 4704420 | N29: 00004-00000409 | O29: 46043 | P29: 46050 | Q29: =+P29-O29 -> 7 | R29: 4704420 | S29: =+R29-M29 -> 0
A30: 28 | B30: DOS DE FIERRO SA | C30: 26 | D30: 9452 | E30: 46041 | F30: 5329.9 | G30: =+F30/D30 -> 0.56389124 | H30: 420 | J30: =+H30*F30 -> 2238558 | K30: =$K$2*C30 -> 10212.28 | L30: =$L$2*C30 -> 13910 | M30: =+(J30*1.21)+K30+L30 -> 2732777.5 | N30: 00004-00000410 | O30: 46043 | P30: 46057 | Q30: =+P30-O30 -> 14 | R30: 2732777.5 | S30: =+R30-M30 -> 0
A31: 29 | B31: FERREYRA MARTIN | C31: 15 | D31: 5044 | E31: 46041 | F31: 2923.1 | G31: =+F31/D31 -> 0.57952022 | H31: 420 | J31: =+H31*F31 -> 1227702 | K31: =$K$2*C31 -> 5891.7 | L31: =$L$2*C31 -> 8025 | M31: =+(J31*1.21)+K31+L31 -> 1499436.1 | N31: 00004-00000411 | O31: 46043 | P31: 46048 | Q31: =+P31-O31 -> 5 | R31: 1499436.1 | S31: =+R31-M31 -> 0
A32: 30 | B32: BOSQUES AMADOS SRL | C32: 18 | D32: =356+6343 -> 6699 | E32: 20-21/01/2026 | F32: =194.6+3633.1 -> 3827.7 | G32: =+F32/D32 -> 0.57138379 | H32: 420 | J32: =+H32*F32 -> 1607634 | K32: =$K$2*C32 -> 7070.04 | L32: =$L$2*C32 -> 9630 | M32: =+(J32*1.21)+K32+L32 -> 1961937.2 | N32: 00004-00000412 | O32: 46045 | P32: 46055 | Q32: =+P32-O32 -> 10 | R32: 1961937.2 | S32: =+R32-M32 -> 0
A33: 31 | B33: MUCA SAS | C33: 50 | D33: 24991 | E33: 46042 | F33: 14763.6 | G33: =+F33/D33 -> 0.59075667 | H33: 420 | J33: =+H33*F33 -> 6200712 | K33: =$K$2*C33 -> 19639 | L33: =$L$2*C33 -> 26750 | M33: =+(J33*1.21)+K33+L33 -> 7549250.5 | N33: 00004-00000413 | O33: 46045 | P33: 46059 | Q33: =+P33-O33 -> 14 | R33: 7549250.5 | S33: =+R33-M33 -> 0
A34: 32 | B34: FERREYRA ALBERTO | C34: 8 | D34: 2803 | E34: 46044 | F34: 1669.6 | G34: =+F34/D34 -> 0.59564752 | H34: 420 | J34: =+H34*F34 -> 701232 | K34: =$K$2*C34 -> 3142.24 | L34: =$L$2*C34 -> 4280 | M34: =+(J34*1.21)+K34+L34 -> 855912.96 | N34: 00004-00000414 | O34: 46045 | P34: 46050 | Q34: =+P34-O34 -> 5 | R34: 855912.96 | S34: =+R34-M34 -> 0
A35: 33 | B35: FERREYRA MARTIN | C35: 20 | D35: 7197 | E35: 46044 | F35: 4225.7 | G35: =+F35/D35 -> 0.58714742 | H35: 420 | J35: =+H35*F35 -> 1774794 | K35: =$K$2*C35 -> 7855.6 | L35: =$L$2*C35 -> 10700 | M35: =+(J35*1.21)+K35+L35 -> 2166056.3 | N35: 00004-00000415 | O35: 46045 | P35: 46055 | Q35: =+P35-O35 -> 10 | R35: 2166156.3 | S35: =+R35-M35 -> 100
A36: 34 | B36: FRIGORIFICO DE LA PATAGONIA SRL | C36: 15 | D36: 5823 | E36: 46045 | F36: 3412.6 | G36: =+F36/D36 -> 0.5860553 | H36: 420 | J36: =+H36*F36 -> 1433292 | K36: =$K$2*C36 -> 5891.7 | L36: =$L$2*C36 -> 8025 | M36: =+(J36*1.21)+K36+L36 -> 1748200 | N36: 00004-00000416 | O36: 46045 | P36: 46057 | Q36: =+P36-O36 -> 12 | R36: 1748200 | S36: =+R36-M36 -> 0
A37: 35 | B37: MUCA SAS | C37: 13 | D37: 5332 | E37: 46045 | F37: 2920.2 | G37: =+F37/D37 -> 0.54767442 | H37: 420 | J37: =+H37*F37 -> 1226484 | K37: =$K$2*C37 -> 5106.14 | L37: =$L$2*C37 -> 6955 | M37: =+(J37*1.21)+K37+L37 -> 1496106.8 | N37: 00004-00000417 | O37: 46045 | P37: 46059 | Q37: =+P37-O37 -> 14 | R37: 1496106.8 | S37: =+R37-M37 -> 0
A38: 36 | B38: MUCA SAS | C38: 15 | D38: 7438 | E38: 46045 | F38: 4307.2 | G38: =+F38/D38 -> 0.5790804 | H38: 420 | J38: =+H38*F38 -> 1809024 | K38: =$K$2*C38 -> 5891.7 | L38: =$L$2*C38 -> 8025 | M38: =+(J38*1.21)+K38+L38 -> 2202835.7 | N38: 00004-00000417 | O38: 46045 | P38: 46059 | Q38: =+P38-O38 -> 14 | R38: 2202835.7 | S38: =+R38-M38 -> 0
A39: 37 | B39: FERREYRA MARTIN | C39: 15 | D39: 4501 | E39: 46048 | F39: 2620.9 | G39: =+F39/D39 -> 0.58229282 | H39: 420 | J39: =+H39*F39 -> 1100778 | K39: =$K$2*C39 -> 5891.7 | L39: =$L$2*C39 -> 8025 | M39: =+(J39*1.21)+K39+L39 -> 1345858.1 | N39: 00004-00000419 | O39: 46049 | P39: 46057 | Q39: =+P39-O39 -> 8 | R39: 1345858.1 | S39: =+R39-M39 -> 0
A40: 38 | B40: FRIGORIFICO DE LA PATAGONIA SRL | C40: 26 | D40: 9703 | E40: 46048 | F40: 5472.9 | G40: =+F40/D40 -> 0.56404205 | H40: 420 | J40: =+H40*F40 -> 2298618 | K40: =$K$2*C40 -> 10212.28 | L40: =$L$2*C40 -> 13910 | M40: =+(J40*1.21)+K40+L40 -> 2805450.1 | N40: 00004-00000418 | O40: 46049 | P40: 46057 | Q40: =+P40-O40 -> 8 | R40: 2805450.1 | S40: =+R40-M40 -> 0 | T40: Faena Dos de Fierro
A41: 39 | B41: BOSQUES AMADOS SRL | C41: 18 | D41: 6853 | E41: 46049 | F41: 3938 | G41: =+F41/D41 -> 0.57463884 | H41: 420 | J41: =+H41*F41 -> 1653960 | K41: =$K$2*C41 -> 7070.04 | L41: =$L$2*C41 -> 9630 | M41: =+(J41*1.21)+K41+L41 -> 2017991.6 | N41: 00004-00000420 | O41: 46049 | P41: 46067 | Q41: =+P41-O41 -> 18 | R41: 2017991.6 | S41: =+R41-M41 -> 0
A42: 40 | B42: MUCA SAS | C42: 31 | D42: 11492 | E42: 46049 | F42: 6649.5 | G42: =+F42/D42 -> 0.57861991 | H42: 420 | J42: =+H42*F42 -> 2792790 | K42: =$K$2*C42 -> 12176.18 | L42: =$L$2*C42 -> 16585 | M42: =+(J42*1.21)+K42+L42 -> 3408037.1 | N42: 00004-00000421 | O42: 46049 | P42: 46064 | Q42: =+P42-O42 -> 15 | R42: 3408037.1 | S42: =+R42-M42 -> 0
A43: 41 | B43: MUCA SAS | C43: 14 | D43: 5514 | E43: 46049 | F43: 3165.1 | G43: =+F43/D43 -> 0.57401161 | H43: 420 | J43: =+H43*F43 -> 1329342 | K43: =$K$2*C43 -> 5498.92 | L43: =$L$2*C43 -> 7490 | M43: =+(J43*1.21)+K43+L43 -> 1621492.7 | N43: 00004-00000421 | O43: 46049 | P43: 46064 | Q43: =+P43-O43 -> 15 | R43: 1621492.7 | S43: =+R43-M43 -> 0
A44: 42 | B44: FERREYRA MARTIN | C44: 14 | D44: 4495 | E44: 46050 | F44: 2464.5 | G44: =+F44/D44 -> 0.54827586 | H44: 420 | J44: =+H44*F44 -> 1035090 | K44: =$K$2*C44 -> 5498.92 | L44: =$L$2*C44 -> 7490 | M44: =+(J44*1.21)+K44+L44 -> 1265447.8 | N44: 00004-00000422 | O44: 46052 | P44: 46063 | Q44: =+P44-O44 -> 11 | R44: 1265447.8 | S44: =+R44-M44 -> 0
A45: 43 | B45: FERREYRA MARTIN | C45: 9 | D45: 3254 | E45: 46050 | F45: 1827.6 | G45: =+F45/D45 -> 0.5616472 | H45: 420 | J45: =+H45*F45 -> 767592 | K45: =$K$2*C45 -> 3535.02 | L45: =$L$2*C45 -> 4815 | M45: =+(J45*1.21)+K45+L45 -> 937136.34 | N45: 00004-00000422 | O45: 46052 | P45: 46063 | Q45: =+P45-O45 -> 11 | R45: 937136.34 | S45: =+R45-M45 -> 0
A46: 44 | B46: FERREYRA ALBERTO | C46: 6 | D46: 2216 | E46: 46050 | F46: 1197.1 | G46: =+F46/D46 -> 0.54020758 | H46: 420 | J46: =+H46*F46 -> 502782 | K46: =$K$2*C46 -> 2356.68 | L46: =$L$2*C46 -> 3210 | M46: =+(J46*1.21)+K46+L46 -> 613932.9 | N46: 00004-00000423 | O46: 46052 | P46: 46057 | Q46: =+P46-O46 -> 5 | R46: 613933 | S46: =+R46-M46 -> 0.1
A47: 45 | B47: FRIGORIFICO DE LA PATAGONIA SRL | C47: 22 | D47: 8229 | E47: 46052 | F47: 4622.2 | G47: =+F47/D47 -> 0.56169644 | H47: 420 | J47: =+H47*F47 -> 1941324 | K47: =$K$2*C47 -> 8641.16 | L47: =$L$2*C47 -> 11770 | M47: =+(J47*1.21)+K47+L47 -> 2369413.2 | N47: 00004-00000424 | O47: 46052 | P47: 46057 | Q47: =+P47-O47 -> 5 | R47: 2369413.2 | S47: =+R47-M47 -> 0
A48: 46 | B48: FRIGORIFICO DE LA PATAGONIA SRL | C48: 20 | D48: 7358 | E48: 46052 | F48: 4096.1 | G48: =+F48/D48 -> 0.5566866 | H48: 420 | J48: =+H48*F48 -> 1720362 | K48: =$K$2*C48 -> 7855.6 | L48: =$L$2*C48 -> 10700 | M48: =+(J48*1.21)+K48+L48 -> 2100193.6 | N48: 00004-00000424 | O48: 46052 | P48: 46057 | Q48: =+P48-O48 -> 5 | R48: 2100193.6 | S48: =+R48-M48 -> 0
A49: 47 | B49: MUCA SAS | C49: 13 | D49: 4933 | E49: 46052 | F49: 2656.7 | G49: =+F49/D49 -> 0.53855666 | H49: 420 | J49: =+H49*F49 -> 1115814 | K49: =$K$2*C49 -> 5106.14 | L49: =$L$2*C49 -> 6955 | M49: =+(J49*1.21)+K49+L49 -> 1362196.1 | N49: 00004-00000425 | O49: 46055 | P49: 46064 | Q49: =+P49-O49 -> 9 | R49: 1362196.1 | S49: =+R49-M49 -> 0
A50: 48 | B50: MUCA SAS | C50: 8 | D50: 4230 | E50: 46052 | F50: 2534.9 | G50: =+F50/D50 -> 0.59926714 | H50: 420 | J50: =+H50*F50 -> 1064658 | K50: =$K$2*C50 -> 3142.24 | L50: =$L$2*C50 -> 4280 | M50: =+(J50*1.21)+K50+L50 -> 1295658.4 | N50: 00004-00000425 | O50: 46055 | P50: 46064 | Q50: =+P50-O50 -> 9 | R50: 842584.6 | S50: =+R50-M50 -> -453073.82
A51: 49 | B51: MUCA SAS | C51: 5 | D51: 1890 | E51: 46052 | F51: 1128.1 | G51: =+F51/D51 -> 0.59687831 | H51: 420 | J51: =+H51*F51 -> 473802 | K51: =$K$2*C51 -> 1963.9 | L51: =$L$2*C51 -> 2675 | M51: =+(J51*1.21)+K51+L51 -> 577939.32 | N51: 00004-00000425 | O51: 46055 | Q51: =+P51-O51 -> -46055 | S51: =+R51-M51 -> -577939.32
A52: 50 | B52: MUCA SAS | C52: 2 | D52: 739 | E52: 46052 | F52: 423.7 | G52: =+F52/D52 -> 0.57334235 | H52: 420 | J52: =+H52*F52 -> 177954 | K52: =$K$2*C52 -> 785.56 | L52: =$L$2*C52 -> 1070 | M52: =+(J52*1.21)+K52+L52 -> 217179.9 | N52: 00004-00000425 | O52: 46055 | Q52: =+P52-O52 -> -46055 | S52: =+R52-M52 -> -217179.9
A53: 51 | B53: GANADERA NORTE NEUQUINO | C53: 42 | D53: 16674 | E53: 46055 | F53: 9646.8 | G53: =+F53/D53 -> 0.57855344 | H53: 420 | J53: =+H53*F53 -> 4051656 | K53: =$K$2*C53 -> 16496.76 | L53: =$L$2*C53 -> 22470 | M53: =+(J53*1.21)+K53+L53 -> 4941470.5 | N53: 00004-00000426 | O53: 46055 | P53: 46063 | Q53: =+P53-O53 -> 8 | R53: 4941470.5 | S53: =+R53-M53 -> 0
A54: 52 | B54: FERREYRA MARTIN | C54: 18 | D54: 5318 | E54: 46055 | F54: 3004.4 | G54: =+F54/D54 -> 0.56494923 | H54: 420 | J54: =+H54*F54 -> 1261848 | K54: =$K$2*C54 -> 7070.04 | L54: =$L$2*C54 -> 9630 | M54: =+(J54*1.21)+K54+L54 -> 1543536.1 | N54: 00004-00000428 | O54: 46055 | P54: 46065 | Q54: =+P54-O54 -> 10 | R54: 1543536.1 | S54: =+R54-M54 -> 0
A55: 53 | B55: BOSQUES AMADOS SRL | C55: 17 | D55: 6232 | E55: 46057 | F55: 3545.7 | G55: =+F55/D55 -> 0.56895058 | H55: 420 | J55: =+H55*F55 -> 1489194 | K55: =$K$2*C55 -> 6677.26 | L55: =$L$2*C55 -> 9095 | M55: =+(J55*1.21)+K55+L55 -> 1817697 | N55: 00004-00000429 | O55: 46057 | Q55: =+P55-O55 -> -46057 | S55: =+R55-M55 -> -1817697
A56: 54 | B56: MUCA SAS | C56: 50 | D56: 26689 | E56: 46056 | F56: 15684.1 | G56: =+F56/D56 -> 0.58766158 | H56: 420 | J56: =+H56*F56 -> 6587322 | K56: =$K$2*C56 -> 19639 | L56: =$L$2*C56 -> 26750 | M56: =+(J56*1.21)+K56+L56 -> 8017048.6 | N56: 00004-00000430 | O56: 46057 | Q56: =+P56-O56 -> -46057 | S56: =+R56-M56 -> -8017048.6
A57: 55 | B57: MORAGA | C57: 10 | D57: 3489 | E57: 46057 | F57: 1943.7 | G57: =+F57/D57 -> 0.55709372 | H57: 420 | J57: =+H57*F57 -> 816354 | K57: =$K$2*C57 -> 3927.8 | L57: =$L$2*C57 -> 5350 | M57: =+(J57*1.21)+K57+L57 -> 997066.14 | N57: 00004-00000431 | O57: 46057 | P57: 46063 | Q57: =+P57-O57 -> 6 | R57: 997066.14 | S57: =+R57-M57 -> 0
A58: 56 | B58: FERREYRA MARTIN | C58: 15 | D58: 6032 | E58: 46058 | F58: 3484.6 | G58: =+F58/D58 -> 0.57768568 | H58: 420 | J58: =+H58*F58 -> 1463532 | K58: =$K$2*C58 -> 5891.7 | L58: =$L$2*C58 -> 8025 | M58: =+(J58*1.21)+K58+L58 -> 1784790.4 | N58: 00004-00000433 | O58: 46058 | P58: 46070 | Q58: =+P58-O58 -> 12 | R58: 1784790.4 | S58: =+R58-M58 -> 0
A59: 57 | B59: FERREYRA ALBERTO | C59: 5 | D59: 1664 | E59: 46057 | F59: 925.9 | G59: =+F59/D59 -> 0.55643029 | H59: 420 | J59: =+H59*F59 -> 388878 | K59: =$K$2*C59 -> 1963.9 | L59: =$L$2*C59 -> 2675 | M59: =+(J59*1.21)+K59+L59 -> 475181.28 | N59: 00004-00000434 | O59: 46058 | P59: 46065 | Q59: =+P59-O59 -> 7 | R59: 475182 | S59: =+R59-M59 -> 0.72
A60: 58 | B60: FERREYRA MARTIN | C60: 10 | D60: 3214 | E60: 46058 | F60: 1768.6 | G60: =+F60/D60 -> 0.55028002 | H60: 420 | J60: =+H60*F60 -> 742812 | K60: =$K$2*C60 -> 3927.8 | L60: =$L$2*C60 -> 5350 | M60: =+(J60*1.21)+K60+L60 -> 908080.32 | N60: 00004-00000433 | O60: 46058 | P60: 46070 | Q60: =+P60-O60 -> 12 | R60: 908080.32 | S60: =+R60-M60 -> 0
A61: 59 | B61: FRIGORIFICO DE LA PATAGONIA SRL | C61: 20 | D61: 5711 | E61: 46059 | F61: 3150.7 | G61: =+F61/D61 -> 0.55168972 | H61: 420 | J61: =+H61*F61 -> 1323294 | K61: =$K$2*C61 -> 7855.6 | L61: =$L$2*C61 -> 10700 | M61: =+(J61*1.21)+K61+L61 -> 1619741.3 | N61: 00004-00000436 | O61: 46059 | P61: 46078 | Q61: =+P61-O61 -> 19 | R61: 1619741.3 | S61: =+R61-M61 -> 0
A62: 60 | B62: FRIGORIFICO DE LA PATAGONIA SRL | C62: 28 | D62: 8846 | E62: 46059 | F62: 5073.9 | G62: =+F62/D62 -> 0.57358128 | H62: 420 | J62: =+H62*F62 -> 2131038 | K62: =$K$2*C62 -> 10997.84 | L62: =$L$2*C62 -> 14980 | M62: =+(J62*1.21)+K62+L62 -> 2604533.8 | N62: 00004-00000436 | O62: 46059 | P62: 46078 | Q62: =+P62-O62 -> 19 | R62: 2604533.8 | S62: =+R62-M62 -> 0
A63: 61 | B63: MAIZALES DE LA PATAGONIA SRL | C63: 20 | D63: 7249 | E63: 46059 | F63: 4074.2 | G63: =+F63/D63 -> 0.56203614 | H63: 420 | J63: =+H63*F63 -> 1711164 | K63: =$K$2*C63 -> 7855.6 | L63: =$L$2*C63 -> 10700 | M63: =+(J63*1.21)+K63+L63 -> 2089064 | N63: 00004-00000435 | O63: 46059 | P63: 46064 | Q63: =+P63-O63 -> 5 | R63: 2089064 | S63: =+R63-M63 -> 0
A64: 62 | B64: FRIGORIFICO DE LA PATAGONIA SRL | C64: 1 | D64: 322 | E64: 46059 | F64: 189.7 | G64: =+F64/D64 -> 0.58913043 | H64: 420 | J64: =+H64*F64 -> 79674 | K64: =$K$2*C64 -> 392.78 | L64: =$L$2*C64 -> 535 | M64: =+(J64*1.21)+K64+L64 -> 97333.32 | N64: 00004-00000436 | O64: 46059 | P64: 46066 | Q64: =+P64-O64 -> 7 | R64: 89948.88 | S64: =+R64-M64 -> -7384.44
A65: 63 | B65: FERREYRA MARTIN | C65: 8 | D65: 2549 | E65: 46062 | F65: 1437.3 | G65: =+F65/D65 -> 0.56386818 | H65: 420 | J65: =+H65*F65 -> 603666 | K65: =$K$2*C65 -> 3142.24 | L65: =$L$2*C65 -> 4280 | M65: =+(J65*1.21)+K65+L65 -> 737858.1 | N65: 00004-00000437 | O65: 46062 | P65: 46076 | Q65: =+P65-O65 -> 14 | R65: 737858.1 | S65: =+R65-M65 -> 0
A66: 64 | B66: FERREYRA MARTIN | C66: 3 | D66: 1208 | E66: 46062 | F66: 697.2 | G66: =+F66/D66 -> 0.57715232 | H66: 420 | J66: =+H66*F66 -> 292824 | K66: =$K$2*C66 -> 1178.34 | L66: =$L$2*C66 -> 1605 | M66: =+(J66*1.21)+K66+L66 -> 357100.38 | N66: 00004-00000437 | O66: 46062 | P66: 46076 | Q66: =+P66-O66 -> 14 | R66: 357100.38 | S66: =+R66-M66 -> 0
A67: 65 | B67: FERREYRA MARTIN | C67: 4 | D67: 1273 | E67: 46062 | F67: 696.2 | G67: =+F67/D67 -> 0.54689709 | H67: 420 | J67: =+H67*F67 -> 292404 | K67: =$K$2*C67 -> 1571.12 | L67: =$L$2*C67 -> 2140 | M67: =+(J67*1.21)+K67+L67 -> 357519.96 | N67: 00004-00000437 | O67: 46062 | P67: 46076 | Q67: =+P67-O67 -> 14 | R67: 357519.96 | S67: =+R67-M67 -> 0
A68: 66 | B68: DOS DE FIERRO SA | C68: 21 | D68: 7963 | E68: 46062 | F68: 4464 | G68: =+F68/D68 -> 0.56059274 | H68: 420 | J68: =+H68*F68 -> 1874880 | K68: =$K$2*C68 -> 8248.38 | L68: =$L$2*C68 -> 11235 | M68: =+(J68*1.21)+K68+L68 -> 2288088.2 | N68: 00004-00000438 | O68: 46062 | P68: 46073 | Q68: =+P68-O68 -> 11 | R68: 2288088.2 | S68: =+R68-M68 -> 0
... A70: 68 | B70: BOSQUES AMADOS SRL | C70: 18 | D70: 6542 | E70: 46063 | F70: 3742.8 | G70: =+F70/D70 -> 0.57211862 | H70: 420 | J70: =+H70*F70 -> 1571976 | K70: =$K$2*C70 -> 7070.04 | L70: =$L$2*C70 -> 9630 | M70: =+(J70*1.21)+K70+L70 -> 1918791 | N70: 00004-00000440 | O70: 46063 | P70: 46084 | Q70: =+P70-O70 -> 21 | R70: 1918791 | S70: =+R70-M70 -> 0
A71: 69 | B71: MUCA SAS | C71: 50 | D71: 26006 | E71: 46063 | F71: 15246 | G71: =+F71/D71 -> 0.58624933 | H71: 420 | J71: =+H71*F71 -> 6403320 | K71: =$K$2*C71 -> 19639 | L71: =$L$2*C71 -> 26750 | M71: =+(J71*1.21)+K71+L71 -> 7794406.2 | N71: 00004-00000441 | O71: 46063 | Q71: =+P71-O71 -> -46063 | S71: =+R71-M71 -> -7794406.2
A72: 70 | B72: FERREYRA ALBERTO | C72: 5 | D72: 1422 | E72: 46065 | F72: 789.6 | G72: =+F72/D72 -> 0.55527426 | H72: 420 | J72: =+H72*F72 -> 331632 | K72: =$K$2*C72 -> 1963.9 | L72: =$L$2*C72 -> 2675 | M72: =+(J72*1.21)+K72+L72 -> 405913.62 | N72: 00004-00000442 | O72: 46065 | P72: 46071 | Q72: =+P72-O72 -> 6 | R72: 405914 | S72: =+R72-M72 -> 0.38
A73: 71 | B73: FRIGORIFICO DE LA PATAGONIA SRL | C73: 25 | D73: 9309 | E73: 46065 | F73: 5066 | G73: =+F73/D73 -> 0.54420453 | H73: 420 | J73: =+H73*F73 -> 2127720 | K73: =$K$2*C73 -> 9819.5 | L73: =$L$2*C73 -> 13375 | M73: =+(J73*1.21)+K73+L73 -> 2597735.7 | N73: 00004-00000443 | O73: 46066 | P73: 46073 | Q73: =+P73-O73 -> 7 | R73: 2597735.7 | S73: =+R73-M73 -> 0
A74: 72 | B74: FERREYRA MARTIN | C74: 20 | D74: 6329 | E74: 46065 | F74: 3572.3 | G74: =+F74/D74 -> 0.56443356 | H74: 420 | J74: =+H74*F74 -> 1500366 | K74: =$K$2*C74 -> 7855.6 | L74: =$L$2*C74 -> 10700 | M74: =+(J74*1.21)+K74+L74 -> 1833998.5 | N74: 00004-00000444 | O74: 46066 | P74: 46079 | Q74: =+P74-O74 -> 13 | R74: 1833998.5 | S74: =+R74-M74 -> 0
A75: 73 | B75: FRIGORIFICO DE LA PATAGONIA SRL | C75: 15 | D75: 5861 | E75: 46065 | F75: 3350.2 | G75: =+F75/D75 -> 0.57160894 | H75: 420 | J75: =+H75*F75 -> 1407084 | K75: =$K$2*C75 -> 5891.7 | L75: =$L$2*C75 -> 8025 | M75: =+(J75*1.21)+K75+L75 -> 1716488.3 | N75: 00004-00000445 | O75: 46066 | P75: 46073 | Q75: =+P75-O75 -> 7 | R75: 1716488.3 | S75: =+R75-M75 -> 0
A76: 74 | B76: FERREYRA MARTIN | C76: 10 | D76: 2873 | E76: 46071 | F76: 1594.1 | G76: =+F76/D76 -> 0.55485555 | H76: 420 | J76: =+H76*F76 -> 669522 | K76: =$K$2*C76 -> 3927.8 | L76: =$L$2*C76 -> 5350 | M76: =+(J76*1.21)+K76+L76 -> 819399.42 | N76: 00004-00000447 | O76: 46073 | P76: 46081 | Q76: =+P76-O76 -> 8 | R76: 819399.42 | S76: =+R76-M76 -> 0
A77: 75 | B77: FERREYRA MARTIN | C77: 5 | D77: 1499 | E77: 46071 | F77: 862.1 | G77: =+F77/D77 -> 0.57511674 | H77: 420 | J77: =+H77*F77 -> 362082 | K77: =$K$2*C77 -> 1963.9 | L77: =$L$2*C77 -> 2675 | M77: =+(J77*1.21)+K77+L77 -> 442758.12 | N77: 00004-00000447 | O77: 46073 | P77: 46081 | Q77: =+P77-O77 -> 8 | R77: 442758.12 | S77: =+R77-M77 -> 0
A78: 76 | B78: BOSQUES AMADOS SRL | C78: 18 | D78: 6534 | E78: 46071 | F78: 3791.8 | G78: =+F78/D78 -> 0.58031833 | H78: 420 | J78: =+H78*F78 -> 1592556 | K78: =$K$2*C78 -> 7070.04 | L78: =$L$2*C78 -> 9630 | M78: =+(J78*1.21)+K78+L78 -> 1943692.8 | N78: 00004-00000446 | O78: 46072 | P78: 46084 | Q78: =+P78-O78 -> 12 | R78: 1943692.8 | S78: =+R78-M78 -> 0
A79: 77 | B79: FERREYRA MARTIN | C79: 15 | D79: 5197 | E79: 46071 | F79: 2916.3 | G79: =+F79/D79 -> 0.56115066 | H79: 420 | J79: =+H79*F79 -> 1224846 | K79: =$K$2*C79 -> 5891.7 | L79: =$L$2*C79 -> 8025 | M79: =+(J79*1.21)+K79+L79 -> 1495980.4 | N79: 00004-00000447 | O79: 46073 | P79: 46081 | Q79: =+P79-O79 -> 8 | R79: 1495980.4 | S79: =+R79-M79 -> 0
A80: 78 | B80: FERREYRA ALBERTO | C80: 8 | D80: 2616 | E80: 46073 | F80: 1465.5 | G80: =+F80/D80 -> 0.56020642 | H80: 420 | J80: =+H80*F80 -> 615510 | K80: =$K$2*C80 -> 3142.24 | L80: =$L$2*C80 -> 4280 | M80: =+(J80*1.21)+K80+L80 -> 752189.34 | N80: 00004-00000448 | O80: 46076 | P80: 46079 | Q80: =+P80-O80 -> 3 | R80: 752190 | S80: =+R80-M80 -> 0.66
A81: 79 | B81: MUCA SAS | C81: 20 | D81: 8461 | E81: 46073 | F81: 4954.8 | G81: =+F81/D81 -> 0.58560454 | H81: 420 | J81: =+H81*F81 -> 2081016 | K81: =$K$2*C81 -> 7855.6 | L81: =$L$2*C81 -> 10700 | M81: =+(J81*1.21)+K81+L81 -> 2536585 | N81: 00004-00000449 | O81: 46077 | Q81: =+P81-O81 -> -46077 | S81: =+R81-M81 -> -2536585
A82: 80 | B82: FRIGORIFICO DE LA PATAGONIA SRL | C82: 21 | D82: 7254 | E82: 46073 | F82: 4035.7 | G82: =+F82/D82 -> 0.55634133 | H82: 420 | J82: =+H82*F82 -> 1694994 | K82: =$K$2*C82 -> 8248.38 | L82: =$L$2*C82 -> 11235 | M82: =+(J82*1.21)+K82+L82 -> 2070426.1 | N82: 00004-00000450 | O82: 46077 | Q82: =+P82-O82 -> -46077 | S82: =+R82-M82 -> -2070426.1
A83: 81 | B83: FRIGORIFICO DE LA PATAGONIA SRL | C83: 15 | D83: 6056 | E83: 46073 | F83: 3378.4 | G83: =+F83/D83 -> 0.55785997 | H83: 420 | J83: =+H83*F83 -> 1418928 | K83: =$K$2*C83 -> 5891.7 | L83: =$L$2*C83 -> 8025 | M83: =+(J83*1.21)+K83+L83 -> 1730819.6 | N83: 00004-00000450 | O83: 46077 | Q83: =+P83-O83 -> -46077 | S83: =+R83-M83 -> -1730819.6
A84: 82 | B84: MAIZALES DE LA PATAGONIA SRL | C84: 15 | D84: 5629 | E84: 46073 | F84: 3097.6 | G84: =+F84/D84 -> 0.55029312 | H84: 420 | J84: =+H84*F84 -> 1300992 | K84: =$K$2*C84 -> 5891.7 | L84: =$L$2*C84 -> 8025 | M84: =+(J84*1.21)+K84+L84 -> 1588117 | N84: 00004-00000451 | O84: 46077 | P84: 46080 | Q84: =+P84-O84 -> 3 | R84: 1588117 | S84: =+R84-M84 -> 0
A85: 83 | B85: MAIZALES DE LA PATAGONIA SRL | C85: 15 | D85: 5306 | E85: 46073 | F85: 2910.6 | G85: =+F85/D85 -> 0.54854881 | H85: 420 | J85: =+H85*F85 -> 1222452 | K85: =$K$2*C85 -> 5891.7 | L85: =$L$2*C85 -> 8025 | M85: =+(J85*1.21)+K85+L85 -> 1493083.6 | N85: 00004-00000451 | O85: 46077 | P85: 46080 | Q85: =+P85-O85 -> 3 | R85: 1493083.6 | S85: =+R85-M85 -> 0
A86: 84 | B86: DOS DE FIERRO SA | C86: 21 | D86: 8105 | E86: 46076 | F86: 4552.4 | G86: =+F86/D86 -> 0.56167798 | H86: 420 | J86: =+H86*F86 -> 1912008 | K86: =$K$2*C86 -> 8248.38 | L86: =$L$2*C86 -> 11235 | M86: =+(J86*1.21)+K86+L86 -> 2333013.1 | N86: 00004-00000452 | O86: 46077 | P86: 46084 | Q86: =+P86-O86 -> 7 | R86: 2333013.1 | S86: =+R86-M86 -> 0
A87: 85 | B87: FERREYRA MARTIN | C87: 18 | D87: 6551 | E87: 46076 | F87: 3838.7 | G87: =+F87/D87 -> 0.58597161 | H87: 420 | J87: =+H87*F87 -> 1612254 | K87: =$K$2*C87 -> 7070.04 | L87: =$L$2*C87 -> 9630 | M87: =+(J87*1.21)+K87+L87 -> 1967527.4 | N87: 00004-00000453 | O87: 46077 | P87: 46085 | Q87: =+P87-O87 -> 8 | R87: 1967527.4 | S87: =+R87-M87 -> 0
A88: 86 | B88: MUCA SAS | C88: 50 | D88: 26239 | E88: 46077 | F88: 15497.2 | G88: =+F88/D88 -> 0.59061702 | H88: 420 | J88: =+H88*F88 -> 6508824 | K88: =$K$2*C88 -> 19639 | L88: =$L$2*C88 -> 26750 | M88: =+(J88*1.21)+K88+L88 -> 7922066 | N88: 00004-00000454 | O88: 46077 | Q88: =+P88-O88 -> -46077 | S88: =+R88-M88 -> -7922066
A89: 87 | B89: BOSQUES AMADOS SRL | C89: 18 | D89: 6703 | E89: 46077 | F89: 3790.6 | G89: =+F89/D89 -> 0.56550798 | H89: 420 | J89: =+H89*F89 -> 1592052 | K89: =$K$2*C89 -> 7070.04 | L89: =$L$2*C89 -> 9630 | M89: =+(J89*1.21)+K89+L89 -> 1943083 | N89: 00004-00000455 | O89: 46077 | Q89: =+P89-O89 -> -46077 | S89: =+R89-M89 -> -1943083
A90: 88 | B90: FERREYRA ALBERTO | C90: 8 | D90: 2367 | E90: 46078 | F90: 1321.4 | G90: =+F90/D90 -> 0.5582594 | H90: 420 | J90: =+H90*F90 -> 554988 | K90: =$K$2*C90 -> 3142.24 | L90: =$L$2*C90 -> 4280 | M90: =+(J90*1.21)+K90+L90 -> 678957.72 | N90: 00004-00000457 | O90: 46079 | Q90: =+P90-O90 -> -46079 | S90: =+R90-M90 -> -678957.72
A91: 89 | B91: FERREYRA MARTIN | C91: 7 | D91: 2687 | E91: 46078 | F91: 1494.8 | G91: =+F91/D91 -> 0.55630815 | H91: 420 | J91: =+H91*F91 -> 627816 | K91: =$K$2*C91 -> 2749.46 | L91: =$L$2*C91 -> 3745 | M91: =+(J91*1.21)+K91+L91 -> 766151.82 | N91: 00004-00000458 | O91: 46079 | Q91: =+P91-O91 -> -46079 | S91: =+R91-M91 -> -766151.82
A92: 90 | B92: FERREYRA MARTIN | C92: 11 | D92: 4591 | E92: 46078 | F92: 2726 | G92: =+F92/D92 -> 0.59377042 | H92: 420 | J92: =+H92*F92 -> 1144920 | K92: =$K$2*C92 -> 4320.58 | L92: =$L$2*C92 -> 5885 | M92: =+(J92*1.21)+K92+L92 -> 1395558.8 | N92: 00004-00000458 | O92: 46079 | Q92: =+P92-O92 -> -46079 | S92: =+R92-M92 -> -1395558.8
A93: 91 | B93: FRIGORIFICO DE LA PATAGONIA SRL | C93: 15 | D93: 5784 | E93: 46080 | F93: 3311.8 | G93: =+F93/D93 -> 0.57257953 | H93: 420 | J93: =+H93*F93 -> 1390956 | K93: =$K$2*C93 -> 5891.7 | L93: =$L$2*C93 -> 8025 | M93: =+(J93*1.21)+K93+L93 -> 1696973.5 | N93: 00004-00000460 | O93: 46080 | Q93: =+P93-O93 -> -46080 | S93: =+R93-M93 -> -1696973.5
A94: 92 | B94: MAIZALES DE LA PATAGONIA SRL | C94: 10 | D94: 3553 | E94: 46080 | F94: 2010 | G94: =+F94/D94 -> 0.56571911 | H94: 420 | J94: =+H94*F94 -> 844200 | K94: =$K$2*C94 -> 3927.8 | L94: =$L$2*C94 -> 5350 | M94: =+(J94*1.21)+K94+L94 -> 1030759.8 | N94: 00004-00000461 | O94: 46080 | Q94: =+P94-O94 -> -46080 | S94: =+R94-M94 -> -1030759.8
A95: 93 | B95: MAIZALES DE LA PATAGONIA SRL | C95: 20 | D95: 7512 | E95: 46080 | F95: 4121.3 | G95: =+F95/D95 -> 0.54862886 | H95: 420 | J95: =+H95*F95 -> 1730946 | K95: =$K$2*C95 -> 7855.6 | L95: =$L$2*C95 -> 10700 | M95: =+(J95*1.21)+K95+L95 -> 2113000.3 | N95: 00004-00000461 | O95: 46080 | Q95: =+P95-O95 -> -46080 | S95: =+R95-M95 -> -2113000.3
A96: 94 | B96: FRIGORIFICO DE LA PATAGONIA SRL | C96: 8 | D96: 3024 | E96: 46080 | F96: 1727.9 | G96: =+F96/D96 -> 0.5713955 | H96: 420 | J96: =+H96*F96 -> 725718 | K96: =$K$2*C96 -> 3142.24 | L96: =$L$2*C96 -> 4280 | M96: =+(J96*1.21)+K96+L96 -> 885541.02 | N96: 00004-00000460 | O96: 46080 | Q96: =+P96-O96 -> -46080 | S96: =+R96-M96 -> -885541.02
A97: 95 | B97: MUCA SAS | C97: 15 | D97: 6021 | E97: 46080 | F97: 3367.8 | G97: =+F97/D97 -> 0.5593423 | H97: 420 | J97: =+H97*F97 -> 1414476 | K97: =$K$2*C97 -> 5891.7 | L97: =$L$2*C97 -> 8025 | M97: =+(J97*1.21)+K97+L97 -> 1725432.7 | N97: 00004-00000462 | O97: 46080 | Q97: =+P97-O97 -> -46080 | S97: =+R97-M97 -> -1725432.7
A98: 96 | B98: FRIGORIFICO DE LA PATAGONIA SRL | C98: 22 | D98: 8567 | E98: 46080 | F98: 4885.3 | G98: =+F98/D98 -> 0.57024629 | H98: 420 | J98: =+H98*F98 -> 2051826 | K98: =$K$2*C98 -> 8641.16 | L98: =$L$2*C98 -> 11770 | M98: =+(J98*1.21)+K98+L98 -> 2503120.6 | N98: 00004-00000460 | O98: 46080 | Q98: =+P98-O98 -> -46080 | S98: =+R98-M98 -> -2503120.6
A99: 97 | B99: FERREYRA MARTIN | C99: 18 | D99: 4930 | E99: 46083 | F99: 2665.6 | G99: =+F99/D99 -> 0.54068966 | H99: 500 | J99: =+H99*F99 -> 1332800 | K99: =$K$2*C99 -> 7070.04 | L99: =$L$2*C99 -> 9630 | M99: =+(J99*1.21)+K99+L99 -> 1629388 | N99: 00004-00000463 | O99: 46083 | Q99: =+P99-O99 -> -46083 | S99: =+R99-M99 -> -1629388
... A102: 100 | B102: BOSQUES AMADOS SRL | C102: 18 | D102: 6219 | E102: 46084 | F102: 3494.7 | G102: =+F102/D102 -> 0.56193922 | H102: 500 | J102: =+H102*F102 -> 1747350 | K102: =$K$2*C102 -> 7070.04 | L102: =$L$2*C102 -> 9630 | M102: =+(J102*1.21)+K102+L102 -> 2130993.5 | N102: 00004-00000466 | O102: 46084 | Q102: =+P102-O102 -> -46084 | S102: =+R102-M102 -> -2130993.5
A103: 101 | B103: FERREYRA ALBERTO | C103: 8 | D103: 2542 | E103: 46085 | F103: 1416.4 | G103: =+F103/D103 -> 0.55719906 | H103: 500 | J103: =+H103*F103 -> 708200 | K103: =$K$2*C103 -> 3142.24 | L103: =$L$2*C103 -> 4280 | M103: =+(J103*1.21)+K103+L103 -> 864344.24 | Q103: =+P103-O103 -> 0 | S103: =+R103-M103 -> -864344.24
...

Sheet SERVICIO DESPOSTE
A1: Nº TROPA | B1: USUARIO | C1: FAENA | H1: SERVIO DESPOSTE
C2: Nº ANIMAL | D2: KG PIE | E2: FECHA FAENA | F2: KG GANCHO | G2: RINDE % | H2: 1/2 RES DER. | I2: 1/2 RES IZQ | J2: MERMA % | K2: KG ASADO | L2: KG DELANTERO | M2: KG TRASERO | N2: TOTAL KG ING. | O2: KG CARNE | P2: $/KG CARNE | Q2: KG CARNE C/H | R2: $/KG CARNE C/H | S2: HUESO | T2: GRASA | U2: RINDE | V2: DIF. +/- | W2: TOTAL FAC. | X2: TOTAL FAC. CON IMP. | Y2: Nº FAC. | Z2: FECHA FAC. | AA2: FECHA PAGO | AB2: Monto depositado | AC2: ESTADO
A3: =+'SERVICIO FAENA'!A3 -> 1 | B3: =+'SERVICIO FAENA'!B3 -> MORAGA | E3: =+'SERVICIO FAENA'!E3 -> 46024 | G3: =+F3/D3 -> #DIV/0! | J3: =+((F3-(H3+I3))/F3) -> #DIV/0! | N3: =SUM(K3:M3) -> 0 | P3: 880 | R3: 260 | W3: =+(P3*O3)+(R3*Q3) -> 0 | X3: =+((O3*P3)+(Q3*R3))*1.21 -> 0
A4: =+'SERVICIO FAENA'!A4 -> 2 | B4: =+'SERVICIO FAENA'!B4 -> GANADERA NORTE NEUQUINO | E4: =+'SERVICIO FAENA'!E4 -> 46024 | G4: =+F4/D4 -> #DIV/0! | J4: =+((F4-(H4+I4))/F4) -> #DIV/0! | N4: =SUM(K4:M4) -> 0 | P4: 880 | R4: 260 | W4: =+(P4*O4)+(R4*Q4) -> 0 | X4: =+((O4*P4)+(Q4*R4))*1.21 -> 0
A5: =+'SERVICIO FAENA'!A5 -> 3 | B5: =+'SERVICIO FAENA'!B5 -> GANADERA NORTE NEUQUINO | E5: =+'SERVICIO FAENA'!E5 -> 46027 | G5: =+F5/D5 -> #DIV/0! | J5: =+((F5-(H5+I5))/F5) -> #DIV/0! | N5: =SUM(K5:M5) -> 0 | P5: 880 | R5: 260 | W5: =+(P5*O5)+(R5*Q5) -> 0 | X5: =+((O5*P5)+(Q5*R5))*1.21 -> 0
A6: =+'SERVICIO FAENA'!A6 -> 4 | B6: =+'SERVICIO FAENA'!B6 -> DOS DE FIERRO SA | E6: =+'SERVICIO FAENA'!E6 -> 46027 | G6: =+F6/D6 -> #DIV/0! | J6: =+((F6-(H6+I6))/F6) -> #DIV/0! | N6: =SUM(K6:M6) -> 0 | P6: 880 | R6: 260 | W6: =+(P6*O6)+(R6*Q6) -> 0 | X6: =+((O6*P6)+(Q6*R6))*1.21 -> 0
A7: =+'SERVICIO FAENA'!A7 -> 5 | B7: =+'SERVICIO FAENA'!B7 -> DISTRIBUIDORA DE LA PATAGONIA | E7: =+'SERVICIO FAENA'!E7 -> 46027 | G7: =+F7/D7 -> #DIV/0! | J7: =+((F7-(H7+I7))/F7) -> #DIV/0! | N7: =SUM(K7:M7) -> 0 | P7: 880 | R7: 260 | W7: =+(P7*O7)+(R7*Q7) -> 0 | X7: =+((O7*P7)+(Q7*R7))*1.21 -> 0
A8: =+'SERVICIO FAENA'!A8 -> 6 | B8: =+'SERVICIO FAENA'!B8 -> DISTRIBUIDORA DE LA PATAGONIA | E8: =+'SERVICIO FAENA'!E8 -> 46028 | G8: =+F8/D8 -> #DIV/0! | J8: =+((F8-(H8+I8))/F8) -> #DIV/0! | N8: =SUM(K8:M8) -> 0 | P8: 880 | R8: 260 | W8: =+(P8*O8)+(R8*Q8) -> 0 | X8: =+((O8*P8)+(Q8*R8))*1.21 -> 0
A9: =+'SERVICIO FAENA'!A9 -> 7 | B9: =+'SERVICIO FAENA'!B9 -> MUCA SAS | E9: =+'SERVICIO FAENA'!E9 -> 46028 | G9: =+F9/D9 -> #DIV/0! | J9: =+((F9-(H9+I9))/F9) -> #DIV/0! | N9: =SUM(K9:M9) -> 0 | P9: 880 | R9: 260 | W9: =+(P9*O9)+(R9*Q9) -> 0 | X9: =+((O9*P9)+(Q9*R9))*1.21 -> 0
A10: =+'SERVICIO FAENA'!A10 -> 8 | B10: =+'SERVICIO FAENA'!B10 -> MUCA SAS | E10: =+'SERVICIO FAENA'!E10 -> 46028 | G10: =+F10/D10 -> #DIV/0! | J10: =+((F10-(H10+I10))/F10) -> #DIV/0! | N10: =SUM(K10:M10) -> 0 | P10: 880 | R10: 260 | W10: =+(P10*O10)+(R10*Q10) -> 0 | X10: =+((O10*P10)+(Q10*R10))*1.21 -> 0
A11: =+'SERVICIO FAENA'!A11 -> 9 | B11: =+'SERVICIO FAENA'!B11 -> MUCA SAS | E11: =+'SERVICIO FAENA'!E11 -> 46028 | G11: =+F11/D11 -> #DIV/0! | J11: =+((F11-(H11+I11))/F11) -> #DIV/0! | N11: =SUM(K11:M11) -> 0 | P11: 880 | R11: 260 | W11: =+(P11*O11)+(R11*Q11) -> 0 | X11: =+((O11*P11)+(Q11*R11))*1.21 -> 0
A12: =+'SERVICIO FAENA'!A12 -> 10 | B12: =+'SERVICIO FAENA'!B12 -> MORAGA | E12: =+'SERVICIO FAENA'!E12 -> 46028 | G12: =+F12/D12 -> #DIV/0! | J12: =+((F12-(H12+I12))/F12) -> #DIV/0! | N12: =SUM(K12:M12) -> 0 | P12: 880 | R12: 260 | W12: =+(P12*O12)+(R12*Q12) -> 0 | X12: =+((O12*P12)+(Q12*R12))*1.21 -> 0
A13: =+'SERVICIO FAENA'!A13 -> 11 | B13: =+'SERVICIO FAENA'!B13 -> FERREYRA MARTIN | E13: =+'SERVICIO FAENA'!E13 -> 46029 | G13: =+F13/D13 -> #DIV/0! | J13: =+((F13-(H13+I13))/F13) -> #DIV/0! | N13: =SUM(K13:M13) -> 0 | P13: 880 | R13: 260 | W13: =+(P13*O13)+(R13*Q13) -> 0 | X13: =+((O13*P13)+(Q13*R13))*1.21 -> 0
A14: =+'SERVICIO FAENA'!A14 -> 12 | B14: =+'SERVICIO FAENA'!B14 -> FERREYRA MARTIN | E14: =+'SERVICIO FAENA'!E14 -> 46029 | G14: =+F14/D14 -> #DIV/0! | J14: =+((F14-(H14+I14))/F14) -> #DIV/0! | N14: =SUM(K14:M14) -> 0 | P14: 880 | R14: 260 | W14: =+(P14*O14)+(R14*Q14) -> 0 | X14: =+((O14*P14)+(Q14*R14))*1.21 -> 0
... A40: =+'SERVICIO FAENA'!A40 -> 38 | B40: =+'SERVICIO FAENA'!B40 -> FRIGORIFICO DE LA PATAGONIA SRL | E40: =+'SERVICIO FAENA'!E40 -> 46048 | G40: =+F40/D40 -> #DIV/0! | J40: =+((F40-(H40+I40))/F40) -> #DIV/0! | N40: =SUM(K40:M40) -> 0 | P40: 880 | R40: 260 | W40: =+(P40*O40)+(R40*Q40) -> 0 | X40: =+((O40*P40)+(Q40*R40))*1.21 -> 0
A41: =+'SERVICIO FAENA'!A41 -> 39 | B41: =+'SERVICIO FAENA'!B41 -> BOSQUES AMADOS SRL | C41: 5 | D41: 2142 | E41: =+'SERVICIO FAENA'!E41 -> 46049 | F41: 1207.4 | G41: =+F41/D41 -> 0.5636788 | H41: 589.6 | I41: 594.9 | J41: =+((F41-(H41+I41))/F41) -> 0.018966374 | K41: 279.34 | L41: 351.02 | M41: 554.8 | N41: =SUM(K41:M41) -> 1185.16 | O41: 704.59 | P41: 880 | Q41: 279.34 | R41: 260 | S41: 192.7 | T41: 8 | U41: =+(Q41+O41)/N41 -> 0.83020858 | V41: =+(T41+S41+Q41+O41)-N41 -> -0.53 | W41: =+(P41*O41)+(R41*Q41) -> 692667.6 | X41: =+((O41*P41)+(Q41*R41))*1.21 -> 838127.8 | AC41: =+AB41-X41 -> -838127.8
A42: =+'SERVICIO FAENA'!A42 -> 40 | B42: =+'SERVICIO FAENA'!B42 -> MUCA SAS | E42: =+'SERVICIO FAENA'!E42 -> 46049 | G42: =+F42/D42 -> #DIV/0! | J42: =+((F42-(H42+I42))/F42) -> #DIV/0! | N42: =SUM(K42:M42) -> 0 | P42: 880 | R42: 260 | W42: =+(P42*O42)+(R42*Q42) -> 0 | X42: =+((O42*P42)+(Q42*R42))*1.21 -> 0
A43: =+'SERVICIO FAENA'!A43 -> 41 | B43: =+'SERVICIO FAENA'!B43 -> MUCA SAS | E43: =+'SERVICIO FAENA'!E43 -> 46049 | G43: =+F43/D43 -> #DIV/0! | J43: =+((F43-(H43+I43))/F43) -> #DIV/0! | N43: =SUM(K43:M43) -> 0 | P43: 880 | R43: 260 | W43: =+(P43*O43)+(R43*Q43) -> 0 | X43: =+((O43*P43)+(Q43*R43))*1.21 -> 0
A44: =+'SERVICIO FAENA'!A44 -> 42 | B44: =+'SERVICIO FAENA'!B44 -> FERREYRA MARTIN | E44: =+'SERVICIO FAENA'!E44 -> 46050 | G44: =+F44/D44 -> #DIV/0! | J44: =+((F44-(H44+I44))/F44) -> #DIV/0! | N44: =SUM(K44:M44) -> 0 | P44: 880 | R44: 260 | W44: =+(P44*O44)+(R44*Q44) -> 0 | X44: =+((O44*P44)+(Q44*R44))*1.21 -> 0
A45: =+'SERVICIO FAENA'!A45 -> 43 | B45: =+'SERVICIO FAENA'!B45 -> FERREYRA MARTIN | E45: =+'SERVICIO FAENA'!E45 -> 46050 | G45: =+F45/D45 -> #DIV/0! | J45: =+((F45-(H45+I45))/F45) -> #DIV/0! | N45: =SUM(K45:M45) -> 0 | P45: 880 | R45: 260 | W45: =+(P45*O45)+(R45*Q45) -> 0 | X45: =+((O45*P45)+(Q45*R45))*1.21 -> 0
A46: =+'SERVICIO FAENA'!A46 -> 44 | B46: =+'SERVICIO FAENA'!B46 -> FERREYRA ALBERTO | E46: =+'SERVICIO FAENA'!E46 -> 46050 | G46: =+F46/D46 -> #DIV/0! | J46: =+((F46-(H46+I46))/F46) -> #DIV/0! | N46: =SUM(K46:M46) -> 0 | P46: 880 | R46: 260 | W46: =+(P46*O46)+(R46*Q46) -> 0 | X46: =+((O46*P46)+(Q46*R46))*1.21 -> 0
A47: =+'SERVICIO FAENA'!A47 -> 45 | B47: =+'SERVICIO FAENA'!B47 -> FRIGORIFICO DE LA PATAGONIA SRL | E47: =+'SERVICIO FAENA'!E47 -> 46052 | G47: =+F47/D47 -> #DIV/0! | J47: =+((F47-(H47+I47))/F47) -> #DIV/0! | N47: =SUM(K47:M47) -> 0 | P47: 880 | R47: 260 | W47: =+(P47*O47)+(R47*Q47) -> 0 | X47: =+((O47*P47)+(Q47*R47))*1.21 -> 0
A48: =+'SERVICIO FAENA'!A48 -> 46 | B48: =+'SERVICIO FAENA'!B48 -> FRIGORIFICO DE LA PATAGONIA SRL | E48: =+'SERVICIO FAENA'!E48 -> 46052 | G48: =+F48/D48 -> #DIV/0! | J48: =+((F48-(H48+I48))/F48) -> #DIV/0! | N48: =SUM(K48:M48) -> 0 | P48: 880 | R48: 260 | W48: =+(P48*O48)+(R48*Q48) -> 0 | X48: =+((O48*P48)+(Q48*R48))*1.21 -> 0
A49: =+'SERVICIO FAENA'!A49 -> 47 | B49: =+'SERVICIO FAENA'!B49 -> MUCA SAS | E49: =+'SERVICIO FAENA'!E49 -> 46052 | G49: =+F49/D49 -> #DIV/0! | J49: =+((F49-(H49+I49))/F49) -> #DIV/0! | N49: =SUM(K49:M49) -> 0 | P49: 880 | R49: 260 | W49: =+(P49*O49)+(R49*Q49) -> 0 | X49: =+((O49*P49)+(Q49*R49))*1.21 -> 0
A50: =+'SERVICIO FAENA'!A50 -> 48 | B50: =+'SERVICIO FAENA'!B50 -> MUCA SAS | E50: =+'SERVICIO FAENA'!E50 -> 46052 | G50: =+F50/D50 -> #DIV/0! | J50: =+((F50-(H50+I50))/F50) -> #DIV/0! | N50: =SUM(K50:M50) -> 0 | P50: 880 | R50: 260 | W50: =+(P50*O50)+(R50*Q50) -> 0 | X50: =+((O50*P50)+(Q50*R50))*1.21 -> 0
A51: =+'SERVICIO FAENA'!A51 -> 49 | B51: =+'SERVICIO FAENA'!B51 -> MUCA SAS | E51: =+'SERVICIO FAENA'!E51 -> 46052 | G51: =+F51/D51 -> #DIV/0! | J51: =+((F51-(H51+I51))/F51) -> #DIV/0! | N51: =SUM(K51:M51) -> 0 | P51: 880 | R51: 260 | W51: =+(P51*O51)+(R51*Q51) -> 0 | X51: =+((O51*P51)+(Q51*R51))*1.21 -> 0
A52: =+'SERVICIO FAENA'!A52 -> 50 | B52: =+'SERVICIO FAENA'!B52 -> MUCA SAS | E52: =+'SERVICIO FAENA'!E52 -> 46052 | G52: =+F52/D52 -> #DIV/0! | J52: =+((F52-(H52+I52))/F52) -> #DIV/0! | N52: =SUM(K52:M52) -> 0 | P52: 880 | R52: 260 | W52: =+(P52*O52)+(R52*Q52) -> 0 | X52: =+((O52*P52)+(Q52*R52))*1.21 -> 0
A53: =+'SERVICIO FAENA'!A53 -> 51 | B53: =+'SERVICIO FAENA'!B53 -> GANADERA NORTE NEUQUINO | E53: =+'SERVICIO FAENA'!E53 -> 46055 | G53: =+F53/D53 -> #DIV/0! | J53: =+((F53-(H53+I53))/F53) -> #DIV/0! | N53: =SUM(K53:M53) -> 0 | P53: 880 | R53: 260 | W53: =+(P53*O53)+(R53*Q53) -> 0 | X53: =+((O53*P53)+(Q53*R53))*1.21 -> 0
... A86: =+'SERVICIO FAENA'!A86 -> 84 | B86: =+'SERVICIO FAENA'!B86 -> DOS DE FIERRO SA | E86: =+'SERVICIO FAENA'!E86 -> 46076 | G86: =+F86/D86 -> #DIV/0! | J86: =+((F86-(H86+I86))/F86) -> #DIV/0! | N86: =SUM(K86:M86) -> 0 | P86: 880 | R86: 260 | W86: =+(P86*O86)+(R86*Q86) -> 0 | X86: =+((O86*P86)+(Q86*R86))*1.21 -> 0
A87: =+'SERVICIO FAENA'!A87 -> 85 | B87: =+'SERVICIO FAENA'!B87 -> FERREYRA MARTIN | C87: 7.5 | D87: 3322 | E87: =+'SERVICIO FAENA'!E87 -> 46076 | F87: 1884.7 | G87: =+F87/D87 -> 0.56733895 | H87: 862.4 | I87: 975.4 | J87: =+((F87-(H87+I87))/F87) -> 0.024884597 | K87: 420.56 | L87: 257.3 | M87: 1158.4 | N87: =SUM(K87:M87) -> 1836.26 | O87: 1183.49 | P87: 880 | Q87: 412.4 | R87: 260 | S87: 236.5 | T87: 3 | U87: =+(Q87+O87)/N87 -> 0.86909806 | V87: =+(T87+S87+Q87+O87)-N87 -> -0.87 | W87: =+(P87*O87)+(R87*Q87) -> 1148695.2 | X87: =+((O87*P87)+(Q87*R87))*1.21 -> 1389921.2
A88: =+'SERVICIO FAENA'!A88 -> 86 | B88: =+'SERVICIO FAENA'!B88 -> MUCA SAS | E88: =+'SERVICIO FAENA'!E88 -> 46077 | G88: =+F88/D88 -> #DIV/0! | J88: =+((F88-(H88+I88))/F88) -> #DIV/0! | N88: =SUM(K88:M88) -> 0 | P88: 880 | R88: 260 | W88: =+(P88*O88)+(R88*Q88) -> 0 | X88: =+((O88*P88)+(Q88*R88))*1.21 -> 0
A89: =+'SERVICIO FAENA'!A89 -> 87 | B89: =+'SERVICIO FAENA'!B89 -> BOSQUES AMADOS SRL | E89: =+'SERVICIO FAENA'!E89 -> 46077 | G89: =+F89/D89 -> #DIV/0! | J89: =+((F89-(H89+I89))/F89) -> #DIV/0! | N89: =SUM(K89:M89) -> 0 | P89: 880 | R89: 260 | W89: =+(P89*O89)+(R89*Q89) -> 0 | X89: =+((O89*P89)+(Q89*R89))*1.21 -> 0
A90: =+'SERVICIO FAENA'!A90 -> 88 | B90: =+'SERVICIO FAENA'!B90 -> FERREYRA ALBERTO | E90: =+'SERVICIO FAENA'!E90 -> 46078 | G90: =+F90/D90 -> #DIV/0! | J90: =+((F90-(H90+I90))/F90) -> #DIV/0! | N90: =SUM(K90:M90) -> 0 | P90: 880 | R90: 260 | W90: =+(P90*O90)+(R90*Q90) -> 0 | X90: =+((O90*P90)+(Q90*R90))*1.21 -> 0
A91: =+'SERVICIO FAENA'!A91 -> 89 | B91: =+'SERVICIO FAENA'!B91 -> FERREYRA MARTIN | E91: =+'SERVICIO FAENA'!E91 -> 46078 | G91: =+F91/D91 -> #DIV/0! | J91: =+((F91-(H91+I91))/F91) -> #DIV/0! | N91: =SUM(K91:M91) -> 0 | P91: 880 | R91: 260 | W91: =+(P91*O91)+(R91*Q91) -> 0 | X91: =+((O91*P91)+(Q91*R91))*1.21 -> 0
A92: =+'SERVICIO FAENA'!A92 -> 90 | B92: =+'SERVICIO FAENA'!B92 -> FERREYRA MARTIN | E92: =+'SERVICIO FAENA'!E92 -> 46078 | G92: =+F92/D92 -> #DIV/0! | J92: =+((F92-(H92+I92))/F92) -> #DIV/0! | N92: =SUM(K92:M92) -> 0 | P92: 880 | R92: 260 | W92: =+(P92*O92)+(R92*Q92) -> 0 | X92: =+((O92*P92)+(Q92*R92))*1.21 -> 0
A93: =+'SERVICIO FAENA'!A93 -> 91 | B93: =+'SERVICIO FAENA'!B93 -> FRIGORIFICO DE LA PATAGONIA SRL | E93: =+'SERVICIO FAENA'!E93 -> 46080 | G93: =+F93/D93 -> #DIV/0! | J93: =+((F93-(H93+I93))/F93) -> #DIV/0! | N93: =SUM(K93:M93) -> 0 | P93: 880 | R93: 260 | W93: =+(P93*O93)+(R93*Q93) -> 0 | X93: =+((O93*P93)+(Q93*R93))*1.21 -> 0
A94: =+'SERVICIO FAENA'!A94 -> 92 | B94: =+'SERVICIO FAENA'!B94 -> MAIZALES DE LA PATAGONIA SRL | E94: =+'SERVICIO FAENA'!E94 -> 46080 | G94: =+F94/D94 -> #DIV/0! | J94: =+((F94-(H94+I94))/F94) -> #DIV/0! | N94: =SUM(K94:M94) -> 0 | P94: 880 | R94: 260 | W94: =+(P94*O94)+(R94*Q94) -> 0 | X94: =+((O94*P94)+(Q94*R94))*1.21 -> 0
A95: =+'SERVICIO FAENA'!A95 -> 93 | B95: =+'SERVICIO FAENA'!B95 -> MAIZALES DE LA PATAGONIA SRL | E95: =+'SERVICIO FAENA'!E95 -> 46080 | G95: =+F95/D95 -> #DIV/0! | J95: =+((F95-(H95+I95))/F95) -> #DIV/0! | N95: =SUM(K95:M95) -> 0 | P95: 880 | R95: 260 | W95: =+(P95*O95)+(R95*Q95) -> 0 | X95: =+((O95*P95)+(Q95*R95))*1.21 -> 0
A96: =+'SERVICIO FAENA'!A96 -> 94 | B96: =+'SERVICIO FAENA'!B96 -> FRIGORIFICO DE LA PATAGONIA SRL | E96: =+'SERVICIO FAENA'!E96 -> 46080 | G96: =+F96/D96 -> #DIV/0! | J96: =+((F96-(H96+I96))/F96) -> #DIV/0! | N96: =SUM(K96:M96) -> 0 | P96: 880 | R96: 260 | W96: =+(P96*O96)+(R96*Q96) -> 0 | X96: =+((O96*P96)+(Q96*R96))*1.21 -> 0
A97: =+'SERVICIO FAENA'!A97 -> 95 | B97: =+'SERVICIO FAENA'!B97 -> MUCA SAS | E97: =+'SERVICIO FAENA'!E97 -> 46080 | G97: =+F97/D97 -> #DIV/0! | J97: =+((F97-(H97+I97))/F97) -> #DIV/0! | N97: =SUM(K97:M97) -> 0 | P97: 880 | R97: 260 | W97: =+(P97*O97)+(R97*Q97) -> 0 | X97: =+((O97*P97)+(Q97*R97))*1.21 -> 0
A98: =+'SERVICIO FAENA'!A98 -> 96 | B98: =+'SERVICIO FAENA'!B98 -> FRIGORIFICO DE LA PATAGONIA SRL | E98: =+'SERVICIO FAENA'!E98 -> 46080 | G98: =+F98/D98 -> #DIV/0! | J98: =+((F98-(H98+I98))/F98) -> #DIV/0! | N98: =SUM(K98:M98) -> 0 | P98: 880 | R98: 260 | W98: =+(P98*O98)+(R98*Q98) -> 0 | X98: =+((O98*P98)+(Q98*R98))*1.21 -> 0
A99: =+'SERVICIO FAENA'!A99 -> 97 | B99: =+'SERVICIO FAENA'!B99 -> FERREYRA MARTIN | E99: =+'SERVICIO FAENA'!E99 -> 46083 | G99: =+F99/D99 -> #DIV/0! | J99: =+((F99-(H99+I99))/F99) -> #DIV/0! | N99: =SUM(K99:M99) -> 0 | P99: 880 | R99: 260 | W99: =+(P99*O99)+(R99*Q99) -> 0 | X99: =+((O99*P99)+(Q99*R99))*1.21 -> 0
... A893: =+'SERVICIO FAENA'!A893 -> 0 | B893: =+'SERVICIO FAENA'!B893 -> 0 | E893: =+'SERVICIO FAENA'!E893 -> 0 | G893: =+F893/D893 -> #DIV/0! | J893: =+((F893-(H893+I893))/F893) -> #DIV/0! | N893: =SUM(K893:M893) -> 0 | P893: 880 | R893: 260 | W893: =+(P893*O893)+(R893*Q893) -> 0 | X893: =+((O893*P893)+(Q893*R893))*1.21 -> 0

Sheet MENUDENCIAS
G1: AREA COMPRAS | K1: AREA VENTA
A2: Nº TROPA | B2: USUARIO | C2: CANTIDAD ANIMALES | D2: KG ACHURAS | E2: KG ACHURAS Decomisadas | F2: KG LAVADITO | G2: VALOR POR KG | H2: VALOR POR UNIDAD | I2: TOTAL FACTURA COMPRA | J2: Nº FACTURA | K2: $/KG + 10.5 IVA | L2: TOTAL | M2: CLIENTE | N2: Nº FACTURA | O2: TOTAL $ FACTURA S/IVA | P2: TOTAL $ FACTURA C/IVA | Q2: FECHA DE PAGO | R2: MONTO DEPOSITADO | S2: ESTADO | T2: OBSERVACIONES
A3: =+'SERVICIO FAENA'!A3 -> 1 | B3: =+'SERVICIO FAENA'!B3 -> MORAGA | C3: =+'SERVICIO FAENA'!C3 -> 15 | D3: 209.1 | E3: 9.96 | L3: =+K3*F3 -> 0 | O3: =+K3*F3 -> 0 | P3: =+(L3*10.5/100)+L3 -> 0 | R3: 0 | S3: =+R3-P3 -> 0
A4: =+'SERVICIO FAENA'!A4 -> 2 | B4: =+'SERVICIO FAENA'!B4 -> GANADERA NORTE NEUQUINO | C4: =+'SERVICIO FAENA'!C4 -> 43 | D4: 677.88 | E4: 1.64 | L4: =+K4*F4 -> 0 | O4: =+K4*F4 -> 0 | P4: =+(L4*10.5/100)+L4 -> 0 | R4: 0 | S4: =+R4-P4 -> 0
A5: =+'SERVICIO FAENA'!A5 -> 3 | B5: =+'SERVICIO FAENA'!B5 -> GANADERA NORTE NEUQUINO | C5: =+'SERVICIO FAENA'!C5 -> 40 | D5: 562.14 | E5: 59.08 | L5: =+K5*F5 -> 0 | O5: =+K5*F5 -> 0 | P5: =+(L5*10.5/100)+L5 -> 0 | R5: 0 | S5: =+R5-P5 -> 0
A6: =+'SERVICIO FAENA'!A6 -> 4 | B6: =+'SERVICIO FAENA'!B6 -> DOS DE FIERRO SA | C6: =+'SERVICIO FAENA'!C6 -> 25 | D6: 403.98 | E6: 5.9 | L6: =+K6*F6 -> 0 | O6: =+K6*F6 -> 0 | P6: =+(L6*10.5/100)+L6 -> 0 | R6: 0 | S6: =+R6-P6 -> 0
A7: =+'SERVICIO FAENA'!A7 -> 5 | B7: =+'SERVICIO FAENA'!B7 -> DISTRIBUIDORA DE LA PATAGONIA | C7: =+'SERVICIO FAENA'!C7 -> 30 | D7: 450.62 | E7: 49.86 | L7: =+K7*F7 -> 0 | O7: =+K7*F7 -> 0 | P7: =+(L7*10.5/100)+L7 -> 0 | R7: 0 | S7: =+R7-P7 -> 0
A8: =+'SERVICIO FAENA'!A8 -> 6 | B8: =+'SERVICIO FAENA'!B8 -> DISTRIBUIDORA DE LA PATAGONIA | C8: =+'SERVICIO FAENA'!C8 -> 15 | D8: 214.99 | E8: 4.58 | L8: =+K8*F8 -> 0 | O8: =+K8*F8 -> 0 | P8: =+(L8*10.5/100)+L8 -> 0 | R8: 0 | S8: =+R8-P8 -> 0
A9: =+'SERVICIO FAENA'!A9 -> 7 | B9: =+'SERVICIO FAENA'!B9 -> MUCA SAS | C9: =+'SERVICIO FAENA'!C9 -> 35 | D9: 998.84 | E9: 15.84 | L9: =+K9*F9 -> 0 | O9: =+K9*F9 -> 0 | P9: =+(L9*10.5/100)+L9 -> 0 | R9: 0 | S9: =+R9-P9 -> 0
A10: =+'SERVICIO FAENA'!A10 -> 8 | B10: =+'SERVICIO FAENA'!B10 -> MUCA SAS | C10: =+'SERVICIO FAENA'!C10 -> 5 | L10: =+K10*F10 -> 0 | O10: =+K10*F10 -> 0 | P10: =+(L10*10.5/100)+L10 -> 0 | R10: 0 | S10: =+R10-P10 -> 0
A11: =+'SERVICIO FAENA'!A11 -> 9 | B11: =+'SERVICIO FAENA'!B11 -> MUCA SAS | C11: =+'SERVICIO FAENA'!C11 -> 10 | L11: =+K11*F11 -> 0 | O11: =+K11*F11 -> 0 | P11: =+(L11*10.5/100)+L11 -> 0 | R11: 0 | S11: =+R11-P11 -> 0
A12: =+'SERVICIO FAENA'!A12 -> 10 | B12: =+'SERVICIO FAENA'!B12 -> MORAGA | C12: =+'SERVICIO FAENA'!C12 -> 15 | D12: 243.74 | E12: 11.26 | L12: =+K12*F12 -> 0 | O12: =+K12*F12 -> 0 | P12: =+(L12*10.5/100)+L12 -> 0 | R12: 0 | S12: =+R12-P12 -> 0
A13: =+'SERVICIO FAENA'!A13 -> 11 | B13: =+'SERVICIO FAENA'!B13 -> FERREYRA MARTIN | C13: =+'SERVICIO FAENA'!C13 -> 20 | D13: 285.5 | E13: 23.78 | L13: =+K13*F13 -> 0 | O13: =+K13*F13 -> 0 | P13: =+(L13*10.5/100)+L13 -> 0 | R13: 0 | S13: =+R13-P13 -> 0
A14: =+'SERVICIO FAENA'!A14 -> 12 | B14: =+'SERVICIO FAENA'!B14 -> FERREYRA MARTIN | C14: =+'SERVICIO FAENA'!C14 -> 3 | L14: =+K14*F14 -> 0 | O14: =+K14*F14 -> 0 | P14: =+(L14*10.5/100)+L14 -> 0 | R14: 0 | S14: =+R14-P14 -> 0
A15: =+'SERVICIO FAENA'!A15 -> 13 | B15: =+'SERVICIO FAENA'!B15 -> GANADERA NORTE NEUQUINO | C15: =+'SERVICIO FAENA'!C15 -> 40 | D15: 680.64 | E15: 43.88 | L15: =+K15*F15 -> 0 | O15: =+K15*F15 -> 0 | P15: =+(L15*10.5/100)+L15 -> 0 | R15: 0 | S15: =+R15-P15 -> 0
A16: =+'SERVICIO FAENA'!A16 -> 14 | B16: =+'SERVICIO FAENA'!B16 -> FRIGORIFICO DE LA PATAGONIA SRL | C16: =+'SERVICIO FAENA'!C16 -> 35 | D16: 475.76 | L16: =+K16*F16 -> 0 | O16: =+K16*F16 -> 0 | P16: =+(L16*10.5/100)+L16 -> 0 | R16: 0 | S16: =+R16-P16 -> 0
A17: =+'SERVICIO FAENA'!A17 -> 15 | B17: =+'SERVICIO FAENA'!B17 -> GANADERA NORTE NEUQUINO | C17: =+'SERVICIO FAENA'!C17 -> 46 | D17: 680.32 | E17: 7.34 | L17: =+K17*F17 -> 0 | O17: =+K17*F17 -> 0 | P17: =+(L17*10.5/100)+L17 -> 0 | R17: 0 | S17: =+R17-P17 -> 0
A18: =+'SERVICIO FAENA'!A18 -> 16 | B18: =+'SERVICIO FAENA'!B18 -> MORAGA | C18: =+'SERVICIO FAENA'!C18 -> 15 | D18: 262.52 | L18: =+K18*F18 -> 0 | O18: =+K18*F18 -> 0 | P18: =+(L18*10.5/100)+L18 -> 0 | R18: 0 | S18: =+R18-P18 -> 0
A19: =+'SERVICIO FAENA'!A19 -> 17 | B19: =+'SERVICIO FAENA'!B19 -> LASAGNO JORGE ALBERTO | C19: =+'SERVICIO FAENA'!C19 -> 17 | D19: 278.78 | E19: 4.34 | L19: =+K19*F19 -> 0 | O19: =+K19*F19 -> 0 | P19: =+(L19*10.5/100)+L19 -> 0 | R19: 0 | S19: =+R19-P19 -> 0
A20: =+'SERVICIO FAENA'!A20 -> 18 | B20: =+'SERVICIO FAENA'!B20 -> GANADERA NORTE NEUQUINO | C20: =+'SERVICIO FAENA'!C20 -> 43 | D20: 640.84 | E20: 8.82 | L20: =+K20*F20 -> 0 | O20: =+K20*F20 -> 0 | P20: =+(L20*10.5/100)+L20 -> 0 | R20: 0 | S20: =+R20-P20 -> 0
A21: =+'SERVICIO FAENA'!A21 -> 19 | B21: =+'SERVICIO FAENA'!B21 -> DOS DE FIERRO SA | C21: =+'SERVICIO FAENA'!C21 -> 25 | D21: 230.52 | E21: 4.64 | L21: =+K21*F21 -> 0 | O21: =+K21*F21 -> 0 | P21: =+(L21*10.5/100)+L21 -> 0 | R21: 0 | S21: =+R21-P21 -> 0
A22: =+'SERVICIO FAENA'!A22 -> 20 | B22: =+'SERVICIO FAENA'!B22 -> FERREYRA MARTIN | C22: =+'SERVICIO FAENA'!C22 -> 15 | D22: 374.6 | L22: =+K22*F22 -> 0 | O22: =+K22*F22 -> 0 | P22: =+(L22*10.5/100)+L22 -> 0 | R22: 0 | S22: =+R22-P22 -> 0
A23: =+'SERVICIO FAENA'!A23 -> 21 | B23: =+'SERVICIO FAENA'!B23 -> MUCA SAS | C23: =+'SERVICIO FAENA'!C23 -> 8 | D23: 402.22 | E23: 8.76 | L23: =+K23*F23 -> 0 | O23: =+K23*F23 -> 0 | P23: =+(L23*10.5/100)+L23 -> 0 | R23: 0 | S23: =+R23-P23 -> 0
A24: =+'SERVICIO FAENA'!A24 -> 22 | B24: =+'SERVICIO FAENA'!B24 -> MUCA SAS | C24: =+'SERVICIO FAENA'!C24 -> 7 | L24: =+K24*F24 -> 0 | O24: =+K24*F24 -> 0 | P24: =+(L24*10.5/100)+L24 -> 0 | R24: 0 | S24: =+R24-P24 -> 0
A25: =+'SERVICIO FAENA'!A25 -> 23 | B25: =+'SERVICIO FAENA'!B25 -> MUCA SAS | C25: =+'SERVICIO FAENA'!C25 -> 5 | L25: =+K25*F25 -> 0 | O25: =+K25*F25 -> 0 | P25: =+(L25*10.5/100)+L25 -> 0 | R25: 0 | S25: =+R25-P25 -> 0
A26: =+'SERVICIO FAENA'!A26 -> 24 | B26: =+'SERVICIO FAENA'!B26 -> FERREYRA MARTIN | C26: =+'SERVICIO FAENA'!C26 -> 30 | D26: 442.84 | E26: 20.28 | L26: =+K26*F26 -> 0 | O26: =+K26*F26 -> 0 | P26: =+(L26*10.5/100)+L26 -> 0 | R26: 0 | S26: =+R26-P26 -> 0
A27: =+'SERVICIO FAENA'!A27 -> 25 | B27: =+'SERVICIO FAENA'!B27 -> FERREYRA ALBERTO | C27: =+'SERVICIO FAENA'!C27 -> 6 | D27: 86.58 | E27: 4.98 | L27: =+K27*F27 -> 0 | O27: =+K27*F27 -> 0 | P27: =+(L27*10.5/100)+L27 -> 0 | R27: 0 | S27: =+R27-P27 -> 0
A28: =+'SERVICIO FAENA'!A28 -> 26 | B28: =+'SERVICIO FAENA'!B28 -> FRIGORIFICO DE LA PATAGONIA SRL | C28: =+'SERVICIO FAENA'!C28 -> 50 | D28: 831.32 | E28: 19.08 | L28: =+K28*F28 -> 0 | O28: =+K28*F28 -> 0 | P28: =+(L28*10.5/100)+L28 -> 0 | R28: 0 | S28: =+R28-P28 -> 0
A29: =+'SERVICIO FAENA'!A29 -> 27 | B29: =+'SERVICIO FAENA'!B29 -> GANADERA NORTE NEUQUINO | C29: =+'SERVICIO FAENA'!C29 -> 40 | D29: 669.82 | E29: 29.4 | L29: =+K29*F29 -> 0 | O29: =+K29*F29 -> 0 | P29: =+(L29*10.5/100)+L29 -> 0 | R29: 0 | S29: =+R29-P29 -> 0
A30: =+'SERVICIO FAENA'!A30 -> 28 | B30: =+'SERVICIO FAENA'!B30 -> DOS DE FIERRO SA | C30: =+'SERVICIO FAENA'!C30 -> 26 | D30: 417.6 | E30: 9.84 | L30: =+K30*F30 -> 0 | O30: =+K30*F30 -> 0 | P30: =+(L30*10.5/100)+L30 -> 0 | R30: 0 | S30: =+R30-P30 -> 0
A31: =+'SERVICIO FAENA'!A31 -> 29 | B31: =+'SERVICIO FAENA'!B31 -> FERREYRA MARTIN | C31: =+'SERVICIO FAENA'!C31 -> 15 | D31: 210.28 | E31: 19.62 | L31: =+K31*F31 -> 0 | O31: =+K31*F31 -> 0 | P31: =+(L31*10.5/100)+L31 -> 0 | R31: 0 | S31: =+R31-P31 -> 0
A32: =+'SERVICIO FAENA'!A32 -> 30 | B32: =+'SERVICIO FAENA'!B32 -> BOSQUES AMADOS SRL | C32: =+'SERVICIO FAENA'!C32 -> 18 | D32: 255.58 | E32: 13.22 | L32: =+K32*F32 -> 0 | O32: =+K32*F32 -> 0 | P32: =+(L32*10.5/100)+L32 -> 0 | R32: 0 | S32: =+R32-P32 -> 0
A33: =+'SERVICIO FAENA'!A33 -> 31 | B33: =+'SERVICIO FAENA'!B33 -> MUCA SAS | C33: =+'SERVICIO FAENA'!C33 -> 50 | D33: 911.38 | E33: 12.96 | L33: =+K33*F33 -> 0 | O33: =+K33*F33 -> 0 | P33: =+(L33*10.5/100)+L33 -> 0 | R33: 0 | S33: =+R33-P33 -> 0
A34: =+'SERVICIO FAENA'!A34 -> 32 | B34: =+'SERVICIO FAENA'!B34 -> FERREYRA ALBERTO | C34: =+'SERVICIO FAENA'!C34 -> 8 | D34: 115.54 | L34: =+K34*F34 -> 0 | O34: =+K34*F34 -> 0 | P34: =+(L34*10.5/100)+L34 -> 0 | R34: 0 | S34: =+R34-P34 -> 0
A35: =+'SERVICIO FAENA'!A35 -> 33 | B35: =+'SERVICIO FAENA'!B35 -> FERREYRA MARTIN | C35: =+'SERVICIO FAENA'!C35 -> 20 | D35: 276.88 | E35: 35.34 | L35: =+K35*F35 -> 0 | O35: =+K35*F35 -> 0 | P35: =+(L35*10.5/100)+L35 -> 0 | R35: 0 | S35: =+R35-P35 -> 0
A36: =+'SERVICIO FAENA'!A36 -> 34 | B36: =+'SERVICIO FAENA'!B36 -> FRIGORIFICO DE LA PATAGONIA SRL | C36: =+'SERVICIO FAENA'!C36 -> 15 | D36: 246.74 | L36: =+K36*F36 -> 0 | O36: =+K36*F36 -> 0 | P36: =+(L36*10.5/100)+L36 -> 0 | R36: 0 | S36: =+R36-P36 -> 0
A37: =+'SERVICIO FAENA'!A37 -> 35 | B37: =+'SERVICIO FAENA'!B37 -> MUCA SAS | C37: =+'SERVICIO FAENA'!C37 -> 13 | D37: 467 | E37: 43.28 | L37: =+K37*F37 -> 0 | O37: =+K37*F37 -> 0 | P37: =+(L37*10.5/100)+L37 -> 0 | R37: 0 | S37: =+R37-P37 -> 0
A38: =+'SERVICIO FAENA'!A38 -> 36 | B38: =+'SERVICIO FAENA'!B38 -> MUCA SAS | C38: =+'SERVICIO FAENA'!C38 -> 15 | L38: =+K38*F38 -> 0 | O38: =+K38*F38 -> 0 | P38: =+(L38*10.5/100)+L38 -> 0 | R38: 0 | S38: =+R38-P38 -> 0
A39: =+'SERVICIO FAENA'!A39 -> 37 | B39: =+'SERVICIO FAENA'!B39 -> FERREYRA MARTIN | C39: =+'SERVICIO FAENA'!C39 -> 15 | D39: 188.44 | E39: 4.8 | L39: =+K39*F39 -> 0 | O39: =+K39*F39 -> 0 | P39: =+(L39*10.5/100)+L39 -> 0 | R39: 0 | S39: =+R39-P39 -> 0
A40: =+'SERVICIO FAENA'!A40 -> 38 | B40: =+'SERVICIO FAENA'!B40 -> FRIGORIFICO DE LA PATAGONIA SRL | C40: =+'SERVICIO FAENA'!C40 -> 26 | D40: 435.16 | E40: 10.1 | L40: =+K40*F40 -> 0 | O40: =+K40*F40 -> 0 | P40: =+(L40*10.5/100)+L40 -> 0 | R40: 0 | S40: =+R40-P40 -> 0
A41: =+'SERVICIO FAENA'!A41 -> 39 | B41: =+'SERVICIO FAENA'!B41 -> BOSQUES AMADOS SRL | C41: =+'SERVICIO FAENA'!C41 -> 18 | D41: 312.78 | E41: 6.48 | L41: =+K41*F41 -> 0 | O41: =+K41*F41 -> 0 | P41: =+(L41*10.5/100)+L41 -> 0 | R41: 0 | S41: =+R41-P41 -> 0
A42: =+'SERVICIO FAENA'!A42 -> 40 | B42: =+'SERVICIO FAENA'!B42 -> MUCA SAS | C42: =+'SERVICIO FAENA'!C42 -> 31 | D42: 653.4 | E42: 83.86 | L42: =+K42*F42 -> 0 | O42: =+K42*F42 -> 0 | P42: =+(L42*10.5/100)+L42 -> 0 | R42: 0 | S42: =+R42-P42 -> 0
A43: =+'SERVICIO FAENA'!A43 -> 41 | B43: =+'SERVICIO FAENA'!B43 -> MUCA SAS | C43: =+'SERVICIO FAENA'!C43 -> 14 | L43: =+K43*F43 -> 0 | O43: =+K43*F43 -> 0 | P43: =+(L43*10.5/100)+L43 -> 0 | R43: 0 | S43: =+R43-P43 -> 0
A44: =+'SERVICIO FAENA'!A44 -> 42 | B44: =+'SERVICIO FAENA'!B44 -> FERREYRA MARTIN | C44: =+'SERVICIO FAENA'!C44 -> 14 | L44: =+K44*F44 -> 0 | O44: =+K44*F44 -> 0 | P44: =+(L44*10.5/100)+L44 -> 0 | R44: 0 | S44: =+R44-P44 -> 0
A45: =+'SERVICIO FAENA'!A45 -> 43 | B45: =+'SERVICIO FAENA'!B45 -> FERREYRA MARTIN | C45: =+'SERVICIO FAENA'!C45 -> 9 | L45: =+K45*F45 -> 0 | O45: =+K45*F45 -> 0 | P45: =+(L45*10.5/100)+L45 -> 0 | R45: 0 | S45: =+R45-P45 -> 0
A46: =+'SERVICIO FAENA'!A46 -> 44 | B46: =+'SERVICIO FAENA'!B46 -> FERREYRA ALBERTO | C46: =+'SERVICIO FAENA'!C46 -> 6 | L46: =+K46*F46 -> 0 | O46: =+K46*F46 -> 0 | P46: =+(L46*10.5/100)+L46 -> 0 | R46: 0 | S46: =+R46-P46 -> 0
A47: =+'SERVICIO FAENA'!A47 -> 45 | B47: =+'SERVICIO FAENA'!B47 -> FRIGORIFICO DE LA PATAGONIA SRL | C47: =+'SERVICIO FAENA'!C47 -> 22 | D47: 671.22 | E47: 18.88 | L47: =+K47*F47 -> 0 | O47: =+K47*F47 -> 0 | P47: =+(L47*10.5/100)+L47 -> 0 | R47: 0 | S47: =+R47-P47 -> 0
A48: =+'SERVICIO FAENA'!A48 -> 46 | B48: =+'SERVICIO FAENA'!B48 -> FRIGORIFICO DE LA PATAGONIA SRL | C48: =+'SERVICIO FAENA'!C48 -> 20 | L48: =+K48*F48 -> 0 | O48: =+K48*F48 -> 0 | P48: =+(L48*10.5/100)+L48 -> 0 | R48: 0 | S48: =+R48-P48 -> 0
A49: =+'SERVICIO FAENA'!A49 -> 47 | B49: =+'SERVICIO FAENA'!B49 -> MUCA SAS | C49: =+'SERVICIO FAENA'!C49 -> 13 | D49: 433.1 | E49: 37.02 | L49: =+K49*F49 -> 0 | O49: =+K49*F49 -> 0 | P49: =+(L49*10.5/100)+L49 -> 0 | R49: 0 | S49: =+R49-P49 -> 0
A50: =+'SERVICIO FAENA'!A50 -> 48 | B50: =+'SERVICIO FAENA'!B50 -> MUCA SAS | C50: =+'SERVICIO FAENA'!C50 -> 8 | L50: =+K50*F50 -> 0 | O50: =+K50*F50 -> 0 | P50: =+(L50*10.5/100)+L50 -> 0 | R50: 0 | S50: =+R50-P50 -> 0
A51: =+'SERVICIO FAENA'!A51 -> 49 | B51: =+'SERVICIO FAENA'!B51 -> MUCA SAS | C51: =+'SERVICIO FAENA'!C51 -> 5 | L51: =+K51*F51 -> 0 | O51: =+K51*F51 -> 0 | P51: =+(L51*10.5/100)+L51 -> 0 | R51: 0 | S51: =+R51-P51 -> 0
A52: =+'SERVICIO FAENA'!A52 -> 50 | B52: =+'SERVICIO FAENA'!B52 -> MUCA SAS | C52: =+'SERVICIO FAENA'!C52 -> 2 | L52: =+K52*F52 -> 0 | O52: =+K52*F52 -> 0 | P52: =+(L52*10.5/100)+L52 -> 0 | R52: 0 | S52: =+R52-P52 -> 0
A53: =+'SERVICIO FAENA'!A53 -> 51 | B53: =+'SERVICIO FAENA'!B53 -> GANADERA NORTE NEUQUINO | C53: =+'SERVICIO FAENA'!C53 -> 42 | D53: 651.62 | E53: 3.98 | L53: =+K53*F53 -> 0 | O53: =+K53*F53 -> 0 | P53: =+(L53*10.5/100)+L53 -> 0 | R53: 0 | S53: =+R53-P53 -> 0
A54: =+'SERVICIO FAENA'!A54 -> 52 | B54: =+'SERVICIO FAENA'!B54 -> FERREYRA MARTIN | C54: =+'SERVICIO FAENA'!C54 -> 18 | D54: 247.56 | E54: 11.22 | L54: =+K54*F54 -> 0 | O54: =+K54*F54 -> 0 | P54: =+(L54*10.5/100)+L54 -> 0 | R54: 0 | S54: =+R54-P54 -> 0
A55: =+'SERVICIO FAENA'!A55 -> 53 | B55: =+'SERVICIO FAENA'!B55 -> BOSQUES AMADOS SRL | C55: =+'SERVICIO FAENA'!C55 -> 17 | D55: 260.55 | E55: 3.9 | L55: =+K55*F55 -> 0 | O55: =+K55*F55 -> 0 | P55: =+(L55*10.5/100)+L55 -> 0 | R55: 0 | S55: =+R55-P55 -> 0
A56: =+'SERVICIO FAENA'!A56 -> 54 | B56: =+'SERVICIO FAENA'!B56 -> MUCA SAS | C56: =+'SERVICIO FAENA'!C56 -> 50 | D56: 938.78 | E56: 118.78 | L56: =+K56*F56 -> 0 | O56: =+K56*F56 -> 0 | P56: =+(L56*10.5/100)+L56 -> 0 | R56: 0 | S56: =+R56-P56 -> 0
A57: =+'SERVICIO FAENA'!A57 -> 55 | B57: =+'SERVICIO FAENA'!B57 -> MORAGA | C57: =+'SERVICIO FAENA'!C57 -> 10 | D57: 141.74 | E57: 4.16 | L57: =+K57*F57 -> 0 | O57: =+K57*F57 -> 0 | P57: =+(L57*10.5/100)+L57 -> 0 | R57: 0 | S57: =+R57-P57 -> 0
A58: =+'SERVICIO FAENA'!A58 -> 56 | B58: =+'SERVICIO FAENA'!B58 -> FERREYRA MARTIN | C58: =+'SERVICIO FAENA'!C58 -> 15 | D58: 388.22 | E58: 4.69 | L58: =+K58*F58 -> 0 | O58: =+K58*F58 -> 0 | P58: =+(L58*10.5/100)+L58 -> 0 | R58: 0 | S58: =+R58-P58 -> 0
A59: =+'SERVICIO FAENA'!A59 -> 57 | B59: =+'SERVICIO FAENA'!B59 -> FERREYRA ALBERTO | C59: =+'SERVICIO FAENA'!C59 -> 5 | D59: 71.34 | L59: =+K59*F59 -> 0 | O59: =+K59*F59 -> 0 | P59: =+(L59*10.5/100)+L59 -> 0 | R59: 0 | S59: =+R59-P59 -> 0
A60: =+'SERVICIO FAENA'!A60 -> 58 | B60: =+'SERVICIO FAENA'!B60 -> FERREYRA MARTIN | C60: =+'SERVICIO FAENA'!C60 -> 10 | L60: =+K60*F60 -> 0 | O60: =+K60*F60 -> 0 | P60: =+(L60*10.5/100)+L60 -> 0 | R60: 0 | S60: =+R60-P60 -> 0
A61: =+'SERVICIO FAENA'!A61 -> 59 | B61: =+'SERVICIO FAENA'!B61 -> FRIGORIFICO DE LA PATAGONIA SRL | C61: =+'SERVICIO FAENA'!C61 -> 20 | D61: 683.48 | L61: =+K61*F61 -> 0 | O61: =+K61*F61 -> 0 | P61: =+(L61*10.5/100)+L61 -> 0 | R61: 0 | S61: =+R61-P61 -> 0
A62: =+'SERVICIO FAENA'!A62 -> 60 | B62: =+'SERVICIO FAENA'!B62 -> FRIGORIFICO DE LA PATAGONIA SRL | C62: =+'SERVICIO FAENA'!C62 -> 28 | L62: =+K62*F62 -> 0 | O62: =+K62*F62 -> 0 | P62: =+(L62*10.5/100)+L62 -> 0 | R62: 0 | S62: =+R62-P62 -> 0
A63: =+'SERVICIO FAENA'!A63 -> 61 | B63: =+'SERVICIO FAENA'!B63 -> MAIZALES DE LA PATAGONIA SRL | C63: =+'SERVICIO FAENA'!C63 -> 20 | D63: 305 | L63: =+K63*F63 -> 0 | O63: =+K63*F63 -> 0 | P63: =+(L63*10.5/100)+L63 -> 0 | R63: 0 | S63: =+R63-P63 -> 0
A64: =+'SERVICIO FAENA'!A64 -> 62 | B64: =+'SERVICIO FAENA'!B64 -> FRIGORIFICO DE LA PATAGONIA SRL | C64: =+'SERVICIO FAENA'!C64 -> 1 | L64: =+K64*F64 -> 0 | O64: =+K64*F64 -> 0 | P64: =+(L64*10.5/100)+L64 -> 0 | R64: 0 | S64: =+R64-P64 -> 0
A65: =+'SERVICIO FAENA'!A65 -> 63 | B65: =+'SERVICIO FAENA'!B65 -> FERREYRA MARTIN | C65: =+'SERVICIO FAENA'!C65 -> 8 | D65: 223.68 | L65: =+K65*F65 -> 0 | O65: =+K65*F65 -> 0 | P65: =+(L65*10.5/100)+L65 -> 0 | R65: 0 | S65: =+R65-P65 -> 0
A66: =+'SERVICIO FAENA'!A66 -> 64 | B66: =+'SERVICIO FAENA'!B66 -> FERREYRA MARTIN | C66: =+'SERVICIO FAENA'!C66 -> 3 | L66: =+K66*F66 -> 0 | O66: =+K66*F66 -> 0 | P66: =+(L66*10.5/100)+L66 -> 0 | R66: 0 | S66: =+R66-P66 -> 0
A67: =+'SERVICIO FAENA'!A67 -> 65 | B67: =+'SERVICIO FAENA'!B67 -> FERREYRA MARTIN | C67: =+'SERVICIO FAENA'!C67 -> 4 | L67: =+K67*F67 -> 0 | O67: =+K67*F67 -> 0 | P67: =+(L67*10.5/100)+L67 -> 0 | R67: 0 | S67: =+R67-P67 -> 0
A68: =+'SERVICIO FAENA'!A68 -> 66 | B68: =+'SERVICIO FAENA'!B68 -> DOS DE FIERRO SA | C68: =+'SERVICIO FAENA'!C68 -> 21 | D68: 334.9 | L68: =+K68*F68 -> 0 | O68: =+K68*F68 -> 0 | P68: =+(L68*10.5/100)+L68 -> 0 | R68: 0 | S68: =+R68-P68 -> 0
A69: =+'SERVICIO FAENA'!A69 -> 67 | B69: =+'SERVICIO FAENA'!B69 -> GANADERA NORTE NEUQUINO | C69: =+'SERVICIO FAENA'!C69 -> 45 | D69: 554.16 | L69: =+K69*F69 -> 0 | O69: =+K69*F69 -> 0 | P69: =+(L69*10.5/100)+L69 -> 0 | R69: 0 | S69: =+R69-P69 -> 0
A70: =+'SERVICIO FAENA'!A70 -> 68 | B70: =+'SERVICIO FAENA'!B70 -> BOSQUES AMADOS SRL | C70: =+'SERVICIO FAENA'!C70 -> 18 | D70: 287.94 | L70: =+K70*F70 -> 0 | O70: =+K70*F70 -> 0 | P70: =+(L70*10.5/100)+L70 -> 0 | R70: 0 | S70: =+R70-P70 -> 0
A71: =+'SERVICIO FAENA'!A71 -> 69 | B71: =+'SERVICIO FAENA'!B71 -> MUCA SAS | C71: =+'SERVICIO FAENA'!C71 -> 50 | D71: 982.86 | E71: 19.7 | L71: =+K71*F71 -> 0 | O71: =+K71*F71 -> 0 | P71: =+(L71*10.5/100)+L71 -> 0 | R71: 0 | S71: =+R71-P71 -> 0
A72: =+'SERVICIO FAENA'!A72 -> 70 | B72: =+'SERVICIO FAENA'!B72 -> FERREYRA ALBERTO | C72: =+'SERVICIO FAENA'!C72 -> 5 | D72: 67.78 | L72: =+K72*F72 -> 0 | O72: =+K72*F72 -> 0 | P72: =+(L72*10.5/100)+L72 -> 0 | R72: 0 | S72: =+R72-P72 -> 0
A73: =+'SERVICIO FAENA'!A73 -> 71 | B73: =+'SERVICIO FAENA'!B73 -> FRIGORIFICO DE LA PATAGONIA SRL | C73: =+'SERVICIO FAENA'!C73 -> 25 | D73: 635.7 | E73: 28.68 | L73: =+K73*F73 -> 0 | O73: =+K73*F73 -> 0 | P73: =+(L73*10.5/100)+L73 -> 0 | R73: 0 | S73: =+R73-P73 -> 0
A74: =+'SERVICIO FAENA'!A74 -> 72 | B74: =+'SERVICIO FAENA'!B74 -> FERREYRA MARTIN | C74: =+'SERVICIO FAENA'!C74 -> 20 | D74: 287.74 | L74: =+K74*F74 -> 0 | O74: =+K74*F74 -> 0 | P74: =+(L74*10.5/100)+L74 -> 0 | R74: 0 | S74: =+R74-P74 -> 0
A75: =+'SERVICIO FAENA'!A75 -> 73 | B75: =+'SERVICIO FAENA'!B75 -> FRIGORIFICO DE LA PATAGONIA SRL | C75: =+'SERVICIO FAENA'!C75 -> 15 | L75: =+K75*F75 -> 0 | O75: =+K75*F75 -> 0 | P75: =+(L75*10.5/100)+L75 -> 0 | R75: 0 | S75: =+R75-P75 -> 0
A76: =+'SERVICIO FAENA'!A76 -> 74 | B76: =+'SERVICIO FAENA'!B76 -> FERREYRA MARTIN | C76: =+'SERVICIO FAENA'!C76 -> 10 | D76: 423.96 | E76: 5.32 | L76: =+K76*F76 -> 0 | O76: =+K76*F76 -> 0 | P76: =+(L76*10.5/100)+L76 -> 0 | R76: 0 | S76: =+R76-P76 -> 0
A77: =+'SERVICIO FAENA'!A77 -> 75 | B77: =+'SERVICIO FAENA'!B77 -> FERREYRA MARTIN | C77: =+'SERVICIO FAENA'!C77 -> 5 | L77: =+K77*F77 -> 0 | O77: =+K77*F77 -> 0 | P77: =+(L77*10.5/100)+L77 -> 0 | R77: 0 | S77: =+R77-P77 -> 0
A78: =+'SERVICIO FAENA'!A78 -> 76 | B78: =+'SERVICIO FAENA'!B78 -> BOSQUES AMADOS SRL | C78: =+'SERVICIO FAENA'!C78 -> 18 | D78: 292.06 | L78: =+K78*F78 -> 0 | O78: =+K78*F78 -> 0 | P78: =+(L78*10.5/100)+L78 -> 0 | R78: 0 | S78: =+R78-P78 -> 0
A79: =+'SERVICIO FAENA'!A79 -> 77 | B79: =+'SERVICIO FAENA'!B79 -> FERREYRA MARTIN | C79: =+'SERVICIO FAENA'!C79 -> 15 | L79: =+K79*F79 -> 0 | O79: =+K79*F79 -> 0 | P79: =+(L79*10.5/100)+L79 -> 0 | R79: 0 | S79: =+R79-P79 -> 0
A80: =+'SERVICIO FAENA'!A80 -> 78 | B80: =+'SERVICIO FAENA'!B80 -> FERREYRA ALBERTO | C80: =+'SERVICIO FAENA'!C80 -> 8 | D80: 119.86 | L80: =+K80*F80 -> 0 | O80: =+K80*F80 -> 0 | P80: =+(L80*10.5/100)+L80 -> 0 | R80: 0 | S80: =+R80-P80 -> 0
A81: =+'SERVICIO FAENA'!A81 -> 79 | B81: =+'SERVICIO FAENA'!B81 -> MUCA SAS | C81: =+'SERVICIO FAENA'!C81 -> 20 | D81: 326.84 | E81: 41.86 | L81: =+K81*F81 -> 0 | O81: =+K81*F81 -> 0 | P81: =+(L81*10.5/100)+L81 -> 0 | R81: 0 | S81: =+R81-P81 -> 0
A82: =+'SERVICIO FAENA'!A82 -> 80 | B82: =+'SERVICIO FAENA'!B82 -> FRIGORIFICO DE LA PATAGONIA SRL | C82: =+'SERVICIO FAENA'!C82 -> 21 | D82: 587.26 | L82: =+K82*F82 -> 0 | O82: =+K82*F82 -> 0 | P82: =+(L82*10.5/100)+L82 -> 0 | R82: 0 | S82: =+R82-P82 -> 0
A83: =+'SERVICIO FAENA'!A83 -> 81 | B83: =+'SERVICIO FAENA'!B83 -> FRIGORIFICO DE LA PATAGONIA SRL | C83: =+'SERVICIO FAENA'!C83 -> 15 | L83: =+K83*F83 -> 0 | O83: =+K83*F83 -> 0 | P83: =+(L83*10.5/100)+L83 -> 0 | R83: 0 | S83: =+R83-P83 -> 0
A84: =+'SERVICIO FAENA'!A84 -> 82 | B84: =+'SERVICIO FAENA'!B84 -> MAIZALES DE LA PATAGONIA SRL | C84: =+'SERVICIO FAENA'!C84 -> 15 | D84: 444.5 | E84: 9.5 | L84: =+K84*F84 -> 0 | O84: =+K84*F84 -> 0 | P84: =+(L84*10.5/100)+L84 -> 0 | R84: 0 | S84: =+R84-P84 -> 0
A85: =+'SERVICIO FAENA'!A85 -> 83 | B85: =+'SERVICIO FAENA'!B85 -> MAIZALES DE LA PATAGONIA SRL | C85: =+'SERVICIO FAENA'!C85 -> 15 | L85: =+K85*F85 -> 0 | O85: =+K85*F85 -> 0 | P85: =+(L85*10.5/100)+L85 -> 0 | R85: 0 | S85: =+R85-P85 -> 0
A86: =+'SERVICIO FAENA'!A86 -> 84 | B86: =+'SERVICIO FAENA'!B86 -> DOS DE FIERRO SA | C86: =+'SERVICIO FAENA'!C86 -> 21 | D86: 345.62 | L86: =+K86*F86 -> 0 | O86: =+K86*F86 -> 0 | P86: =+(L86*10.5/100)+L86 -> 0 | R86: 0 | S86: =+R86-P86 -> 0
A87: =+'SERVICIO FAENA'!A87 -> 85 | B87: =+'SERVICIO FAENA'!B87 -> FERREYRA MARTIN | C87: =+'SERVICIO FAENA'!C87 -> 18 | D87: 279.8 | L87: =+K87*F87 -> 0 | O87: =+K87*F87 -> 0 | P87: =+(L87*10.5/100)+L87 -> 0 | R87: 0 | S87: =+R87-P87 -> 0
A88: =+'SERVICIO FAENA'!A88 -> 86 | B88: =+'SERVICIO FAENA'!B88 -> MUCA SAS | C88: =+'SERVICIO FAENA'!C88 -> 50 | D88: 1008.89 | E88: 7.18 | L88: =+K88*F88 -> 0 | O88: =+K88*F88 -> 0 | P88: =+(L88*10.5/100)+L88 -> 0 | R88: 0 | S88: =+R88-P88 -> 0
A89: =+'SERVICIO FAENA'!A89 -> 87 | B89: =+'SERVICIO FAENA'!B89 -> BOSQUES AMADOS SRL | C89: =+'SERVICIO FAENA'!C89 -> 18 | D89: 285.38 | L89: =+K89*F89 -> 0 | O89: =+K89*F89 -> 0 | P89: =+(L89*10.5/100)+L89 -> 0 | R89: 0 | S89: =+R89-P89 -> 0
A90: =+'SERVICIO FAENA'!A90 -> 88 | B90: =+'SERVICIO FAENA'!B90 -> FERREYRA ALBERTO | C90: =+'SERVICIO FAENA'!C90 -> 8 | D90: 110.46 | L90: =+K90*F90 -> 0 | O90: =+K90*F90 -> 0 | P90: =+(L90*10.5/100)+L90 -> 0 | R90: 0 | S90: =+R90-P90 -> 0
A91: =+'SERVICIO FAENA'!A91 -> 89 | B91: =+'SERVICIO FAENA'!B91 -> FERREYRA MARTIN | C91: =+'SERVICIO FAENA'!C91 -> 7 | D91: 285.72 | E91: 6.1 | L91: =+K91*F91 -> 0 | O91: =+K91*F91 -> 0 | P91: =+(L91*10.5/100)+L91 -> 0 | R91: 0 | S91: =+R91-P91 -> 0
A92: =+'SERVICIO FAENA'!A92 -> 90 | B92: =+'SERVICIO FAENA'!B92 -> FERREYRA MARTIN | C92: =+'SERVICIO FAENA'!C92 -> 11 | L92: =+K92*F92 -> 0 | O92: =+K92*F92 -> 0 | P92: =+(L92*10.5/100)+L92 -> 0 | R92: 0 | S92: =+R92-P92 -> 0
A93: =+'SERVICIO FAENA'!A93 -> 91 | B93: =+'SERVICIO FAENA'!B93 -> FRIGORIFICO DE LA PATAGONIA SRL | C93: =+'SERVICIO FAENA'!C93 -> 15 | D93: 772.12 | L93: =+K93*F93 -> 0 | O93: =+K93*F93 -> 0 | P93: =+(L93*10.5/100)+L93 -> 0 | R93: 0 | S93: =+R93-P93 -> 0
A94: =+'SERVICIO FAENA'!A94 -> 92 | B94: =+'SERVICIO FAENA'!B94 -> MAIZALES DE LA PATAGONIA SRL | C94: =+'SERVICIO FAENA'!C94 -> 10 | L94: =+K94*F94 -> 0 | O94: =+K94*F94 -> 0 | P94: =+(L94*10.5/100)+L94 -> 0 | R94: 0 | S94: =+R94-P94 -> 0
A95: =+'SERVICIO FAENA'!A95 -> 93 | B95: =+'SERVICIO FAENA'!B95 -> MAIZALES DE LA PATAGONIA SRL | C95: =+'SERVICIO FAENA'!C95 -> 20 | D95: 490.3 | L95: =+K95*F95 -> 0 | O95: =+K95*F95 -> 0 | P95: =+(L95*10.5/100)+L95 -> 0 | R95: 0 | S95: =+R95-P95 -> 0
A96: =+'SERVICIO FAENA'!A96 -> 94 | B96: =+'SERVICIO FAENA'!B96 -> FRIGORIFICO DE LA PATAGONIA SRL | C96: =+'SERVICIO FAENA'!C96 -> 8 | L96: =+K96*F96 -> 0 | O96: =+K96*F96 -> 0 | P96: =+(L96*10.5/100)+L96 -> 0 | R96: 0 | S96: =+R96-P96 -> 0
A97: =+'SERVICIO FAENA'!A97 -> 95 | B97: =+'SERVICIO FAENA'!B97 -> MUCA SAS | C97: =+'SERVICIO FAENA'!C97 -> 15 | D97: 267.86 | L97: =+K97*F97 -> 0 | O97: =+K97*F97 -> 0 | P97: =+(L97*10.5/100)+L97 -> 0 | R97: 0 | S97: =+R97-P97 -> 0
A98: =+'SERVICIO FAENA'!A98 -> 96 | B98: =+'SERVICIO FAENA'!B98 -> FRIGORIFICO DE LA PATAGONIA SRL | C98: =+'SERVICIO FAENA'!C98 -> 22 | L98: =+K98*F98 -> 0 | O98: =+K98*F98 -> 0 | P98: =+(L98*10.5/100)+L98 -> 0 | R98: 0 | S98: =+R98-P98 -> 0
A99: =+'SERVICIO FAENA'!A99 -> 97 | B99: =+'SERVICIO FAENA'!B99 -> FERREYRA MARTIN | C99: =+'SERVICIO FAENA'!C99 -> 18 | D99: 245.62 | L99: =+K99*F99 -> 0 | O99: =+K99*F99 -> 0 | P99: =+(L99*10.5/100)+L99 -> 0 | R99: 0 | S99: =+R99-P99 -> 0
A100: =+'SERVICIO FAENA'!A100 -> 98 | B100: =+'SERVICIO FAENA'!B100 -> GANADERA NORTE NEUQUINO | C100: =+'SERVICIO FAENA'!C100 -> 44 | D100: 572.76 | E100: 5.64 | L100: =+K100*F100 -> 0 | O100: =+K100*F100 -> 0 | P100: =+(L100*10.5/100)+L100 -> 0 | R100: 0 | S100: =+R100-P100 -> 0
...

Sheet RENDERING
A1: FECHA FAENA | B1: Nº TROPAS | C1: PRECIO POR CLIENTE | E1: KG DESPERDICIO | F1: $ / KG +10,5 IVA | G1: KG HUESO | H1: $ / KG +10,5 IVA | I1: KG GRASA | J1: $ / KG +10,5 IVA | K1: FACTURA Nº | L1: FECHA | M1: MONTO TOTAL | N1: ESTADO | O1: OBSERVACIONES | Q1: PRECIO MARMETO X KG | R1: 100 | T1: PRECIO TRIAUD X KG | U1: 300 | V1: 60
A2: 46024 | B2: =+'SERVICIO FAENA'!A3 -> 1 | E2: 2260 | F2: =+E2*C2 -> 0 | G2: 900 | H2: =+G2*C2 -> 0 | I2: 560 | J2: =+I2*D2 -> 0 | M2: =+F2+H2+J2 -> 0
A3: =+'SERVICIO FAENA'!E4 -> 46024 | B3: =+'SERVICIO FAENA'!A4 -> 2 | F3: =+E3*C3 -> 0 | H3: =+G3*C3 -> 0 | J3: =+I3*D3 -> 0 | M3: =+F3+H3+J3 -> 0
A4: =+'SERVICIO FAENA'!E5 -> 46027 | B4: =+'SERVICIO FAENA'!A5 -> 3 | F4: =+E4*C4 -> 0 | H4: =+G4*C4 -> 0 | J4: =+I4*D4 -> 0 | M4: =+F4+H4+J4 -> 0 | O4: DECOMISADO
A5: =+'SERVICIO FAENA'!E6 -> 46027 | B5: =+'SERVICIO FAENA'!A6 -> 4 | F5: =+E5*C5 -> 0 | H5: =+G5*C5 -> 0 | J5: =+I5*D5 -> 0 | M5: =+F5+H5+J5 -> 0
A6: =+'SERVICIO FAENA'!E7 -> 46027 | B6: =+'SERVICIO FAENA'!A7 -> 5 | E6: 2620 | F6: =+E6*C6 -> 0 | G6: 1420 | H6: =+G6*C6 -> 0 | I6: 880 | J6: =+I6*D6 -> 0 | M6: =+F6+H6+J6 -> 0
A7: =+'SERVICIO FAENA'!E8 -> 46028 | B7: =+'SERVICIO FAENA'!A8 -> 6 | E7: 3860 | F7: =+E7*C7 -> 0 | G7: 1360 | H7: =+G7*C7 -> 0 | I7: 1160 | J7: =+I7*D7 -> 0 | M7: =+F7+H7+J7 -> 0
A8: =+'SERVICIO FAENA'!E9 -> 46028 | B8: =+'SERVICIO FAENA'!A9 -> 7 | F8: =+E8*C8 -> 0 | H8: =+G8*C8 -> 0 | J8: =+I8*D8 -> 0 | M8: =+F8+H8+J8 -> 0
A9: =+'SERVICIO FAENA'!E10 -> 46028 | B9: =+'SERVICIO FAENA'!A10 -> 8 | F9: =+E9*C9 -> 0 | H9: =+G9*C9 -> 0 | J9: =+I9*D9 -> 0 | M9: =+F9+H9+J9 -> 0
A10: =+'SERVICIO FAENA'!E11 -> 46028 | B10: =+'SERVICIO FAENA'!A11 -> 9 | F10: =+E10*C10 -> 0 | H10: =+G10*C10 -> 0 | J10: =+I10*D10 -> 0 | M10: =+F10+H10+J10 -> 0
A11: =+'SERVICIO FAENA'!E12 -> 46028 | B11: =+'SERVICIO FAENA'!A12 -> 10 | F11: =+E11*C11 -> 0 | H11: =+G11*C11 -> 0 | J11: =+I11*D11 -> 0 | M11: =+F11+H11+J11 -> 0
A12: =+'SERVICIO FAENA'!E13 -> 46029 | B12: =+'SERVICIO FAENA'!A13 -> 11 | E12: 2360 | F12: =+E12*C12 -> 0 | G12: 860 | H12: =+G12*C12 -> 0 | I12: 520 | J12: =+I12*D12 -> 0 | M12: =+F12+H12+J12 -> 0
A13: =+'SERVICIO FAENA'!E14 -> 46029 | B13: =+'SERVICIO FAENA'!A14 -> 12 | F13: =+E13*C13 -> 0 | H13: =+G13*C13 -> 0 | J13: =+I13*D13 -> 0 | M13: =+F13+H13+J13 -> 0
A14: =+'SERVICIO FAENA'!E15 -> 46029 | B14: =+'SERVICIO FAENA'!A15 -> 13 | F14: =+E14*C14 -> 0 | H14: =+G14*C14 -> 0 | J14: =+I14*D14 -> 0 | M14: =+F14+H14+J14 -> 0
A15: =+'SERVICIO FAENA'!E16 -> 46030 | B15: =+'SERVICIO FAENA'!A16 -> 14 | C15: 40 | D15: 40 | E15: 1000 | F15: =+E15*C15 -> 40000 | G15: 400 | H15: =+G15*C15 -> 16000 | I15: 340 | J15: =+I15*D15 -> 13600 | M15: =+F15+H15+J15 -> 69600 | O15: RETIRO MARMETTO 09-01-26
A16: =+'SERVICIO FAENA'!E17 -> 46031 | B16: =+'SERVICIO FAENA'!A17 -> 15 | C16: 40 | D16: 40 | E16: 2880 | F16: =+E16*C16 -> 115200 | G16: 1160 | H16: =+G16*C16 -> 46400 | I16: 620 | J16: =+I16*D16 -> 24800 | M16: =+F16+H16+J16 -> 186400
A17: =+'SERVICIO FAENA'!E18 -> 46031 | B17: =+'SERVICIO FAENA'!A18 -> 16 | F17: =+E17*C17 -> 0 | H17: =+G17*C17 -> 0 | J17: =+I17*D17 -> 0 | M17: =+F17+H17+J17 -> 0
A18: =+'SERVICIO FAENA'!E19 -> 46031 | B18: =+'SERVICIO FAENA'!A19 -> 17 | F18: =+E18*C18 -> 0 | H18: =+G18*C18 -> 0 | J18: =+I18*D18 -> 0 | M18: =+F18+H18+J18 -> 0
A19: =+'SERVICIO FAENA'!E20 -> 46034 | B19: =+'SERVICIO FAENA'!A20 -> 18 | C19: 40 | D19: 40 | E19: 1440 | F19: =+E19*C19 -> 57600 | G19: 1160 | H19: =+G19*C19 -> 46400 | I19: 780 | J19: =+I19*D19 -> 31200 | M19: =+F19+H19+J19 -> 135200 | O19: RETIRO MARMETTO 16-01-26
A20: =+'SERVICIO FAENA'!E21 -> 46034 | B20: =+'SERVICIO FAENA'!A21 -> 19 | F20: =+E20*C20 -> 0 | H20: =+G20*C20 -> 0 | J20: =+I20*D20 -> 0 | M20: =+F20+H20+J20 -> 0
A21: =+'SERVICIO FAENA'!E22 -> 46034 | B21: =+'SERVICIO FAENA'!A22 -> 20 | F21: =+E21*C21 -> 0 | H21: =+G21*C21 -> 0 | J21: =+I21*D21 -> 0 | M21: =+F21+H21+J21 -> 0
A22: =+'SERVICIO FAENA'!E23 -> 46035 | B22: =+'SERVICIO FAENA'!A23 -> 21 | C22: 40 | D22: 40 | E22: 1000 | F22: =+E22*C22 -> 40000 | G22: 420 | H22: =+G22*C22 -> 16800 | I22: 240 | J22: =+I22*D22 -> 9600 | M22: =+F22+H22+J22 -> 66400
A23: =+'SERVICIO FAENA'!E24 -> 46035 | B23: =+'SERVICIO FAENA'!A24 -> 22 | F23: =+E23*C23 -> 0 | H23: =+G23*C23 -> 0 | J23: =+I23*D23 -> 0 | M23: =+F23+H23+J23 -> 0
A24: =+'SERVICIO FAENA'!E25 -> 46035 | B24: =+'SERVICIO FAENA'!A25 -> 23 | F24: =+E24*C24 -> 0 | H24: =+G24*C24 -> 0 | J24: =+I24*D24 -> 0 | M24: =+F24+H24+J24 -> 0
A25: =+'SERVICIO FAENA'!E26 -> 46036 | B25: =+'SERVICIO FAENA'!A26 -> 24 | C25: 40 | D25: 40 | E25: 1180 | F25: =+E25*C25 -> 47200 | G25: 480 | H25: =+G25*C25 -> 19200 | I25: 400 | J25: =+I25*D25 -> 16000 | M25: =+F25+H25+J25 -> 82400
A26: =+'SERVICIO FAENA'!E27 -> 46036 | B26: =+'SERVICIO FAENA'!A27 -> 25 | F26: =+E26*C26 -> 0 | H26: =+G26*C26 -> 0 | J26: =+I26*D26 -> 0 | M26: =+F26+H26+J26 -> 0
A27: =+'SERVICIO FAENA'!E28 -> 46038 | B27: =+'SERVICIO FAENA'!A28 -> 26 | C27: 40 | D27: 40 | E27: 2080 | F27: =+E27*C27 -> 83200 | G27: 800 | H27: =+G27*C27 -> 32000 | I27: 480 | J27: =+I27*D27 -> 19200 | M27: =+F27+H27+J27 -> 134400
A28: =+'SERVICIO FAENA'!E29 -> 46041 | B28: =+'SERVICIO FAENA'!A29 -> 27 | C28: 40 | D28: 40 | E28: 3020 | F28: =+E28*C28 -> 120800 | G28: 1280 | H28: =+G28*C28 -> 51200 | I28: 740 | J28: =+I28*D28 -> 29600 | M28: =+F28+H28+J28 -> 201600
A29: =+'SERVICIO FAENA'!E30 -> 46041 | B29: =+'SERVICIO FAENA'!A30 -> 28 | F29: =+E29*C29 -> 0 | H29: =+G29*C29 -> 0 | J29: =+I29*D29 -> 0 | M29: =+F29+H29+J29 -> 0
A30: =+'SERVICIO FAENA'!E31 -> 46041 | B30: =+'SERVICIO FAENA'!A31 -> 29 | F30: =+E30*C30 -> 0 | H30: =+G30*C30 -> 0 | J30: =+I30*D30 -> 0 | M30: =+F30+H30+J30 -> 0
A31: =+'SERVICIO FAENA'!E32 -> 20-21/01/2026 | B31: =+'SERVICIO FAENA'!A32 -> 30 | C31: 40 | D31: 40 | E31: 2580 | F31: =+E31*C31 -> 103200 | G31: 900 | H31: =+G31*C31 -> 36000 | I31: 940 | J31: =+I31*D31 -> 37600 | M31: =+F31+H31+J31 -> 176800
A32: =+'SERVICIO FAENA'!E33 -> 46042 | B32: =+'SERVICIO FAENA'!A33 -> 31 | C32: 40 | D32: 40 | E32: 580 | F32: =+E32*C32 -> 23200 | G32: 240 | H32: =+G32*C32 -> 9600 | I32: 180 | J32: =+I32*D32 -> 7200 | M32: =+F32+H32+J32 -> 40000
A33: =+'SERVICIO FAENA'!E34 -> 46044 | B33: =+'SERVICIO FAENA'!A34 -> 32 | F33: =+E33*C33 -> 0 | H33: =+G33*C33 -> 0 | J33: =+I33*D33 -> 0 | M33: =+F33+H33+J33 -> 0
A34: =+'SERVICIO FAENA'!E35 -> 46044 | B34: =+'SERVICIO FAENA'!A35 -> 33 | F34: =+E34*C34 -> 0 | H34: =+G34*C34 -> 0 | J34: =+I34*D34 -> 0 | M34: =+F34+H34+J34 -> 0
A35: =+'SERVICIO FAENA'!E36 -> 46045 | B35: =+'SERVICIO FAENA'!A36 -> 34 | C35: 40 | D35: 40 | E35: 1820 | F35: =+E35*C35 -> 72800 | G35: 780 | H35: =+G35*C35 -> 31200 | I35: 400 | J35: =+I35*D35 -> 16000 | M35: =+F35+H35+J35 -> 120000
A36: =+'SERVICIO FAENA'!E37 -> 46045 | B36: =+'SERVICIO FAENA'!A37 -> 35 | F36: =+E36*C36 -> 0 | H36: =+G36*C36 -> 0 | J36: =+I36*D36 -> 0 | M36: =+F36+H36+J36 -> 0
A37: =+'SERVICIO FAENA'!E38 -> 46045 | B37: =+'SERVICIO FAENA'!A38 -> 36 | F37: =+E37*C37 -> 0 | H37: =+G37*C37 -> 0 | J37: =+I37*D37 -> 0 | M37: =+F37+H37+J37 -> 0
A38: =+'SERVICIO FAENA'!E39 -> 46048 | B38: =+'SERVICIO FAENA'!A39 -> 37 | C38: 40 | D38: 40 | E38: 1500 | F38: =+E38*C38 -> 60000 | G38: 580 | H38: =+G38*C38 -> 23200 | I38: 380 | J38: =+I38*D38 -> 15200 | M38: =+F38+H38+J38 -> 98400
A39: =+'SERVICIO FAENA'!E40 -> 46048 | B39: =+'SERVICIO FAENA'!A40 -> 38 | F39: =+E39*C39 -> 0 | H39: =+G39*C39 -> 0 | J39: =+I39*D39 -> 0 | M39: =+F39+H39+J39 -> 0
A40: =+'SERVICIO FAENA'!E41 -> 46049 | B40: =+'SERVICIO FAENA'!A41 -> 39 | C40: 40 | D40: 40 | E40: 2220 | F40: =+E40*C40 -> 88800 | G40: 1000 | H40: =+G40*C40 -> 40000 | I40: 500 | J40: =+I40*D40 -> 20000 | M40: =+F40+H40+J40 -> 148800
A41: =+'SERVICIO FAENA'!E42 -> 46049 | B41: =+'SERVICIO FAENA'!A42 -> 40 | F41: =+E41*C41 -> 0 | H41: =+G41*C41 -> 0 | J41: =+I41*D41 -> 0 | M41: =+F41+H41+J41 -> 0
A42: =+'SERVICIO FAENA'!E43 -> 46049 | B42: =+'SERVICIO FAENA'!A43 -> 41 | F42: =+E42*C42 -> 0 | H42: =+G42*C42 -> 0 | J42: =+I42*D42 -> 0 | M42: =+F42+H42+J42 -> 0
A43: =+'SERVICIO FAENA'!E44 -> 46050 | B43: =+'SERVICIO FAENA'!A44 -> 42 | C43: 40 | D43: 40 | E43: 900 | F43: =+E43*C43 -> 36000 | G43: 400 | H43: =+G43*C43 -> 16000 | I43: 260 | J43: =+I43*D43 -> 10400 | M43: =+F43+H43+J43 -> 62400
A44: =+'SERVICIO FAENA'!E45 -> 46050 | B44: =+'SERVICIO FAENA'!A45 -> 43 | F44: =+E44*C44 -> 0 | H44: =+G44*C44 -> 0 | J44: =+I44*D44 -> 0 | M44: =+F44+H44+J44 -> 0
A45: =+'SERVICIO FAENA'!E46 -> 46050 | B45: =+'SERVICIO FAENA'!A46 -> 44 | F45: =+E45*C45 -> 0 | H45: =+G45*C45 -> 0 | J45: =+I45*D45 -> 0 | M45: =+F45+H45+J45 -> 0
A46: =+'SERVICIO FAENA'!E47 -> 46052 | B46: =+'SERVICIO FAENA'!A47 -> 45 | F46: =+E46*C46 -> 0 | H46: =+G46*C46 -> 0 | J46: =+I46*D46 -> 0 | M46: =+F46+H46+J46 -> 0 | O46: DECOMISO
A47: =+'SERVICIO FAENA'!E48 -> 46052 | B47: =+'SERVICIO FAENA'!A48 -> 46 | F47: =+E47*C47 -> 0 | H47: =+G47*C47 -> 0 | J47: =+I47*D47 -> 0 | M47: =+F47+H47+J47 -> 0
A48: =+'SERVICIO FAENA'!E49 -> 46052 | B48: =+'SERVICIO FAENA'!A49 -> 47 | F48: =+E48*C48 -> 0 | H48: =+G48*C48 -> 0 | J48: =+I48*D48 -> 0 | M48: =+F48+H48+J48 -> 0
A49: =+'SERVICIO FAENA'!E50 -> 46052 | B49: =+'SERVICIO FAENA'!A50 -> 48 | F49: =+E49*C49 -> 0 | H49: =+G49*C49 -> 0 | J49: =+I49*D49 -> 0 | M49: =+F49+H49+J49 -> 0
A50: =+'SERVICIO FAENA'!E51 -> 46052 | B50: =+'SERVICIO FAENA'!A51 -> 49 | F50: =+E50*C50 -> 0 | H50: =+G50*C50 -> 0 | J50: =+I50*D50 -> 0 | M50: =+F50+H50+J50 -> 0
A51: =+'SERVICIO FAENA'!E52 -> 46052 | B51: =+'SERVICIO FAENA'!A52 -> 50 | F51: =+E51*C51 -> 0 | H51: =+G51*C51 -> 0 | J51: =+I51*D51 -> 0 | M51: =+F51+H51+J51 -> 0
A52: =+'SERVICIO FAENA'!E53 -> 46055 | B52: =+'SERVICIO FAENA'!A53 -> 51 | C52: 40 | D52: 40 | E52: 2040 | F52: =+E52*C52 -> 81600 | G52: 900 | H52: =+G52*C52 -> 36000 | I52: 480 | J52: =+I52*D52 -> 19200 | M52: =+F52+H52+J52 -> 136800
A53: =+'SERVICIO FAENA'!E54 -> 46055 | B53: =+'SERVICIO FAENA'!A54 -> 52 | F53: =+E53*C53 -> 0 | H53: =+G53*C53 -> 0 | J53: =+I53*D53 -> 0 | M53: =+F53+H53+J53 -> 0
A54: =+'SERVICIO FAENA'!E55 -> 46057 | B54: =+'SERVICIO FAENA'!A55 -> 53 | F54: =+E54*C54 -> 0 | H54: =+G54*C54 -> 0 | J54: =+I54*D54 -> 0 | M54: =+F54+H54+J54 -> 0
A55: =+'SERVICIO FAENA'!E56 -> 46056 | B55: =+'SERVICIO FAENA'!A56 -> 54 | C55: 40 | D55: 40 | E55: 2780 | F55: =+E55*C55 -> 111200 | G55: 900 | H55: =+G55*C55 -> 36000 | I55: 900 | J55: =+I55*D55 -> 36000 | M55: =+F55+H55+J55 -> 183200
A56: =+'SERVICIO FAENA'!E57 -> 46057 | B56: =+'SERVICIO FAENA'!A57 -> 55 | C56: 40 | D56: 40 | E56: 1060 | F56: =+E56*C56 -> 42400 | G56: 480 | H56: =+G56*C56 -> 19200 | I56: 280 | J56: =+I56*D56 -> 11200 | M56: =+F56+H56+J56 -> 72800
A57: =+'SERVICIO FAENA'!E58 -> 46058 | B57: =+'SERVICIO FAENA'!A58 -> 56 | F57: =+E57*C57 -> 0 | H57: =+G57*C57 -> 0 | J57: =+I57*D57 -> 0 | M57: =+F57+H57+J57 -> 0
A58: =+'SERVICIO FAENA'!E59 -> 46057 | B58: =+'SERVICIO FAENA'!A59 -> 57 | F58: =+E58*C58 -> 0 | H58: =+G58*C58 -> 0 | J58: =+I58*D58 -> 0 | M58: =+F58+H58+J58 -> 0
A59: =+'SERVICIO FAENA'!E60 -> 46058 | B59: =+'SERVICIO FAENA'!A60 -> 58 | F59: =+E59*C59 -> 0 | H59: =+G59*C59 -> 0 | J59: =+I59*D59 -> 0 | M59: =+F59+H59+J59 -> 0
A60: =+'SERVICIO FAENA'!E61 -> 46059 | B60: =+'SERVICIO FAENA'!A61 -> 59 | C60: 40 | D60: 40 | E60: 2080 | F60: =+E60*C60 -> 83200 | G60: 980 | H60: =+G60*C60 -> 39200 | I60: 440 | J60: =+I60*D60 -> 17600 | M60: =+F60+H60+J60 -> 140000
A61: =+'SERVICIO FAENA'!E62 -> 46059 | B61: =+'SERVICIO FAENA'!A62 -> 60 | F61: =+E61*C61 -> 0 | H61: =+G61*C61 -> 0 | J61: =+I61*D61 -> 0 | M61: =+F61+H61+J61 -> 0
A62: =+'SERVICIO FAENA'!E63 -> 46059 | B62: =+'SERVICIO FAENA'!A63 -> 61 | F62: =+E62*C62 -> 0 | H62: =+G62*C62 -> 0 | J62: =+I62*D62 -> 0 | M62: =+F62+H62+J62 -> 0
A63: =+'SERVICIO FAENA'!E64 -> 46059 | B63: =+'SERVICIO FAENA'!A64 -> 62 | F63: =+E63*C63 -> 0 | H63: =+G63*C63 -> 0 | J63: =+I63*D63 -> 0 | M63: =+F63+H63+J63 -> 0
A64: =+'SERVICIO FAENA'!E65 -> 46062 | B64: =+'SERVICIO FAENA'!A65 -> 63 | C64: 40 | D64: 40 | E64: 2100 | F64: =+E64*C64 -> 84000 | G64: 1140 | H64: =+G64*C64 -> 45600 | I64: 700 | J64: =+I64*D64 -> 28000 | M64: =+F64+H64+J64 -> 157600
A65: =+'SERVICIO FAENA'!E66 -> 46062 | B65: =+'SERVICIO FAENA'!A66 -> 64 | F65: =+E65*C65 -> 0 | H65: =+G65*C65 -> 0 | J65: =+I65*D65 -> 0 | M65: =+F65+H65+J65 -> 0
A66: =+'SERVICIO FAENA'!E67 -> 46062 | B66: =+'SERVICIO FAENA'!A67 -> 65 | F66: =+E66*C66 -> 0 | H66: =+G66*C66 -> 0 | J66: =+I66*D66 -> 0 | M66: =+F66+H66+J66 -> 0
A67: =+'SERVICIO FAENA'!E68 -> 46062 | B67: =+'SERVICIO FAENA'!A68 -> 66 | F67: =+E67*C67 -> 0 | H67: =+G67*C67 -> 0 | J67: =+I67*D67 -> 0 | M67: =+F67+H67+J67 -> 0
A68: =+'SERVICIO FAENA'!E69 -> 46062 | B68: =+'SERVICIO FAENA'!A69 -> 67 | F68: =+E68*C68 -> 0 | H68: =+G68*C68 -> 0 | J68: =+I68*D68 -> 0 | M68: =+F68+H68+J68 -> 0
A69: =+'SERVICIO FAENA'!E70 -> 46063 | B69: =+'SERVICIO FAENA'!A70 -> 68 | C69: 40 | D69: 40 | E69: 3060 | F69: =+E69*C69 -> 122400 | G69: 1200 | H69: =+G69*C69 -> 48000 | I69: 900 | J69: =+I69*D69 -> 36000 | M69: =+F69+H69+J69 -> 206400
A70: =+'SERVICIO FAENA'!E71 -> 46063 | B70: =+'SERVICIO FAENA'!A71 -> 69 | F70: =+E70*C70 -> 0 | H70: =+G70*C70 -> 0 | J70: =+I70*D70 -> 0 | M70: =+F70+H70+J70 -> 0
A71: =+'SERVICIO FAENA'!E72 -> 46065 | B71: =+'SERVICIO FAENA'!A72 -> 70 | C71: 40 | D71: 40 | E71: 2020 | F71: =+E71*C71 -> 80800 | G71: 1000 | H71: =+G71*C71 -> 40000 | I71: 840 | J71: =+I71*D71 -> 33600 | M71: =+F71+H71+J71 -> 154400
A72: =+'SERVICIO FAENA'!E73 -> 46065 | B72: =+'SERVICIO FAENA'!A73 -> 71 | F72: =+E72*C72 -> 0 | H72: =+G72*C72 -> 0 | J72: =+I72*D72 -> 0 | M72: =+F72+H72+J72 -> 0
A73: =+'SERVICIO FAENA'!E74 -> 46065 | B73: =+'SERVICIO FAENA'!A74 -> 72 | F73: =+E73*C73 -> 0 | H73: =+G73*C73 -> 0 | J73: =+I73*D73 -> 0 | M73: =+F73+H73+J73 -> 0
A74: =+'SERVICIO FAENA'!E75 -> 46065 | B74: =+'SERVICIO FAENA'!A75 -> 73 | F74: =+E74*C74 -> 0 | H74: =+G74*C74 -> 0 | J74: =+I74*D74 -> 0 | M74: =+F74+H74+J74 -> 0
A75: =+'SERVICIO FAENA'!E76 -> 46071 | B75: =+'SERVICIO FAENA'!A76 -> 74 | C75: 40 | D75: 40 | E75: 1380 | F75: =+E75*C75 -> 55200 | G75: 680 | H75: =+G75*C75 -> 27200 | I75: 380 | J75: =+I75*D75 -> 15200 | M75: =+F75+H75+J75 -> 97600
A76: =+'SERVICIO FAENA'!E77 -> 46071 | B76: =+'SERVICIO FAENA'!A77 -> 75 | F76: =+E76*C76 -> 0 | H76: =+G76*C76 -> 0 | J76: =+I76*D76 -> 0 | M76: =+F76+H76+J76 -> 0
A77: =+'SERVICIO FAENA'!E78 -> 46071 | B77: =+'SERVICIO FAENA'!A78 -> 76 | F77: =+E77*C77 -> 0 | H77: =+G77*C77 -> 0 | J77: =+I77*D77 -> 0 | M77: =+F77+H77+J77 -> 0
A78: =+'SERVICIO FAENA'!E79 -> 46071 | B78: =+'SERVICIO FAENA'!A79 -> 77 | F78: =+E78*C78 -> 0 | H78: =+G78*C78 -> 0 | J78: =+I78*D78 -> 0 | M78: =+F78+H78+J78 -> 0
A79: =+'SERVICIO FAENA'!E80 -> 46073 | B79: =+'SERVICIO FAENA'!A80 -> 78 | C79: 40 | D79: 40 | E79: 2980 | F79: =+E79*C79 -> 119200 | G79: 1400 | H79: =+G79*C79 -> 56000 | I79: 880 | J79: =+I79*D79 -> 35200 | M79: =+F79+H79+J79 -> 210400
A80: =+'SERVICIO FAENA'!E81 -> 46073 | B80: =+'SERVICIO FAENA'!A81 -> 79 | F80: =+E80*C80 -> 0 | H80: =+G80*C80 -> 0 | J80: =+I80*D80 -> 0 | M80: =+F80+H80+J80 -> 0
A81: =+'SERVICIO FAENA'!E82 -> 46073 | B81: =+'SERVICIO FAENA'!A82 -> 80 | F81: =+E81*C81 -> 0 | H81: =+G81*C81 -> 0 | J81: =+I81*D81 -> 0 | M81: =+F81+H81+J81 -> 0
A82: =+'SERVICIO FAENA'!E83 -> 46073 | B82: =+'SERVICIO FAENA'!A83 -> 81 | F82: =+E82*C82 -> 0 | H82: =+G82*C82 -> 0 | J82: =+I82*D82 -> 0 | M82: =+F82+H82+J82 -> 0
A83: =+'SERVICIO FAENA'!E84 -> 46073 | B83: =+'SERVICIO FAENA'!A84 -> 82 | F83: =+E83*C83 -> 0 | H83: =+G83*C83 -> 0 | J83: =+I83*D83 -> 0 | M83: =+F83+H83+J83 -> 0
A84: =+'SERVICIO FAENA'!E85 -> 46073 | B84: =+'SERVICIO FAENA'!A85 -> 83 | F84: =+E84*C84 -> 0 | H84: =+G84*C84 -> 0 | J84: =+I84*D84 -> 0 | M84: =+F84+H84+J84 -> 0
A85: =+'SERVICIO FAENA'!E86 -> 46076 | B85: =+'SERVICIO FAENA'!A86 -> 84 | C85: 40 | D85: 40 | E85: 1380 | F85: =+E85*C85 -> 55200 | G85: 580 | H85: =+G85*C85 -> 23200 | I85: 300 | J85: =+I85*D85 -> 12000 | M85: =+F85+H85+J85 -> 90400
A86: =+'SERVICIO FAENA'!E87 -> 46076 | B86: =+'SERVICIO FAENA'!A87 -> 85 | F86: =+E86*C86 -> 0 | H86: =+G86*C86 -> 0 | J86: =+I86*D86 -> 0 | M86: =+F86+H86+J86 -> 0
A87: =+'SERVICIO FAENA'!E88 -> 46077 | B87: =+'SERVICIO FAENA'!A88 -> 86 | C87: 40 | D87: 40 | E87: 3160 | F87: =+E87*C87 -> 126400 | G87: 1160 | H87: =+G87*C87 -> 46400 | I87: 980 | J87: =+I87*D87 -> 39200 | M87: =+F87+H87+J87 -> 212000
A88: =+'SERVICIO FAENA'!E89 -> 46077 | B88: =+'SERVICIO FAENA'!A89 -> 87 | F88: =+E88*C88 -> 0 | H88: =+G88*C88 -> 0 | J88: =+I88*D88 -> 0 | M88: =+F88+H88+J88 -> 0
A89: =+'SERVICIO FAENA'!E90 -> 46078 | B89: =+'SERVICIO FAENA'!A90 -> 88 | C89: 40 | D89: 40 | E89: 740 | F89: =+E89*C89 -> 29600 | G89: 400 | H89: =+G89*C89 -> 16000 | I89: 260 | J89: =+I89*D89 -> 10400 | M89: =+F89+H89+J89 -> 56000
A90: =+'SERVICIO FAENA'!E91 -> 46078 | B90: =+'SERVICIO FAENA'!A91 -> 89 | F90: =+E90*C90 -> 0 | H90: =+G90*C90 -> 0 | J90: =+I90*D90 -> 0 | M90: =+F90+H90+J90 -> 0
A91: =+'SERVICIO FAENA'!E92 -> 46078 | B91: =+'SERVICIO FAENA'!A92 -> 90 | F91: =+E91*C91 -> 0 | H91: =+G91*C91 -> 0 | J91: =+I91*D91 -> 0 | M91: =+F91+H91+J91 -> 0
A92: =+'SERVICIO FAENA'!E93 -> 46080 | B92: =+'SERVICIO FAENA'!A93 -> 91 | C92: 40 | D92: 40 | E92: 3280 | F92: =+E92*C92 -> 131200 | G92: 1380 | H92: =+G92*C92 -> 55200 | I92: 780 | J92: =+I92*D92 -> 31200 | M92: =+F92+H92+J92 -> 217600
A93: =+'SERVICIO FAENA'!E94 -> 46080 | B93: =+'SERVICIO FAENA'!A94 -> 92 | F93: =+E93*C93 -> 0 | H93: =+G93*C93 -> 0 | J93: =+I93*D93 -> 0 | M93: =+F93+H93+J93 -> 0
A94: =+'SERVICIO FAENA'!E95 -> 46080 | B94: =+'SERVICIO FAENA'!A95 -> 93 | F94: =+E94*C94 -> 0 | H94: =+G94*C94 -> 0 | J94: =+I94*D94 -> 0 | M94: =+F94+H94+J94 -> 0
A95: =+'SERVICIO FAENA'!E96 -> 46080 | B95: =+'SERVICIO FAENA'!A96 -> 94 | F95: =+E95*C95 -> 0 | H95: =+G95*C95 -> 0 | J95: =+I95*D95 -> 0 | M95: =+F95+H95+J95 -> 0
A96: =+'SERVICIO FAENA'!E97 -> 46080 | B96: =+'SERVICIO FAENA'!A97 -> 95 | F96: =+E96*C96 -> 0 | H96: =+G96*C96 -> 0 | J96: =+I96*D96 -> 0 | M96: =+F96+H96+J96 -> 0
A97: =+'SERVICIO FAENA'!E98 -> 46080 | B97: =+'SERVICIO FAENA'!A98 -> 96 | F97: =+E97*C97 -> 0 | H97: =+G97*C97 -> 0 | J97: =+I97*D97 -> 0 | M97: =+F97+H97+J97 -> 0
A98: =+'SERVICIO FAENA'!E99 -> 46083 | B98: =+'SERVICIO FAENA'!A99 -> 97 | F98: =+E98*C98 -> 0 | H98: =+G98*C98 -> 0 | J98: =+I98*D98 -> 0 | M98: =+F98+H98+J98 -> 0
A99: =+'SERVICIO FAENA'!E100 -> 46083 | B99: =+'SERVICIO FAENA'!A100 -> 98 | F99: =+E99*C99 -> 0 | H99: =+G99*C99 -> 0 | J99: =+I99*D99 -> 0 | M99: =+F99+H99+J99 -> 0
A100: =+'SERVICIO FAENA'!E101 -> 46083 | B100: =+'SERVICIO FAENA'!A101 -> 99 | F100: =+E100*C100 -> 0 | H100: =+G100*C100 -> 0 | J100: =+I100*D100 -> 0 | M100: =+F100+H100+J100 -> 0
...

Sheet CUEROS
A1: FECHA FAENA | B1: Nº TROPAS | C1: UNIDADES | D1: BUENOS | E1: CORTADO | F1: SALIDA CORTADO | G1: SALIDA BUENO | H1: STOCK | I1: KG TOTAL | J1: $ / UNIDAD +10.5 IVA | K1: $ / KG +10.5 IVA | L1: FACTURA Nº | M1: FECHA | N1: MONTO TOTAL | O1: FECHA PAGO | P1: MONTO DEPOSITADO | Q1: ESTADO PAG. | R1: OBSERVACIONES
D2: 1643 | E2: 137 | H2: =+D2+E2 -> 1780
A3: TOTALES | C3: =+SUM(C4:C90) -> 1702 | D3: =+SUM(D4:D808) -> 1055 | E3: =+SUM(E4:E808) -> 16 | G3: 1100 | H3: =H2-(F3+G3)+H54+H55+H56+H57+H58 -> 1751
A4: =+'SERVICIO FAENA'!E3 -> 46024 | B4: =+'SERVICIO FAENA'!A3 -> 1 | C4: =+'SERVICIO FAENA'!C3 -> 15 | D4: 13 | E4: 2 | H4: =+D4+E4 -> 15 | J4: 0 | K4: 0 | N4: =+K4*I4 -> 0 | P4: 0 | Q4: =+P4-N4 -> 0
A5: =+'SERVICIO FAENA'!E4 -> 46024 | B5: =+'SERVICIO FAENA'!A4 -> 2 | C5: =+'SERVICIO FAENA'!C4 -> 43 | D5: 40 | E5: 3 | H5: =+D5+E5 -> 43 | J5: 0 | K5: 0 | N5: =+K5*I5 -> 0 | P5: 0 | Q5: =+P5-N5 -> 0
A6: =+'SERVICIO FAENA'!E5 -> 46027 | B6: =+'SERVICIO FAENA'!A5 -> 3 | C6: =+'SERVICIO FAENA'!C5 -> 40 | D6: 40 | E6: 0 | H6: =+D6+E6 -> 40 | J6: 0 | K6: 0 | N6: =+K6*I6 -> 0 | P6: 0 | Q6: =+P6-N6 -> 0
A7: =+'SERVICIO FAENA'!E6 -> 46027 | B7: =+'SERVICIO FAENA'!A6 -> 4 | C7: =+'SERVICIO FAENA'!C6 -> 25 | D7: 25 | E7: 0 | H7: =+D7+E7 -> 25 | J7: 0 | K7: 0 | N7: =+K7*I7 -> 0 | P7: 0 | Q7: =+P7-N7 -> 0
A8: =+'SERVICIO FAENA'!E7 -> 46027 | B8: =+'SERVICIO FAENA'!A7 -> 5 | C8: =+'SERVICIO FAENA'!C7 -> 30 | D8: 30 | E8: 0 | H8: =+D8+E8 -> 30 | J8: 0 | K8: 0 | N8: =+K8*I8 -> 0 | P8: 0 | Q8: =+P8-N8 -> 0
A9: =+'SERVICIO FAENA'!E8 -> 46028 | B9: =+'SERVICIO FAENA'!A8 -> 6 | C9: =+'SERVICIO FAENA'!C8 -> 15 | D9: 15 | E9: 0 | H9: =+D9+E9 -> 15 | J9: 0 | K9: 0 | N9: =+K9*I9 -> 0 | P9: 0 | Q9: =+P9-N9 -> 0
A10: =+'SERVICIO FAENA'!E9 -> 46028 | B10: =+'SERVICIO FAENA'!A9 -> 7 | C10: =+'SERVICIO FAENA'!C9 -> 35 | D10: 35 | E10: 0 | H10: =+D10+E10 -> 35 | J10: 0 | K10: 0 | N10: =+K10*I10 -> 0 | P10: 0 | Q10: =+P10-N10 -> 0
A11: =+'SERVICIO FAENA'!E10 -> 46028 | B11: =+'SERVICIO FAENA'!A10 -> 8 | C11: =+'SERVICIO FAENA'!C10 -> 5 | D11: 5 | E11: 0 | H11: =+D11+E11 -> 5 | J11: 0 | K11: 0 | N11: =+K11*I11 -> 0 | P11: 0 | Q11: =+P11-N11 -> 0
A12: =+'SERVICIO FAENA'!E11 -> 46028 | B12: =+'SERVICIO FAENA'!A11 -> 9 | C12: =+'SERVICIO FAENA'!C11 -> 10 | D12: 10 | E12: 0 | H12: =+D12+E12 -> 10 | J12: 0 | K12: 0 | N12: =+K12*I12 -> 0 | P12: 0 | Q12: =+P12-N12 -> 0
A13: =+'SERVICIO FAENA'!E12 -> 46028 | B13: =+'SERVICIO FAENA'!A12 -> 10 | C13: =+'SERVICIO FAENA'!C12 -> 15 | D13: 15 | E13: 0 | H13: =+D13+E13 -> 15 | J13: 0 | K13: 0 | N13: =+K13*I13 -> 0 | P13: 0 | Q13: =+P13-N13 -> 0
A14: =+'SERVICIO FAENA'!E13 -> 46029 | B14: =+'SERVICIO FAENA'!A13 -> 11 | C14: =+'SERVICIO FAENA'!C13 -> 20 | D14: 19 | E14: 1 | H14: =+D14+E14 -> 20 | J14: 0 | K14: 0 | N14: =+K14*I14 -> 0 | P14: 0 | Q14: =+P14-N14 -> 0
A15: =+'SERVICIO FAENA'!E14 -> 46029 | B15: =+'SERVICIO FAENA'!A14 -> 12 | C15: =+'SERVICIO FAENA'!C14 -> 3 | D15: 0 | E15: 0 | H15: =+D15+E15 -> 0 | J15: 0 | K15: 0 | N15: =+K15*I15 -> 0 | P15: 0 | Q15: =+P15-N15 -> 0
... A53: =+'SERVICIO FAENA'!E52 -> 46052 | B53: =+'SERVICIO FAENA'!A52 -> 50 | C53: =+'SERVICIO FAENA'!C52 -> 2 | D53: 2 | E53: 0 | H53: =+D53+E53 -> 2 | J53: 0 | K53: 0 | N53: =+K53*I53 -> 0 | P53: 0 | Q53: =+P53-N53 -> 0
A54: TOTAL | F54: =SUM(F13:F53) -> 0 | H54: =SUM(H4:H53) -> 961
A55: =+'SERVICIO FAENA'!E53 -> 46055 | B55: =+'SERVICIO FAENA'!A53 -> 51 | C55: =+'SERVICIO FAENA'!C53 -> 42 | D55: 42 | E55: 0 | H55: =+D55+E55 -> 42 | J55: 0 | K55: 0 | N55: =+K55*I55 -> 0 | P55: 0 | Q55: =+P55-N55 -> 0
A56: =+'SERVICIO FAENA'!E54 -> 46055 | B56: =+'SERVICIO FAENA'!A54 -> 52 | C56: =+'SERVICIO FAENA'!C54 -> 18 | D56: 18 | E56: 0 | H56: =+D56+E56 -> 18 | J56: 0 | K56: 0 | N56: =+K56*I56 -> 0 | P56: 0 | Q56: =+P56-N56 -> 0
A57: =+'SERVICIO FAENA'!E55 -> 46057 | B57: =+'SERVICIO FAENA'!A55 -> 53 | C57: =+'SERVICIO FAENA'!C55 -> 17 | H57: =+D57+E57 -> 0 | J57: 0 | K57: 0 | N57: =+K57*I57 -> 0 | P57: 0 | Q57: =+P57-N57 -> 0
A58: =+'SERVICIO FAENA'!E56 -> 46056 | B58: =+'SERVICIO FAENA'!A56 -> 54 | C58: =+'SERVICIO FAENA'!C56 -> 50 | D58: 49 | E58: 1 | H58: =+D58+E58 -> 50 | J58: 0 | K58: 0 | N58: =+K58*I58 -> 0 | P58: 0 | Q58: =+P58-N58 -> 0
A59: =+'SERVICIO FAENA'!E57 -> 46057 | B59: =+'SERVICIO FAENA'!A57 -> 55 | C59: =+'SERVICIO FAENA'!C57 -> 10 | H59: =+D59+E59 -> 0 | J59: 0 | K59: 0 | N59: =+K59*I59 -> 0 | P59: 0 | Q59: =+P59-N59 -> 0
A60: =+'SERVICIO FAENA'!E58 -> 46058 | B60: =+'SERVICIO FAENA'!A58 -> 56 | C60: =+'SERVICIO FAENA'!C58 -> 15 | H60: =+D60+E60 -> 0 | J60: 0 | K60: 0 | N60: =+K60*I60 -> 0 | P60: 0 | Q60: =+P60-N60 -> 0
A61: =+'SERVICIO FAENA'!E59 -> 46057 | B61: =+'SERVICIO FAENA'!A59 -> 57 | C61: =+'SERVICIO FAENA'!C59 -> 5 | H61: =+D61+E61 -> 0 | J61: 0 | K61: 0 | N61: =+K61*I61 -> 0 | P61: 0 | Q61: =+P61-N61 -> 0
A62: =+'SERVICIO FAENA'!E60 -> 46058 | B62: =+'SERVICIO FAENA'!A60 -> 58 | C62: =+'SERVICIO FAENA'!C60 -> 10 | H62: =+D62+E62 -> 0 | J62: 0 | K62: 0 | N62: =+K62*I62 -> 0 | P62: 0 | Q62: =+P62-N62 -> 0
A63: =+'SERVICIO FAENA'!E61 -> 46059 | B63: =+'SERVICIO FAENA'!A61 -> 59 | C63: =+'SERVICIO FAENA'!C61 -> 20 | H63: =+D63+E63 -> 0 | J63: 0 | K63: 0 | N63: =+K63*I63 -> 0 | P63: 0 | Q63: =+P63-N63 -> 0
A64: =+'SERVICIO FAENA'!E62 -> 46059 | B64: =+'SERVICIO FAENA'!A62 -> 60 | C64: =+'SERVICIO FAENA'!C62 -> 28 | H64: =+D64+E64 -> 0 | J64: 0 | K64: 0 | N64: =+K64*I64 -> 0 | P64: 0 | Q64: =+P64-N64 -> 0
A65: =+'SERVICIO FAENA'!E63 -> 46059 | B65: =+'SERVICIO FAENA'!A63 -> 61 | C65: =+'SERVICIO FAENA'!C63 -> 20 | H65: =+D65+E65 -> 0 | J65: 0 | K65: 0 | N65: =+K65*I65 -> 0 | P65: 0 | Q65: =+P65-N65 -> 0
A66: =+'SERVICIO FAENA'!E64 -> 46059 | B66: =+'SERVICIO FAENA'!A64 -> 62 | C66: =+'SERVICIO FAENA'!C64 -> 1 | H66: =+D66+E66 -> 0 | J66: 0 | K66: 0 | N66: =+K66*I66 -> 0 | P66: 0 | Q66: =+P66-N66 -> 0
A67: =+'SERVICIO FAENA'!E65 -> 46062 | B67: =+'SERVICIO FAENA'!A65 -> 63 | C67: =+'SERVICIO FAENA'!C65 -> 8 | H67: =+D67+E67 -> 0 | J67: 0 | K67: 0 | N67: =+K67*I67 -> 0 | P67: 0 | Q67: =+P67-N67 -> 0
A68: =+'SERVICIO FAENA'!E66 -> 46062 | B68: =+'SERVICIO FAENA'!A66 -> 64 | C68: =+'SERVICIO FAENA'!C66 -> 3 | H68: =+D68+E68 -> 0 | J68: 0 | K68: 0 | N68: =+K68*I68 -> 0 | P68: 0 | Q68: =+P68-N68 -> 0
A69: =+'SERVICIO FAENA'!E67 -> 46062 | B69: =+'SERVICIO FAENA'!A67 -> 65 | C69: =+'SERVICIO FAENA'!C67 -> 4 | H69: =+D69+E69 -> 0 | J69: 0 | K69: 0 | N69: =+K69*I69 -> 0 | P69: 0 | Q69: =+P69-N69 -> 0
A70: =+'SERVICIO FAENA'!E68 -> 46062 | B70: =+'SERVICIO FAENA'!A68 -> 66 | C70: =+'SERVICIO FAENA'!C68 -> 21 | H70: =+D70+E70 -> 0 | J70: 0 | K70: 0 | N70: =+K70*I70 -> 0 | P70: 0 | Q70: =+P70-N70 -> 0
... A785: =+'SERVICIO FAENA'!E783 -> 0 | B785: =+'SERVICIO FAENA'!A783 -> 0 | C785: =+'SERVICIO FAENA'!C783 -> 0 | H785: =+D785+E785 -> 0 | J785: 0 | K785: 0 | N785: =+K785*I785 -> 0 | P785: 0 | Q785: =+P785-N785 -> 0

Sheet GRASA DREASING
A1: FECHA FAENA | B1: Nº TROPAS | C1: KG TOTAL | D1: $ / KG | E1: FACTURA Nº | F1: FECHA | G1: MONTO TOTAL SIN IVA | H1: FECHA PAGO | I1: MONTO DEPOSITADO | J1: ESTADO PAG. | K1: OBSERVACIONES
A2: =+RENDERING!A2 -> 46024 | B2: =+RENDERING!B2 -> 1 | D2: 0 | G2: =+D2*C2 -> 0 | I2: 0 | J2: =+I2-G2 -> 0
A3: =+RENDERING!A3 -> 46024 | B3: =+RENDERING!B3 -> 2 | D3: 0 | G3: =+D3*C3 -> 0 | I3: 0 | J3: =+I3-G3 -> 0
A4: =+RENDERING!A4 -> 46027 | B4: =+RENDERING!B4 -> 3 | D4: 0 | G4: =+D4*C4 -> 0 | I4: 0 | J4: =+I4-G4 -> 0
A5: =+RENDERING!A5 -> 46027 | B5: =+RENDERING!B5 -> 4 | D5: 0 | G5: =+D5*C5 -> 0 | I5: 0 | J5: =+I5-G5 -> 0
A6: =+RENDERING!A6 -> 46027 | B6: =+RENDERING!B6 -> 5 | D6: 0 | G6: =+D6*C6 -> 0 | I6: 0 | J6: =+I6-G6 -> 0
A7: =+RENDERING!A7 -> 46028 | B7: =+RENDERING!B7 -> 6 | D7: 0 | G7: =+D7*C7 -> 0 | I7: 0 | J7: =+I7-G7 -> 0
A8: =+RENDERING!A8 -> 46028 | B8: =+RENDERING!B8 -> 7 | D8: 0 | G8: =+D8*C8 -> 0 | I8: 0 | J8: =+I8-G8 -> 0
A9: =+RENDERING!A9 -> 46028 | B9: =+RENDERING!B9 -> 8 | D9: 0 | G9: =+D9*C9 -> 0 | I9: 0 | J9: =+I9-G9 -> 0
A10: =+RENDERING!A10 -> 46028 | B10: =+RENDERING!B10 -> 9 | D10: 0 | G10: =+D10*C10 -> 0 | I10: 0 | J10: =+I10-G10 -> 0
A11: =+RENDERING!A11 -> 46028 | B11: =+RENDERING!B11 -> 10 | D11: 0 | G11: =+D11*C11 -> 0 | I11: 0 | J11: =+I11-G11 -> 0
A12: =+RENDERING!A12 -> 46029 | B12: =+RENDERING!B12 -> 11 | D12: 0 | G12: =+D12*C12 -> 0 | I12: 0 | J12: =+I12-G12 -> 0
A13: =+RENDERING!A13 -> 46029 | B13: =+RENDERING!B13 -> 12 | D13: 0 | G13: =+D13*C13 -> 0 | I13: 0 | J13: =+I13-G13 -> 0
... A23: =+RENDERING!A23 -> 46035 | B23: =+RENDERING!B23 -> 22 | D23: 0 | G23: =+D23*C23 -> 0 | I23: 0 | J23: =+I23-G23 -> 0

Sheet MERCADO INTERNO
D1: ARTICULOS COMERCIALIZADOS | AD1: AREA DE VENTA
A2: Nº TROPAS | B2: FECHA FAENA | C2: Cantidad Animales | D2: Lavadito (Chinchulin) | AD2: FACTURA | AG2: TOTAL $ FACTURA S/IVA | AH2: TOTAL $ FACTURA C/IVA | AI2: FECHA DE PAGO | AJ2: MONTO DEPOSITADO | AK2: ESTADO
D3: kg | E3: $/kg s/IVA | F3: kg | G3: $/kg s/IVA | H3: kg | I3: $/kg s/IVA | J3: kg | K3: $/kg s/IVA | L3: kg | M3: $/kg s/IVA | N3: kg | O3: $/kg s/IVA | P3: kg | Q3: $/kg s/IVA | R3: kg | S3: $/kg s/IVA | T3: kg | U3: $/kg s/IVA | V3: kg | W3: $/kg s/IVA | X3: kg | Y3: $/kg s/IVA | Z3: kg | AA3: $/kg s/IVA | AB3: kg | AC3: $/kg s/IVA | AD3: Nº | AE3: Fecha | AF3: Titular
A4: =+'SERVICIO FAENA'!A3 -> 1 | B4: =+'SERVICIO FAENA'!E3 -> 46024 | C4: =+'SERVICIO FAENA'!C3 -> 15 | AG4: =+D4*E4 -> 0 | AH4: =+AG4*1.105 -> 0 | AK4: =+AJ4-AH4 -> 0
A5: =+'SERVICIO FAENA'!A4 -> 2 | B5: =+'SERVICIO FAENA'!E4 -> 46024 | C5: =+'SERVICIO FAENA'!C4 -> 43 | AG5: =+D5*E5 -> 0 | AH5: =+AG5*1.105 -> 0 | AK5: =+AJ5-AH5 -> 0
A6: =+'SERVICIO FAENA'!A5 -> 3 | B6: =+'SERVICIO FAENA'!E5 -> 46027 | C6: =+'SERVICIO FAENA'!C5 -> 40 | AG6: =+D6*E6 -> 0 | AH6: =+AG6*1.105 -> 0 | AK6: =+AJ6-AH6 -> 0
A7: =+'SERVICIO FAENA'!A6 -> 4 | B7: =+'SERVICIO FAENA'!E6 -> 46027 | C7: =+'SERVICIO FAENA'!C6 -> 25 | AG7: =+D7*E7 -> 0 | AH7: =+AG7*1.105 -> 0 | AK7: =+AJ7-AH7 -> 0
A8: =+'SERVICIO FAENA'!A7 -> 5 | B8: =+'SERVICIO FAENA'!E7 -> 46027 | C8: =+'SERVICIO FAENA'!C7 -> 30 | AG8: =+D8*E8 -> 0 | AH8: =+AG8*1.105 -> 0 | AK8: =+AJ8-AH8 -> 0
A9: =+'SERVICIO FAENA'!A8 -> 6 | B9: =+'SERVICIO FAENA'!E8 -> 46028 | C9: =+'SERVICIO FAENA'!C8 -> 15 | AG9: =+D9*E9 -> 0 | AH9: =+AG9*1.105 -> 0 | AK9: =+AJ9-AH9 -> 0
A10: =+'SERVICIO FAENA'!A9 -> 7 | B10: =+'SERVICIO FAENA'!E9 -> 46028 | C10: =+'SERVICIO FAENA'!C9 -> 35 | AG10: =+D10*E10 -> 0 | AH10: =+AG10*1.105 -> 0 | AK10: =+AJ10-AH10 -> 0
A11: =+'SERVICIO FAENA'!A10 -> 8 | B11: =+'SERVICIO FAENA'!E10 -> 46028 | C11: =+'SERVICIO FAENA'!C10 -> 5 | AG11: =+D11*E11 -> 0 | AH11: =+AG11*1.105 -> 0 | AK11: =+AJ11-AH11 -> 0
A12: =+'SERVICIO FAENA'!A11 -> 9 | B12: =+'SERVICIO FAENA'!E11 -> 46028 | C12: =+'SERVICIO FAENA'!C11 -> 10 | AG12: =+D12*E12 -> 0 | AH12: =+AG12*1.105 -> 0 | AK12: =+AJ12-AH12 -> 0
A13: =+'SERVICIO FAENA'!A12 -> 10 | B13: =+'SERVICIO FAENA'!E12 -> 46028 | C13: =+'SERVICIO FAENA'!C12 -> 15 | AG13: =+D13*E13 -> 0 | AH13: =+AG13*1.105 -> 0 | AK13: =+AJ13-AH13 -> 0
A14: =+'SERVICIO FAENA'!A13 -> 11 | B14: =+'SERVICIO FAENA'!E13 -> 46029 | C14: =+'SERVICIO FAENA'!C13 -> 20 | AG14: =+D14*E14 -> 0 | AH14: =+AG14*1.105 -> 0 | AK14: =+AJ14-AH14 -> 0
A15: =+'SERVICIO FAENA'!A14 -> 12 | B15: =+'SERVICIO FAENA'!E14 -> 46029 | C15: =+'SERVICIO FAENA'!C14 -> 3 | D15: 79.72 | E15: 3167.42 | AD15: 00007-00000040 | AE15: 46029 | AF15: VIENTOS DEL VALLE | AG15: =+D15*E15 -> 252506.72 | AH15: =+AG15*1.105 -> 279019.93 | AK15: =+AJ15-AH15 -> -279019.93
A16: =+'SERVICIO FAENA'!A15 -> 13 | B16: =+'SERVICIO FAENA'!E15 -> 46029 | C16: =+'SERVICIO FAENA'!C15 -> 40 | D16: =20.56+20.12+20.16+20.18 -> 81.02 | E16: 3167.421 | AD16: 00007-00000041 | AE16: 8 | AF16: VIENTOS DEL VALLE | AG16: =+D16*E16 -> 256624.45 | AH16: =+AG16*1.105 -> 283570.02 | AK16: =+AJ16-AH16 -> -283570.02
A17: =+'SERVICIO FAENA'!A16 -> 14 | B17: =+'SERVICIO FAENA'!E16 -> 46030 | C17: =+'SERVICIO FAENA'!C16 -> 35 | AG17: =+D17*E17 -> 0 | AH17: =+AG17*1.105 -> 0 | AK17: =+AJ17-AH17 -> 0
A18: =+'SERVICIO FAENA'!A17 -> 15 | B18: =+'SERVICIO FAENA'!E17 -> 46031 | C18: =+'SERVICIO FAENA'!C17 -> 46 | AG18: =+D18*E18 -> 0 | AH18: =+AG18*1.105 -> 0 | AK18: =+AJ18-AH18 -> 0
A19: =+'SERVICIO FAENA'!A18 -> 16 | B19: =+'SERVICIO FAENA'!E18 -> 46031 | C19: =+'SERVICIO FAENA'!C18 -> 15 | AG19: =+D19*E19 -> 0 | AH19: =+AG19*1.105 -> 0 | AK19: =+AJ19-AH19 -> 0
A20: =+'SERVICIO FAENA'!A19 -> 17 | B20: =+'SERVICIO FAENA'!E19 -> 46031 | C20: =+'SERVICIO FAENA'!C19 -> 17 | AG20: =+D20*E20 -> 0 | AH20: =+AG20*1.105 -> 0 | AK20: =+AJ20-AH20 -> 0
A21: =+'SERVICIO FAENA'!A20 -> 18 | B21: =+'SERVICIO FAENA'!E20 -> 46034 | C21: =+'SERVICIO FAENA'!C20 -> 43 | AG21: =+D21*E21 -> 0 | AH21: =+AG21*1.105 -> 0 | AK21: =+AJ21-AH21 -> 0
A22: =+'SERVICIO FAENA'!A21 -> 19 | B22: =+'SERVICIO FAENA'!E21 -> 46034 | C22: =+'SERVICIO FAENA'!C21 -> 25 | AG22: =+D22*E22 -> 0 | AH22: =+AG22*1.105 -> 0 | AK22: =+AJ22-AH22 -> 0
A23: =+'SERVICIO FAENA'!A22 -> 20 | B23: =+'SERVICIO FAENA'!E22 -> 46034 | C23: =+'SERVICIO FAENA'!C22 -> 15 | AG23: =+D23*E23 -> 0 | AH23: =+AG23*1.105 -> 0 | AK23: =+AJ23-AH23 -> 0
A24: =+'SERVICIO FAENA'!A23 -> 21 | B24: =+'SERVICIO FAENA'!E23 -> 46035 | C24: =+'SERVICIO FAENA'!C23 -> 8 | AG24: =+D24*E24 -> 0 | AH24: =+AG24*1.105 -> 0 | AK24: =+AJ24-AH24 -> 0
A25: =+'SERVICIO FAENA'!A24 -> 22 | B25: =+'SERVICIO FAENA'!E24 -> 46035 | C25: =+'SERVICIO FAENA'!C24 -> 7 | AG25: =+D25*E25 -> 0 | AH25: =+AG25*1.105 -> 0 | AK25: =+AJ25-AH25 -> 0
A26: =+'SERVICIO FAENA'!A25 -> 23 | B26: =+'SERVICIO FAENA'!E25 -> 46035 | C26: =+'SERVICIO FAENA'!C25 -> 5 | AG26: =+D26*E26 -> 0 | AH26: =+AG26*1.105 -> 0 | AK26: =+AJ26-AH26 -> 0
A27: =+'SERVICIO FAENA'!A26 -> 24 | B27: =+'SERVICIO FAENA'!E26 -> 46036 | C27: =+'SERVICIO FAENA'!C26 -> 30 | AG27: =+D27*E27 -> 0 | AH27: =+AG27*1.105 -> 0 | AK27: =+AJ27-AH27 -> 0
A28: =+'SERVICIO FAENA'!A27 -> 25 | B28: =+'SERVICIO FAENA'!E27 -> 46036 | C28: =+'SERVICIO FAENA'!C27 -> 6 | AG28: =+D28*E28 -> 0 | AH28: =+AG28*1.105 -> 0 | AK28: =+AJ28-AH28 -> 0
... A70: =+'SERVICIO FAENA'!A69 -> 67 | B70: =+'SERVICIO FAENA'!E69 -> 46062 | C70: =+'SERVICIO FAENA'!C69 -> 45 | AG70: =+D70*E70 -> 0 | AH70: =+AG70*1.105 -> 0 | AK70: =+AJ70-AH70 -> 0
A71: =+'SERVICIO FAENA'!A70 -> 68 | B71: =+'SERVICIO FAENA'!E70 -> 46063 | C71: =+'SERVICIO FAENA'!C70 -> 18 | D71: 101.94 | E71: 3167.42 | AD71: 00007-00000048 | AE71: 46069 | AF71: VIENTOS DEL VALLE | AG71: =+D71*E71 -> 322886.79 | AH71: =+AG71*1.105 -> 356789.91 | AK71: =+AJ71-AH71 -> -356789.91
A72: =+'SERVICIO FAENA'!A71 -> 69 | B72: =+'SERVICIO FAENA'!E71 -> 46063 | C72: =+'SERVICIO FAENA'!C71 -> 50 | AG72: =+D72*E72 -> 0 | AH72: =+AG72*1.105 -> 0 | AK72: =+AJ72-AH72 -> 0
A73: =+'SERVICIO FAENA'!A72 -> 70 | B73: =+'SERVICIO FAENA'!E72 -> 46065 | C73: =+'SERVICIO FAENA'!C72 -> 5 | AG73: =+D73*E73 -> 0 | AH73: =+AG73*1.105 -> 0 | AK73: =+AJ73-AH73 -> 0
A74: =+'SERVICIO FAENA'!A73 -> 71 | B74: =+'SERVICIO FAENA'!E73 -> 46065 | C74: =+'SERVICIO FAENA'!C73 -> 25 | AG74: =+D74*E74 -> 0 | AH74: =+AG74*1.105 -> 0 | AK74: =+AJ74-AH74 -> 0
A75: =+'SERVICIO FAENA'!A74 -> 72 | B75: =+'SERVICIO FAENA'!E74 -> 46065 | C75: =+'SERVICIO FAENA'!C74 -> 20 | AG75: =+D75*E75 -> 0 | AH75: =+AG75*1.105 -> 0 | AK75: =+AJ75-AH75 -> 0
A76: =+'SERVICIO FAENA'!A75 -> 73 | B76: =+'SERVICIO FAENA'!E75 -> 46065 | C76: =+'SERVICIO FAENA'!C75 -> 15 | AG76: =+D76*E76 -> 0 | AH76: =+AG76*1.105 -> 0 | AK76: =+AJ76-AH76 -> 0
A77: =+'SERVICIO FAENA'!A76 -> 74 | B77: =+'SERVICIO FAENA'!E76 -> 46071 | C77: =+'SERVICIO FAENA'!C76 -> 10 | AG77: =+D77*E77 -> 0 | AH77: =+AG77*1.105 -> 0 | AK77: =+AJ77-AH77 -> 0
A78: =+'SERVICIO FAENA'!A77 -> 75 | B78: =+'SERVICIO FAENA'!E77 -> 46071 | C78: =+'SERVICIO FAENA'!C77 -> 5 | AG78: =+D78*E78 -> 0 | AH78: =+AG78*1.105 -> 0 | AK78: =+AJ78-AH78 -> 0
A79: =+'SERVICIO FAENA'!A78 -> 76 | B79: =+'SERVICIO FAENA'!E78 -> 46071 | C79: =+'SERVICIO FAENA'!C78 -> 18 | D79: 100.52 | E79: 3484.16 | AD79: 00007-00000053 | AE79: 46079 | AF79: DOS DE FIERRO SA | AG79: =+D79*E79 -> 350227.76 | AH79: =+AG79*1.105 -> 387001.68 | AK79: =+AJ79-AH79 -> -387001.68
A80: =+'SERVICIO FAENA'!A79 -> 77 | B80: =+'SERVICIO FAENA'!E79 -> 46071 | C80: =+'SERVICIO FAENA'!C79 -> 15 | D80: 100.4 | E80: 3167.42 | AD80: 00007-00000051 | AE80: 46079 | AF80: VIENTOS DEL VALLE | AG80: =+D80*E80 -> 318008.97 | AH80: =+AG80*1.105 -> 351399.91 | AK80: =+AJ80-AH80 -> -351399.91
A81: =+'SERVICIO FAENA'!A80 -> 78 | B81: =+'SERVICIO FAENA'!E80 -> 46073 | C81: =+'SERVICIO FAENA'!C80 -> 8 | AG81: =+D81*E81 -> 0 | AH81: =+AG81*1.105 -> 0 | AK81: =+AJ81-AH81 -> 0
A82: =+'SERVICIO FAENA'!A81 -> 79 | B82: =+'SERVICIO FAENA'!E81 -> 46073 | C82: =+'SERVICIO FAENA'!C81 -> 20 | AG82: =+D82*E82 -> 0 | AH82: =+AG82*1.105 -> 0 | AK82: =+AJ82-AH82 -> 0
A83: =+'SERVICIO FAENA'!A82 -> 80 | B83: =+'SERVICIO FAENA'!E82 -> 46073 | C83: =+'SERVICIO FAENA'!C82 -> 21 | AG83: =+D83*E83 -> 0 | AH83: =+AG83*1.105 -> 0 | AK83: =+AJ83-AH83 -> 0
A84: =+'SERVICIO FAENA'!A83 -> 81 | B84: =+'SERVICIO FAENA'!E83 -> 46073 | C84: =+'SERVICIO FAENA'!C83 -> 15 | AG84: =+D84*E84 -> 0 | AH84: =+AG84*1.105 -> 0 | AK84: =+AJ84-AH84 -> 0
A85: =+'SERVICIO FAENA'!A84 -> 82 | B85: =+'SERVICIO FAENA'!E84 -> 46073 | C85: =+'SERVICIO FAENA'!C84 -> 15 | AG85: =+D85*E85 -> 0 | AH85: =+AG85*1.105 -> 0 | AK85: =+AJ85-AH85 -> 0
A86: =+'SERVICIO FAENA'!A85 -> 83 | B86: =+'SERVICIO FAENA'!E85 -> 46073 | C86: =+'SERVICIO FAENA'!C85 -> 15 | AG86: =+D86*E86 -> 0 | AH86: =+AG86*1.105 -> 0 | AK86: =+AJ86-AH86 -> 0
A87: =+'SERVICIO FAENA'!A86 -> 84 | B87: =+'SERVICIO FAENA'!E86 -> 46076 | C87: =+'SERVICIO FAENA'!C86 -> 21 | AG87: =+D87*E87 -> 0 | AH87: =+AG87*1.105 -> 0 | AK87: =+AJ87-AH87 -> 0
A88: =+'SERVICIO FAENA'!A87 -> 85 | B88: =+'SERVICIO FAENA'!E87 -> 46076 | C88: =+'SERVICIO FAENA'!C87 -> 18 | AG88: =+D88*E88 -> 0 | AH88: =+AG88*1.105 -> 0 | AK88: =+AJ88-AH88 -> 0
A89: =+'SERVICIO FAENA'!A88 -> 86 | B89: =+'SERVICIO FAENA'!E88 -> 46077 | C89: =+'SERVICIO FAENA'!C88 -> 50 | AG89: =+D89*E89 -> 0 | AH89: =+AG89*1.105 -> 0 | AK89: =+AJ89-AH89 -> 0
A90: =+'SERVICIO FAENA'!A89 -> 87 | B90: =+'SERVICIO FAENA'!E89 -> 46077 | C90: =+'SERVICIO FAENA'!C89 -> 18 | AG90: =+D90*E90 -> 0 | AH90: =+AG90*1.105 -> 0 | AK90: =+AJ90-AH90 -> 0
A91: =+'SERVICIO FAENA'!A90 -> 88 | B91: =+'SERVICIO FAENA'!E90 -> 46078 | C91: =+'SERVICIO FAENA'!C90 -> 8 | AG91: =+D91*E91 -> 0 | AH91: =+AG91*1.105 -> 0 | AK91: =+AJ91-AH91 -> 0
A92: =+'SERVICIO FAENA'!A91 -> 89 | B92: =+'SERVICIO FAENA'!E91 -> 46078 | C92: =+'SERVICIO FAENA'!C91 -> 7 | AG92: =+D92*E92 -> 0 | AH92: =+AG92*1.105 -> 0 | AK92: =+AJ92-AH92 -> 0
... A343: =+'SERVICIO FAENA'!A342 -> 0 | B343: =+'SERVICIO FAENA'!E342 -> 0 | C343: =+'SERVICIO FAENA'!C342 -> 0 | AG343: =+D343*E343 -> 0 | AH343: =+AG343*1.105 -> 0 | AK343: =+AJ343-AH343 -> 0
